Workbook

Sheet Resumo_DPO 
AE2: 0.5 | AF2: 0.6 | AG2: 0.7
B4: DISTRIBUIDOR XXXXX | G4: H 2025 | M4: Almacén | P4: Entrega | S4: MKTP
B6: PILARES | E6: META | G6: Enviado | I6: 2025 | K6: Disp.% | M6: DIST | N6: 3PL | P6: DIST | Q6: 3PL
B8: Pilar Seguridad | C8: =VLOOKUP(I8,#REF!,4) -> #REF! | E8: 0.73 | I8: =+'Seguridad OK'!$R$2 -> 0 | K8: =ABS(I8-G8) -> 0 | M8: =+'Seguridad OK'!M2 -> 0 | N8: 0.7 | P8: =+'Seguridad OK'!P2 -> 0 | Q8: 0.57 | V8: 2
B9: Pilar Gente | C9: =VLOOKUP(I9,#REF!,4) -> #REF! | E9: 0.57 | I9: =+'Gente OK'!$R$2 -> 0 | K9: =ABS(I9-G9) -> 0 | M9: =+'Gente OK'!M2 -> 0 | N9: 0.7 | P9: =+'Gente OK'!P2 -> 0 | Q9: 0.57
B10: Pilar Gestión | C10: =VLOOKUP(I10,#REF!,4) -> #REF! | E10: 0.57 | I10: =+'Gestión OK'!$R$2 -> 0 | K10: =ABS(I10-G10) -> 0 | M10: =+'Gestión OK'!M2 -> 0 | N10: 0.7 | P10: =+'Gestión OK'!P2 -> 0 | Q10: 0.57 | AE10: Certificado
B11: Pilar Entrega | C11: =VLOOKUP(I11,#REF!,4) -> #REF! | E11: 0.64 | I11: =+'Entrega OK'!$R$2 -> 0 | K11: =ABS(I11-G11) -> 0 | M11: =+'Entrega OK'!M2 -> N/A | N11: 0.7 | P11: =+'Entrega OK'!P2 -> 0 | Q11: 0.57
B12: Pilar Flota | C12: =VLOOKUP(I12,#REF!,4) -> #REF! | E12: 0.64 | I12: =+'Flota OK'!$R$2 -> 0 | K12: =ABS(I12-G12) -> 0 | M12: =+'Flota OK'!M2 -> 0 | N12: 0.7 | P12: =+'Flota OK'!P2 -> 0 | Q12: 0.57
B13: Pilar Almacén | C13: =VLOOKUP(I13,#REF!,4) -> #REF! | E13: 0.64 | I13: =+'Almacén OK'!$O$2 -> 0 | K13: =ABS(I13-G13) -> 0 | M13: =+'Almacén OK'!L2 -> 0 | N13: 0.7 | P13: N/A | Q13: 0.57 | AE13: =IF(AND(I8<$AG$2,I8>=AF2,I9>=$AF$2),"Certificado","Outro") -> Outro
B14: Pilar Planeamiento | C14: =VLOOKUP(I14,#REF!,4) -> #REF! | E14: 0.64 | I14: =+'Planeamiento OK'!$R$2 -> 0 | K14: =ABS(I14-G14) -> 0 | M14: =+'Planeamiento OK'!M2 -> 0 | N14: 0.7 | P14: =+'Planeamiento OK'!P2 -> 0 | Q14: 0.57
B16: TOTAL | E16: 0.64 | G16: =AVERAGE(G8:G14) -> #DIV/0! | I16: =AVERAGE(I8:I14) -> 0 | K16: =AVERAGE(K8:K14) -> 0 | M16: =IFERROR(AVERAGE(M8:M14),"") -> 0 | N16: =IFERROR(AVERAGE(N8:N14),"") -> 0.7 | P16: =IFERROR(AVERAGE(P8:P14),"") -> 0 | Q16: =IFERROR(AVERAGE(Q8:Q14),"") -> 0.57 | S16: =IFERROR(AVERAGE(S8:S14),"") | U16: SKPIs | W16: 5

Sheet Seguridad OK
A1: KEY | B1: Bloque | C1: N° Preg | D1: Pregunta | E1: Mandatorio | F1: Peso | G1: Guía | H1: Requirimiento | I1: Puntaje | J1: Cómo verificar | K1: Comments | L1: WH - DDC | M1: WH - ABI | N1: ="WH - "&#REF! -> #REF! | O1: DEL - DDC | P1: DEL - ABI | Q1: DEL - 3PL | R1: DDC
B2: Total Pillar Score (Average of Question scores) | L2: =IF(COUNTBLANK(L3:L87)>0,"-", IF(AND(L3="N/A",L69="N/A",L81="N/A"),"N/A", ( N(L5)*$F5+ N(L6)*$F6+ N(L7)*$F7+ N(L8)*$F8+ N(L10)*$F10+ N(L11)*$F11+ N(L12)*$F12+ N(L13)*$F13+ N(L15)*$F15+ N(L16)*$F16+ N(L17)*$F17+ N(L18)*$F18+ N(L19)*$F19+ N(L20)*$F20+ N(L21)*$F21+ N(L23)*$F23+ N(L24)*$F24+ N(L25)*$F25+ N(L27)*$F27+ N(L28)*$F28+ N(L29)*$F29+ N(L30)*$F30+ N(L31)*$F31+ N(L32)*$F32+ N(L34)*$F34+ N(L35)*$F35+ N(L37)*$F37+ N(L38)*$F38+ N(L39)*$F39+ N(L41)*$F41+ N(L42)*$F42+ N(L43)*$F43+ N(L44)*$F44+ N(L45)*$F45+ N(L46)*$F46+ N(L47)*$F47+ N(L48)*$F48+ N(L50)*$F50+ N(L51)*$F51+ N(L51)*$F52+ N(L54)*$F54+ N(L55)*$F55+ N(L56)*$F56+ N(L58)*$F58+ N(L59)*$F59+ N(L61)*$F61+ N(L62)*$F62+ N(L63)*$F63+ N(L64)*$F64+ N(L65)*$F65+ N(L67)*$F67+ N(L68)*$F68+ N(L71)*$F71+ N(L72)*$F72+ N(L73)*$F73+ N(L74)*$F74+ N(L75)*$F75+ N(L77)*$F77+ N(L78)*$F78+ N(L79)*$F79+ N(L80)*$F80+ N(L83)*$F83+ N(L84)*$F84+ N(L85)*$F85+ N(L86)*$F86+ N(L87)*$F87) /( IF(L5="N/A",0,$F5*5)+ IF(L6="N/A",0,$F6*5)+ IF(L7="N/A",0,$F7*5)+ IF(L8="N/A",0,$F8*5)+ IF(L10="N/A",0,$F10*5)+ IF(L11="N/A",0,$F11*5)+ IF(L12="N/A",0,$F12*5)+ IF(L13="N/A",0,$F13*5)+ IF(L15="N/A",0,$F15*5)+ IF(L16="N/A",0,$F16*5)+ IF(L17="N/A",0,$F17*5)+ IF(L18="N/A",0,$F18*5)+ IF(L19="N/A",0,$F19*5)+ IF(L20="N/A",0,$F20*5)+ IF(L21="N/A",0,$F21*5)+ IF(L23="N/A",0,$F23*5)+ IF(L24="N/A",0,$F24*5)+ IF(L25="N/A",0,$F25*5)+ IF(L27="N/A",0,$F27*5)+ IF(L28="N/A",0,$F28*5)+ IF(L29="N/A",0,$F29*5)+ IF(L30="N/A",0,$F30*5)+ IF(L31="N/A",0,$F31*5)+ IF(L32="N/A",0,$F32*5)+ IF(L34="N/A",0,$F34*5)+ IF(L35="N/A",0,$F35*5)+ IF(L37="N/A",0,$F37*5)+ IF(L38="N/A",0,$F38*5)+ IF(L39="N/A",0,$F39*5)+ IF(L41="N/A",0,$F41*5)+ IF(L42="N/A",0,$F42*5)+ IF(L43="N/A",0,$F43*5)+ IF(L44="N/A",0,$F44*5)+ IF(L45="N/A",0,$F45*5)+ IF(L46="N/A",0,$F46*5)+ IF(L47="N/A",0,$F47*5)+ IF(L48="N/A",0,$F48*5)+ IF(L50="N/A",0,$F50*5)+ IF(L51="N/A",0,$F51*5)+ IF(L52="N/A",0,$F52*5)+ IF(L54="N/A",0,$F54*5)+ IF(L55="N/A",0,$F55*5)+ IF(L56="N/A",0,$F56*5)+ IF(L58="N/A",0,$F58*5)+ IF(L59="N/A",0,$F59*5)+ IF(L61="N/A",0,$F61*5)+ IF(L62="N/A",0,$F62*5)+ IF(L63="N/A",0,$F63*5)+ IF(L64="N/A",0,$F64*5)+ IF(L65="N/A",0,$F65*5)+ IF(L67="N/A",0,$F67*5)+ IF(L68="N/A",0,$F68*5)+ IF(L71="N/A",0,$F71*5)+ IF(L72="N/A",0,$F72*5)+ IF(L73="N/A",0,$F73*5)+ IF(L74="N/A",0,$F74*5)+ IF(L75="N/A",0,$F75*5)+ IF(L77="N/A",0,$F77*5)+ IF(L78="N/A",0,$F78*5)+ IF(L79="N/A",0,$F79*5)+ IF(L80="N/A",0,$F80*5)+ IF(L83="N/A",0,$F83*5)+ IF(L84="N/A",0,$F84*5)+ IF(L85="N/A",0,$F85*5)+ IF(L86="N/A",0,$F86*5)+ IF(L87="N/A",0,$F87*5)))) -> 0 | M2: =IF(COUNTBLANK(M3:M87)>0,"-", IF(AND(M3="N/A",M69="N/A",M81="N/A"),"N/A", ( N(M5)*$F5+ N(M6)*$F6+ N(M7)*$F7+ N(M8)*$F8+ N(M10)*$F10+ N(M11)*$F11+ N(M12)*$F12+ N(M13)*$F13+ N(M15)*$F15+ N(M16)*$F16+ N(M17)*$F17+ N(M18)*$F18+ N(M19)*$F19+ N(M20)*$F20+ N(M21)*$F21+ N(M23)*$F23+ N(M24)*$F24+ N(M25)*$F25+ N(M27)*$F27+ N(M28)*$F28+ N(M29)*$F29+ N(M30)*$F30+ N(M31)*$F31+ N(M32)*$F32+ N(M34)*$F34+ N(M35)*$F35+ N(M37)*$F37+ N(M38)*$F38+ N(M39)*$F39+ N(M41)*$F41+ N(M42)*$F42+ N(M43)*$F43+ N(M44)*$F44+ N(M45)*$F45+ N(M46)*$F46+ N(M47)*$F47+ N(M48)*$F48+ N(M50)*$F50+ N(M51)*$F51+ N(M51)*$F52+ N(M54)*$F54+ N(M55)*$F55+ N(M56)*$F56+ N(M58)*$F58+ N(M59)*$F59+ N(M61)*$F61+ N(M62)*$F62+ N(M63)*$F63+ N(M64)*$F64+ N(M65)*$F65+ N(M67)*$F67+ N(M68)*$F68+ N(M71)*$F71+ N(M72)*$F72+ N(M73)*$F73+ N(M74)*$F74+ N(M75)*$F75+ N(M77)*$F77+ N(M78)*$F78+ N(M79)*$F79+ N(M80)*$F80+ N(M83)*$F83+ N(M84)*$F84+ N(M85)*$F85+ N(M86)*$F86+ N(M87)*$F87) /( IF(M5="N/A",0,$F5*5)+ IF(M6="N/A",0,$F6*5)+ IF(M7="N/A",0,$F7*5)+ IF(M8="N/A",0,$F8*5)+ IF(M10="N/A",0,$F10*5)+ IF(M11="N/A",0,$F11*5)+ IF(M12="N/A",0,$F12*5)+ IF(M13="N/A",0,$F13*5)+ IF(M15="N/A",0,$F15*5)+ IF(M16="N/A",0,$F16*5)+ IF(M17="N/A",0,$F17*5)+ IF(M18="N/A",0,$F18*5)+ IF(M19="N/A",0,$F19*5)+ IF(M20="N/A",0,$F20*5)+ IF(M21="N/A",0,$F21*5)+ IF(M23="N/A",0,$F23*5)+ IF(M24="N/A",0,$F24*5)+ IF(M25="N/A",0,$F25*5)+ IF(M27="N/A",0,$F27*5)+ IF(M28="N/A",0,$F28*5)+ IF(M29="N/A",0,$F29*5)+ IF(M30="N/A",0,$F30*5)+ IF(M31="N/A",0,$F31*5)+ IF(M32="N/A",0,$F32*5)+ IF(M34="N/A",0,$F34*5)+ IF(M35="N/A",0,$F35*5)+ IF(M37="N/A",0,$F37*5)+ IF(M38="N/A",0,$F38*5)+ IF(M39="N/A",0,$F39*5)+ IF(M41="N/A",0,$F41*5)+ IF(M42="N/A",0,$F42*5)+ IF(M43="N/A",0,$F43*5)+ IF(M44="N/A",0,$F44*5)+ IF(M45="N/A",0,$F45*5)+ IF(M46="N/A",0,$F46*5)+ IF(M47="N/A",0,$F47*5)+ IF(M48="N/A",0,$F48*5)+ IF(M50="N/A",0,$F50*5)+ IF(M51="N/A",0,$F51*5)+ IF(M52="N/A",0,$F52*5)+ IF(M54="N/A",0,$F54*5)+ IF(M55="N/A",0,$F55*5)+ IF(M56="N/A",0,$F56*5)+ IF(M58="N/A",0,$F58*5)+ IF(M59="N/A",0,$F59*5)+ IF(M61="N/A",0,$F61*5)+ IF(M62="N/A",0,$F62*5)+ IF(M63="N/A",0,$F63*5)+ IF(M64="N/A",0,$F64*5)+ IF(M65="N/A",0,$F65*5)+ IF(M67="N/A",0,$F67*5)+ IF(M68="N/A",0,$F68*5)+ IF(M71="N/A",0,$F71*5)+ IF(M72="N/A",0,$F72*5)+ IF(M73="N/A",0,$F73*5)+ IF(M74="N/A",0,$F74*5)+ IF(M75="N/A",0,$F75*5)+ IF(M77="N/A",0,$F77*5)+ IF(M78="N/A",0,$F78*5)+ IF(M79="N/A",0,$F79*5)+ IF(M80="N/A",0,$F80*5)+ IF(M83="N/A",0,$F83*5)+ IF(M84="N/A",0,$F84*5)+ IF(M85="N/A",0,$F85*5)+ IF(M86="N/A",0,$F86*5)+ IF(M87="N/A",0,$F87*5)))) -> 0 | N2: =IF(COUNTBLANK(N3:N87)>0,"-", IF(AND(N3="N/A",N69="N/A",N81="N/A"),"N/A", ( N(N5)*$F5+ N(N6)*$F6+ N(N7)*$F7+ N(N8)*$F8+ N(N10)*$F10+ N(N11)*$F11+ N(N12)*$F12+ N(N13)*$F13+ N(N15)*$F15+ N(N16)*$F16+ N(N17)*$F17+ N(N18)*$F18+ N(N19)*$F19+ N(N20)*$F20+ N(N21)*$F21+ N(N23)*$F23+ N(N24)*$F24+ N(N25)*$F25+ N(N27)*$F27+ N(N28)*$F28+ N(N29)*$F29+ N(N30)*$F30+ N(N31)*$F31+ N(N32)*$F32+ N(N34)*$F34+ N(N35)*$F35+ N(N37)*$F37+ N(N38)*$F38+ N(N39)*$F39+ N(N41)*$F41+ N(N42)*$F42+ N(N43)*$F43+ N(N44)*$F44+ N(N45)*$F45+ N(N46)*$F46+ N(N47)*$F47+ N(N48)*$F48+ N(N50)*$F50+ N(N51)*$F51+ N(N51)*$F52+ N(N54)*$F54+ N(N55)*$F55+ N(N56)*$F56+ N(N58)*$F58+ N(N59)*$F59+ N(N61)*$F61+ N(N62)*$F62+ N(N63)*$F63+ N(N64)*$F64+ N(N65)*$F65+ N(N67)*$F67+ N(N68)*$F68+ N(N71)*$F71+ N(N72)*$F72+ N(N73)*$F73+ N(N74)*$F74+ N(N75)*$F75+ N(N77)*$F77+ N(N78)*$F78+ N(N79)*$F79+ N(N80)*$F80+ N(N83)*$F83+ N(N84)*$F84+ N(N85)*$F85+ N(N86)*$F86+ N(N87)*$F87) /( IF(N5="N/A",0,$F5*5)+ IF(N6="N/A",0,$F6*5)+ IF(N7="N/A",0,$F7*5)+ IF(N8="N/A",0,$F8*5)+ IF(N10="N/A",0,$F10*5)+ IF(N11="N/A",0,$F11*5)+ IF(N12="N/A",0,$F12*5)+ IF(N13="N/A",0,$F13*5)+ IF(N15="N/A",0,$F15*5)+ IF(N16="N/A",0,$F16*5)+ IF(N17="N/A",0,$F17*5)+ IF(N18="N/A",0,$F18*5)+ IF(N19="N/A",0,$F19*5)+ IF(N20="N/A",0,$F20*5)+ IF(N21="N/A",0,$F21*5)+ IF(N23="N/A",0,$F23*5)+ IF(N24="N/A",0,$F24*5)+ IF(N25="N/A",0,$F25*5)+ IF(N27="N/A",0,$F27*5)+ IF(N28="N/A",0,$F28*5)+ IF(N29="N/A",0,$F29*5)+ IF(N30="N/A",0,$F30*5)+ IF(N31="N/A",0,$F31*5)+ IF(N32="N/A",0,$F32*5)+ IF(N34="N/A",0,$F34*5)+ IF(N35="N/A",0,$F35*5)+ IF(N37="N/A",0,$F37*5)+ IF(N38="N/A",0,$F38*5)+ IF(N39="N/A",0,$F39*5)+ IF(N41="N/A",0,$F41*5)+ IF(N42="N/A",0,$F42*5)+ IF(N43="N/A",0,$F43*5)+ IF(N44="N/A",0,$F44*5)+ IF(N45="N/A",0,$F45*5)+ IF(N46="N/A",0,$F46*5)+ IF(N47="N/A",0,$F47*5)+ IF(N48="N/A",0,$F48*5)+ IF(N50="N/A",0,$F50*5)+ IF(N51="N/A",0,$F51*5)+ IF(N52="N/A",0,$F52*5)+ IF(N54="N/A",0,$F54*5)+ IF(N55="N/A",0,$F55*5)+ IF(N56="N/A",0,$F56*5)+ IF(N58="N/A",0,$F58*5)+ IF(N59="N/A",0,$F59*5)+ IF(N61="N/A",0,$F61*5)+ IF(N62="N/A",0,$F62*5)+ IF(N63="N/A",0,$F63*5)+ IF(N64="N/A",0,$F64*5)+ IF(N65="N/A",0,$F65*5)+ IF(N67="N/A",0,$F67*5)+ IF(N68="N/A",0,$F68*5)+ IF(N71="N/A",0,$F71*5)+ IF(N72="N/A",0,$F72*5)+ IF(N73="N/A",0,$F73*5)+ IF(N74="N/A",0,$F74*5)+ IF(N75="N/A",0,$F75*5)+ IF(N77="N/A",0,$F77*5)+ IF(N78="N/A",0,$F78*5)+ IF(N79="N/A",0,$F79*5)+ IF(N80="N/A",0,$F80*5)+ IF(N83="N/A",0,$F83*5)+ IF(N84="N/A",0,$F84*5)+ IF(N85="N/A",0,$F85*5)+ IF(N86="N/A",0,$F86*5)+ IF(N87="N/A",0,$F87*5)))) -> #DIV/0! | O2: =IF(COUNTBLANK(O3:O87)>0,"-", IF(AND(O3="N/A",O69="N/A",O81="N/A"),"N/A", ( N(O5)*$F5+ N(O6)*$F6+ N(O7)*$F7+ N(O8)*$F8+ N(O10)*$F10+ N(O11)*$F11+ N(O12)*$F12+ N(O13)*$F13+ N(O15)*$F15+ N(O16)*$F16+ N(O17)*$F17+ N(O18)*$F18+ N(O19)*$F19+ N(O20)*$F20+ N(O21)*$F21+ N(O23)*$F23+ N(O24)*$F24+ N(O25)*$F25+ N(O27)*$F27+ N(O28)*$F28+ N(O29)*$F29+ N(O30)*$F30+ N(O31)*$F31+ N(O32)*$F32+ N(O34)*$F34+ N(O35)*$F35+ N(O37)*$F37+ N(O38)*$F38+ N(O39)*$F39+ N(O41)*$F41+ N(O42)*$F42+ N(O43)*$F43+ N(O44)*$F44+ N(O45)*$F45+ N(O46)*$F46+ N(O47)*$F47+ N(O48)*$F48+ N(O50)*$F50+ N(O51)*$F51+ N(O51)*$F52+ N(O54)*$F54+ N(O55)*$F55+ N(O56)*$F56+ N(O58)*$F58+ N(O59)*$F59+ N(O61)*$F61+ N(O62)*$F62+ N(O63)*$F63+ N(O64)*$F64+ N(O65)*$F65+ N(O67)*$F67+ N(O68)*$F68+ N(O71)*$F71+ N(O72)*$F72+ N(O73)*$F73+ N(O74)*$F74+ N(O75)*$F75+ N(O77)*$F77+ N(O78)*$F78+ N(O79)*$F79+ N(O80)*$F80+ N(O83)*$F83+ N(O84)*$F84+ N(O85)*$F85+ N(O86)*$F86+ N(O87)*$F87) /( IF(O5="N/A",0,$F5*5)+ IF(O6="N/A",0,$F6*5)+ IF(O7="N/A",0,$F7*5)+ IF(O8="N/A",0,$F8*5)+ IF(O10="N/A",0,$F10*5)+ IF(O11="N/A",0,$F11*5)+ IF(O12="N/A",0,$F12*5)+ IF(O13="N/A",0,$F13*5)+ IF(O15="N/A",0,$F15*5)+ IF(O16="N/A",0,$F16*5)+ IF(O17="N/A",0,$F17*5)+ IF(O18="N/A",0,$F18*5)+ IF(O19="N/A",0,$F19*5)+ IF(O20="N/A",0,$F20*5)+ IF(O21="N/A",0,$F21*5)+ IF(O23="N/A",0,$F23*5)+ IF(O24="N/A",0,$F24*5)+ IF(O25="N/A",0,$F25*5)+ IF(O27="N/A",0,$F27*5)+ IF(O28="N/A",0,$F28*5)+ IF(O29="N/A",0,$F29*5)+ IF(O30="N/A",0,$F30*5)+ IF(O31="N/A",0,$F31*5)+ IF(O32="N/A",0,$F32*5)+ IF(O34="N/A",0,$F34*5)+ IF(O35="N/A",0,$F35*5)+ IF(O37="N/A",0,$F37*5)+ IF(O38="N/A",0,$F38*5)+ IF(O39="N/A",0,$F39*5)+ IF(O41="N/A",0,$F41*5)+ IF(O42="N/A",0,$F42*5)+ IF(O43="N/A",0,$F43*5)+ IF(O44="N/A",0,$F44*5)+ IF(O45="N/A",0,$F45*5)+ IF(O46="N/A",0,$F46*5)+ IF(O47="N/A",0,$F47*5)+ IF(O48="N/A",0,$F48*5)+ IF(O50="N/A",0,$F50*5)+ IF(O51="N/A",0,$F51*5)+ IF(O52="N/A",0,$F52*5)+ IF(O54="N/A",0,$F54*5)+ IF(O55="N/A",0,$F55*5)+ IF(O56="N/A",0,$F56*5)+ IF(O58="N/A",0,$F58*5)+ IF(O59="N/A",0,$F59*5)+ IF(O61="N/A",0,$F61*5)+ IF(O62="N/A",0,$F62*5)+ IF(O63="N/A",0,$F63*5)+ IF(O64="N/A",0,$F64*5)+ IF(O65="N/A",0,$F65*5)+ IF(O67="N/A",0,$F67*5)+ IF(O68="N/A",0,$F68*5)+ IF(O71="N/A",0,$F71*5)+ IF(O72="N/A",0,$F72*5)+ IF(O73="N/A",0,$F73*5)+ IF(O74="N/A",0,$F74*5)+ IF(O75="N/A",0,$F75*5)+ IF(O77="N/A",0,$F77*5)+ IF(O78="N/A",0,$F78*5)+ IF(O79="N/A",0,$F79*5)+ IF(O80="N/A",0,$F80*5)+ IF(O83="N/A",0,$F83*5)+ IF(O84="N/A",0,$F84*5)+ IF(O85="N/A",0,$F85*5)+ IF(O86="N/A",0,$F86*5)+ IF(O87="N/A",0,$F87*5)))) -> 0 | P2: =IF(COUNTBLANK(P3:P87)>0,"-", IF(AND(P3="N/A",P69="N/A",P81="N/A"),"N/A", ( N(P5)*$F5+ N(P6)*$F6+ N(P7)*$F7+ N(P8)*$F8+ N(P10)*$F10+ N(P11)*$F11+ N(P12)*$F12+ N(P13)*$F13+ N(P15)*$F15+ N(P16)*$F16+ N(P17)*$F17+ N(P18)*$F18+ N(P19)*$F19+ N(P20)*$F20+ N(P21)*$F21+ N(P23)*$F23+ N(P24)*$F24+ N(P25)*$F25+ N(P27)*$F27+ N(P28)*$F28+ N(P29)*$F29+ N(P30)*$F30+ N(P31)*$F31+ N(P32)*$F32+ N(P34)*$F34+ N(P35)*$F35+ N(P37)*$F37+ N(P38)*$F38+ N(P39)*$F39+ N(P41)*$F41+ N(P42)*$F42+ N(P43)*$F43+ N(P44)*$F44+ N(P45)*$F45+ N(P46)*$F46+ N(P47)*$F47+ N(P48)*$F48+ N(P50)*$F50+ N(P51)*$F51+ N(P51)*$F52+ N(P54)*$F54+ N(P55)*$F55+ N(P56)*$F56+ N(P58)*$F58+ N(P59)*$F59+ N(P61)*$F61+ N(P62)*$F62+ N(P63)*$F63+ N(P64)*$F64+ N(P65)*$F65+ N(P67)*$F67+ N(P68)*$F68+ N(P71)*$F71+ N(P72)*$F72+ N(P73)*$F73+ N(P74)*$F74+ N(P75)*$F75+ N(P77)*$F77+ N(P78)*$F78+ N(P79)*$F79+ N(P80)*$F80+ N(P83)*$F83+ N(P84)*$F84+ N(P85)*$F85+ N(P86)*$F86+ N(P87)*$F87) /( IF(P5="N/A",0,$F5*5)+ IF(P6="N/A",0,$F6*5)+ IF(P7="N/A",0,$F7*5)+ IF(P8="N/A",0,$F8*5)+ IF(P10="N/A",0,$F10*5)+ IF(P11="N/A",0,$F11*5)+ IF(P12="N/A",0,$F12*5)+ IF(P13="N/A",0,$F13*5)+ IF(P15="N/A",0,$F15*5)+ IF(P16="N/A",0,$F16*5)+ IF(P17="N/A",0,$F17*5)+ IF(P18="N/A",0,$F18*5)+ IF(P19="N/A",0,$F19*5)+ IF(P20="N/A",0,$F20*5)+ IF(P21="N/A",0,$F21*5)+ IF(P23="N/A",0,$F23*5)+ IF(P24="N/A",0,$F24*5)+ IF(P25="N/A",0,$F25*5)+ IF(P27="N/A",0,$F27*5)+ IF(P28="N/A",0,$F28*5)+ IF(P29="N/A",0,$F29*5)+ IF(P30="N/A",0,$F30*5)+ IF(P31="N/A",0,$F31*5)+ IF(P32="N/A",0,$F32*5)+ IF(P34="N/A",0,$F34*5)+ IF(P35="N/A",0,$F35*5)+ IF(P37="N/A",0,$F37*5)+ IF(P38="N/A",0,$F38*5)+ IF(P39="N/A",0,$F39*5)+ IF(P41="N/A",0,$F41*5)+ IF(P42="N/A",0,$F42*5)+ IF(P43="N/A",0,$F43*5)+ IF(P44="N/A",0,$F44*5)+ IF(P45="N/A",0,$F45*5)+ IF(P46="N/A",0,$F46*5)+ IF(P47="N/A",0,$F47*5)+ IF(P48="N/A",0,$F48*5)+ IF(P50="N/A",0,$F50*5)+ IF(P51="N/A",0,$F51*5)+ IF(P52="N/A",0,$F52*5)+ IF(P54="N/A",0,$F54*5)+ IF(P55="N/A",0,$F55*5)+ IF(P56="N/A",0,$F56*5)+ IF(P58="N/A",0,$F58*5)+ IF(P59="N/A",0,$F59*5)+ IF(P61="N/A",0,$F61*5)+ IF(P62="N/A",0,$F62*5)+ IF(P63="N/A",0,$F63*5)+ IF(P64="N/A",0,$F64*5)+ IF(P65="N/A",0,$F65*5)+ IF(P67="N/A",0,$F67*5)+ IF(P68="N/A",0,$F68*5)+ IF(P71="N/A",0,$F71*5)+ IF(P72="N/A",0,$F72*5)+ IF(P73="N/A",0,$F73*5)+ IF(P74="N/A",0,$F74*5)+ IF(P75="N/A",0,$F75*5)+ IF(P77="N/A",0,$F77*5)+ IF(P78="N/A",0,$F78*5)+ IF(P79="N/A",0,$F79*5)+ IF(P80="N/A",0,$F80*5)+ IF(P83="N/A",0,$F83*5)+ IF(P84="N/A",0,$F84*5)+ IF(P85="N/A",0,$F85*5)+ IF(P86="N/A",0,$F86*5)+ IF(P87="N/A",0,$F87*5)))) -> 0 | Q2: =IF(COUNTBLANK(Q3:Q87)>0,"-", IF(AND(Q3="N/A",Q69="N/A",Q81="N/A"),"N/A", ( N(Q5)*$F5+ N(Q6)*$F6+ N(Q7)*$F7+ N(Q8)*$F8+ N(Q10)*$F10+ N(Q11)*$F11+ N(Q12)*$F12+ N(Q13)*$F13+ N(Q15)*$F15+ N(Q16)*$F16+ N(Q17)*$F17+ N(Q18)*$F18+ N(Q19)*$F19+ N(Q20)*$F20+ N(Q21)*$F21+ N(Q23)*$F23+ N(Q24)*$F24+ N(Q25)*$F25+ N(Q27)*$F27+ N(Q28)*$F28+ N(Q29)*$F29+ N(Q30)*$F30+ N(Q31)*$F31+ N(Q32)*$F32+ N(Q34)*$F34+ N(Q35)*$F35+ N(Q37)*$F37+ N(Q38)*$F38+ N(Q39)*$F39+ N(Q41)*$F41+ N(Q42)*$F42+ N(Q43)*$F43+ N(Q44)*$F44+ N(Q45)*$F45+ N(Q46)*$F46+ N(Q47)*$F47+ N(Q48)*$F48+ N(Q50)*$F50+ N(Q51)*$F51+ N(Q51)*$F52+ N(Q54)*$F54+ N(Q55)*$F55+ N(Q56)*$F56+ N(Q58)*$F58+ N(Q59)*$F59+ N(Q61)*$F61+ N(Q62)*$F62+ N(Q63)*$F63+ N(Q64)*$F64+ N(Q65)*$F65+ N(Q67)*$F67+ N(Q68)*$F68+ N(Q71)*$F71+ N(Q72)*$F72+ N(Q73)*$F73+ N(Q74)*$F74+ N(Q75)*$F75+ N(Q77)*$F77+ N(Q78)*$F78+ N(Q79)*$F79+ N(Q80)*$F80+ N(Q83)*$F83+ N(Q84)*$F84+ N(Q85)*$F85+ N(Q86)*$F86+ N(Q87)*$F87) /( IF(Q5="N/A",0,$F5*5)+ IF(Q6="N/A",0,$F6*5)+ IF(Q7="N/A",0,$F7*5)+ IF(Q8="N/A",0,$F8*5)+ IF(Q10="N/A",0,$F10*5)+ IF(Q11="N/A",0,$F11*5)+ IF(Q12="N/A",0,$F12*5)+ IF(Q13="N/A",0,$F13*5)+ IF(Q15="N/A",0,$F15*5)+ IF(Q16="N/A",0,$F16*5)+ IF(Q17="N/A",0,$F17*5)+ IF(Q18="N/A",0,$F18*5)+ IF(Q19="N/A",0,$F19*5)+ IF(Q20="N/A",0,$F20*5)+ IF(Q21="N/A",0,$F21*5)+ IF(Q23="N/A",0,$F23*5)+ IF(Q24="N/A",0,$F24*5)+ IF(Q25="N/A",0,$F25*5)+ IF(Q27="N/A",0,$F27*5)+ IF(Q28="N/A",0,$F28*5)+ IF(Q29="N/A",0,$F29*5)+ IF(Q30="N/A",0,$F30*5)+ IF(Q31="N/A",0,$F31*5)+ IF(Q32="N/A",0,$F32*5)+ IF(Q34="N/A",0,$F34*5)+ IF(Q35="N/A",0,$F35*5)+ IF(Q37="N/A",0,$F37*5)+ IF(Q38="N/A",0,$F38*5)+ IF(Q39="N/A",0,$F39*5)+ IF(Q41="N/A",0,$F41*5)+ IF(Q42="N/A",0,$F42*5)+ IF(Q43="N/A",0,$F43*5)+ IF(Q44="N/A",0,$F44*5)+ IF(Q45="N/A",0,$F45*5)+ IF(Q46="N/A",0,$F46*5)+ IF(Q47="N/A",0,$F47*5)+ IF(Q48="N/A",0,$F48*5)+ IF(Q50="N/A",0,$F50*5)+ IF(Q51="N/A",0,$F51*5)+ IF(Q52="N/A",0,$F52*5)+ IF(Q54="N/A",0,$F54*5)+ IF(Q55="N/A",0,$F55*5)+ IF(Q56="N/A",0,$F56*5)+ IF(Q58="N/A",0,$F58*5)+ IF(Q59="N/A",0,$F59*5)+ IF(Q61="N/A",0,$F61*5)+ IF(Q62="N/A",0,$F62*5)+ IF(Q63="N/A",0,$F63*5)+ IF(Q64="N/A",0,$F64*5)+ IF(Q65="N/A",0,$F65*5)+ IF(Q67="N/A",0,$F67*5)+ IF(Q68="N/A",0,$F68*5)+ IF(Q71="N/A",0,$F71*5)+ IF(Q72="N/A",0,$F72*5)+ IF(Q73="N/A",0,$F73*5)+ IF(Q74="N/A",0,$F74*5)+ IF(Q75="N/A",0,$F75*5)+ IF(Q77="N/A",0,$F77*5)+ IF(Q78="N/A",0,$F78*5)+ IF(Q79="N/A",0,$F79*5)+ IF(Q80="N/A",0,$F80*5)+ IF(Q83="N/A",0,$F83*5)+ IF(Q84="N/A",0,$F84*5)+ IF(Q85="N/A",0,$F85*5)+ IF(Q86="N/A",0,$F86*5)+ IF(Q87="N/A",0,$F87*5)))) -> #DIV/0! | R2: =IF(COUNTBLANK(R3:R87)>0,"-", IF(AND(R3="N/A",R69="N/A",R81="N/A"),"N/A", ( N(R5)*$F5+ N(R6)*$F6+ N(R7)*$F7+ N(R8)*$F8+ N(R10)*$F10+ N(R11)*$F11+ N(R12)*$F12+ N(R13)*$F13+ N(R15)*$F15+ N(R16)*$F16+ N(R17)*$F17+ N(R18)*$F18+ N(R19)*$F19+ N(R20)*$F20+ N(R21)*$F21+ N(R23)*$F23+ N(R24)*$F24+ N(R25)*$F25+ N(R27)*$F27+ N(R28)*$F28+ N(R29)*$F29+ N(R30)*$F30+ N(R31)*$F31+ N(R32)*$F32+ N(R34)*$F34+ N(R35)*$F35+ N(R37)*$F37+ N(R38)*$F38+ N(R39)*$F39+ N(R41)*$F41+ N(R42)*$F42+ N(R43)*$F43+ N(R44)*$F44+ N(R45)*$F45+ N(R46)*$F46+ N(R47)*$F47+ N(R48)*$F48+ N(R50)*$F50+ N(R51)*$F51+ N(R51)*$F52+ N(R54)*$F54+ N(R55)*$F55+ N(R56)*$F56+ N(R58)*$F58+ N(R59)*$F59+ N(R61)*$F61+ N(R62)*$F62+ N(R63)*$F63+ N(R64)*$F64+ N(R65)*$F65+ N(R67)*$F67+ N(R68)*$F68+ N(R71)*$F71+ N(R72)*$F72+ N(R73)*$F73+ N(R74)*$F74+ N(R75)*$F75+ N(R77)*$F77+ N(R78)*$F78+ N(R79)*$F79+ N(R80)*$F80+ N(R83)*$F83+ N(R84)*$F84+ N(R85)*$F85+ N(R86)*$F86+ N(R87)*$F87) /( IF(R5="N/A",0,$F5*5)+ IF(R6="N/A",0,$F6*5)+ IF(R7="N/A",0,$F7*5)+ IF(R8="N/A",0,$F8*5)+ IF(R10="N/A",0,$F10*5)+ IF(R11="N/A",0,$F11*5)+ IF(R12="N/A",0,$F12*5)+ IF(R13="N/A",0,$F13*5)+ IF(R15="N/A",0,$F15*5)+ IF(R16="N/A",0,$F16*5)+ IF(R17="N/A",0,$F17*5)+ IF(R18="N/A",0,$F18*5)+ IF(R19="N/A",0,$F19*5)+ IF(R20="N/A",0,$F20*5)+ IF(R21="N/A",0,$F21*5)+ IF(R23="N/A",0,$F23*5)+ IF(R24="N/A",0,$F24*5)+ IF(R25="N/A",0,$F25*5)+ IF(R27="N/A",0,$F27*5)+ IF(R28="N/A",0,$F28*5)+ IF(R29="N/A",0,$F29*5)+ IF(R30="N/A",0,$F30*5)+ IF(R31="N/A",0,$F31*5)+ IF(R32="N/A",0,$F32*5)+ IF(R34="N/A",0,$F34*5)+ IF(R35="N/A",0,$F35*5)+ IF(R37="N/A",0,$F37*5)+ IF(R38="N/A",0,$F38*5)+ IF(R39="N/A",0,$F39*5)+ IF(R41="N/A",0,$F41*5)+ IF(R42="N/A",0,$F42*5)+ IF(R43="N/A",0,$F43*5)+ IF(R44="N/A",0,$F44*5)+ IF(R45="N/A",0,$F45*5)+ IF(R46="N/A",0,$F46*5)+ IF(R47="N/A",0,$F47*5)+ IF(R48="N/A",0,$F48*5)+ IF(R50="N/A",0,$F50*5)+ IF(R51="N/A",0,$F51*5)+ IF(R52="N/A",0,$F52*5)+ IF(R54="N/A",0,$F54*5)+ IF(R55="N/A",0,$F55*5)+ IF(R56="N/A",0,$F56*5)+ IF(R58="N/A",0,$F58*5)+ IF(R59="N/A",0,$F59*5)+ IF(R61="N/A",0,$F61*5)+ IF(R62="N/A",0,$F62*5)+ IF(R63="N/A",0,$F63*5)+ IF(R64="N/A",0,$F64*5)+ IF(R65="N/A",0,$F65*5)+ IF(R67="N/A",0,$F67*5)+ IF(R68="N/A",0,$F68*5)+ IF(R71="N/A",0,$F71*5)+ IF(R72="N/A",0,$F72*5)+ IF(R73="N/A",0,$F73*5)+ IF(R74="N/A",0,$F74*5)+ IF(R75="N/A",0,$F75*5)+ IF(R77="N/A",0,$F77*5)+ IF(R78="N/A",0,$F78*5)+ IF(R79="N/A",0,$F79*5)+ IF(R80="N/A",0,$F80*5)+ IF(R83="N/A",0,$F83*5)+ IF(R84="N/A",0,$F84*5)+ IF(R85="N/A",0,$F85*5)+ IF(R86="N/A",0,$F86*5)+ IF(R87="N/A",0,$F87*5)))) -> 0
B3: FUNDAMENTALES | L3: =IF(COUNTBLANK(L4:L68)>0,"-", IF(AND(L4="N/A",L9="N/A",L14="N/A",L22="N/A",L26="N/A",L33="N/A",L36="N/A",L40="N/A",L49="N/A",L53="N/A",L57="N/A",L60="N/A",L66="N/A"),"N/A", (N(L5)*$F5+ N(L6)*$F6+ N(L7)*$F7+ N(L8)*$F8+ N(L10)*$F10+ N(L11)*$F11+ N(L12)*$F12+ N(L13)*$F13+ N(L15)*$F15+ N(L16)*$F16+ N(L17)*$F17+ N(L18)*$F18+ N(L19)*$F19+ N(L20)*$F20+ N(L21)*$F21+ N(L23)*$F23+ N(L24)*$F24+ N(L25)*$F25+ N(L27)*$F27+ N(L28)*$F28+ N(L29)*$F29+ N(L30)*$F30+ N(L31)*$F31+ N(L32)*$F32+ N(L34)*$F34+ N(L35)*$F35+ N(L37)*$F37+ N(L38)*$F38+ N(L39)*$F39+ N(L41)*$F41+ N(L42)*$F42+ N(L43)*$F43+ N(L44)*$F44+ N(L45)*$F45+ N(L46)*$F46+ N(L47)*$F47+ N(L48)*$F48+ N(L50)*$F50+ N(L51)*$F51+ N(L51)*$F52+ N(L54)*$F54+ N(L55)*$F55+ N(L56)*$F56+ N(L58)*$F58+ N(L59)*$F59+ N(L61)*$F61+ N(L62)*$F62+ N(L63)*$F63+ N(L64)*$F64+ N(L65)*$F65+ N(L67)*$F67+ N(L68)*$F68)/ (IF(L5="N/A",0,$F5*5)+ IF(L6="N/A",0,$F6*5)+ IF(L7="N/A",0,$F7*5)+ IF(L8="N/A",0,$F8*5)+ IF(L10="N/A",0,$F10*5)+ IF(L11="N/A",0,$F11*5)+ IF(L12="N/A",0,$F12*5)+ IF(L13="N/A",0,$F13*5)+ IF(L15="N/A",0,$F15*5)+ IF(L16="N/A",0,$F16*5)+ IF(L17="N/A",0,$F17*5)+ IF(L18="N/A",0,$F18*5)+ IF(L19="N/A",0,$F19*5)+ IF(L20="N/A",0,$F20*5)+ IF(L21="N/A",0,$F21*5)+ IF(L23="N/A",0,$F23*5)+ IF(L24="N/A",0,$F24*5)+ IF(L25="N/A",0,$F25*5)+ IF(L27="N/A",0,$F27*5)+ IF(L28="N/A",0,$F28*5)+ IF(L29="N/A",0,$F29*5)+ IF(L30="N/A",0,$F30*5)+ IF(L31="N/A",0,$F31*5)+ IF(L32="N/A",0,$F32*5)+ IF(L34="N/A",0,$F34*5)+ IF(L35="N/A",0,$F35*5)+ IF(L37="N/A",0,$F37*5)+ IF(L38="N/A",0,$F38*5)+ IF(L39="N/A",0,$F39*5)+ IF(L41="N/A",0,$F41*5)+ IF(L42="N/A",0,$F42*5)+ IF(L43="N/A",0,$F43*5)+ IF(L44="N/A",0,$F44*5)+ IF(L45="N/A",0,$F45*5)+ IF(L46="N/A",0,$F46*5)+ IF(L47="N/A",0,$F47*5)+ IF(L48="N/A",0,$F48*5)+ IF(L50="N/A",0,$F50*5)+ IF(L51="N/A",0,$F51*5)+ IF(L52="N/A",0,$F52*5)++ IF(L54="N/A",0,$F54*5)+ IF(L55="N/A",0,$F55*5)+ IF(L56="N/A",0,$F56*5)+ IF(L58="N/A",0,$F58*5)+ IF(L59="N/A",0,$F59*5)+ IF(L61="N/A",0,$F61*5)+ IF(L62="N/A",0,$F62*5)+ IF(L63="N/A",0,$F63*5)+ IF(L64="N/A",0,$F64*5)+ IF(L65="N/A",0,$F65*5)+ IF(L67="N/A",0,$F67*5)+ IF(L68="N/A",0,$F68*5)))) -> 0 | M3: =IF(COUNTBLANK(M4:M68)>0,"-", IF(AND(M4="N/A",M9="N/A",M14="N/A",M22="N/A",M26="N/A",M33="N/A",M36="N/A",M40="N/A",M49="N/A",M53="N/A",M57="N/A",M60="N/A",M66="N/A"),"N/A", (N(M5)*$F5+ N(M6)*$F6+ N(M7)*$F7+ N(M8)*$F8+ N(M10)*$F10+ N(M11)*$F11+ N(M12)*$F12+ N(M13)*$F13+ N(M15)*$F15+ N(M16)*$F16+ N(M17)*$F17+ N(M18)*$F18+ N(M19)*$F19+ N(M20)*$F20+ N(M21)*$F21+ N(M23)*$F23+ N(M24)*$F24+ N(M25)*$F25+ N(M27)*$F27+ N(M28)*$F28+ N(M29)*$F29+ N(M30)*$F30+ N(M31)*$F31+ N(M32)*$F32+ N(M34)*$F34+ N(M35)*$F35+ N(M37)*$F37+ N(M38)*$F38+ N(M39)*$F39+ N(M41)*$F41+ N(M42)*$F42+ N(M43)*$F43+ N(M44)*$F44+ N(M45)*$F45+ N(M46)*$F46+ N(M47)*$F47+ N(M48)*$F48+ N(M50)*$F50+ N(M51)*$F51+ N(M51)*$F52+ N(M54)*$F54+ N(M55)*$F55+ N(M56)*$F56+ N(M58)*$F58+ N(M59)*$F59+ N(M61)*$F61+ N(M62)*$F62+ N(M63)*$F63+ N(M64)*$F64+ N(M65)*$F65+ N(M67)*$F67+ N(M68)*$F68)/ (IF(M5="N/A",0,$F5*5)+ IF(M6="N/A",0,$F6*5)+ IF(M7="N/A",0,$F7*5)+ IF(M8="N/A",0,$F8*5)+ IF(M10="N/A",0,$F10*5)+ IF(M11="N/A",0,$F11*5)+ IF(M12="N/A",0,$F12*5)+ IF(M13="N/A",0,$F13*5)+ IF(M15="N/A",0,$F15*5)+ IF(M16="N/A",0,$F16*5)+ IF(M17="N/A",0,$F17*5)+ IF(M18="N/A",0,$F18*5)+ IF(M19="N/A",0,$F19*5)+ IF(M20="N/A",0,$F20*5)+ IF(M21="N/A",0,$F21*5)+ IF(M23="N/A",0,$F23*5)+ IF(M24="N/A",0,$F24*5)+ IF(M25="N/A",0,$F25*5)+ IF(M27="N/A",0,$F27*5)+ IF(M28="N/A",0,$F28*5)+ IF(M29="N/A",0,$F29*5)+ IF(M30="N/A",0,$F30*5)+ IF(M31="N/A",0,$F31*5)+ IF(M32="N/A",0,$F32*5)+ IF(M34="N/A",0,$F34*5)+ IF(M35="N/A",0,$F35*5)+ IF(M37="N/A",0,$F37*5)+ IF(M38="N/A",0,$F38*5)+ IF(M39="N/A",0,$F39*5)+ IF(M41="N/A",0,$F41*5)+ IF(M42="N/A",0,$F42*5)+ IF(M43="N/A",0,$F43*5)+ IF(M44="N/A",0,$F44*5)+ IF(M45="N/A",0,$F45*5)+ IF(M46="N/A",0,$F46*5)+ IF(M47="N/A",0,$F47*5)+ IF(M48="N/A",0,$F48*5)+ IF(M50="N/A",0,$F50*5)+ IF(M51="N/A",0,$F51*5)+ IF(M52="N/A",0,$F52*5)++ IF(M54="N/A",0,$F54*5)+ IF(M55="N/A",0,$F55*5)+ IF(M56="N/A",0,$F56*5)+ IF(M58="N/A",0,$F58*5)+ IF(M59="N/A",0,$F59*5)+ IF(M61="N/A",0,$F61*5)+ IF(M62="N/A",0,$F62*5)+ IF(M63="N/A",0,$F63*5)+ IF(M64="N/A",0,$F64*5)+ IF(M65="N/A",0,$F65*5)+ IF(M67="N/A",0,$F67*5)+ IF(M68="N/A",0,$F68*5)))) -> 0 | N3: =IF(COUNTBLANK(N4:N68)>0,"-", IF(AND(N4="N/A",N9="N/A",N14="N/A",N22="N/A",N26="N/A",N33="N/A",N36="N/A",N40="N/A",N49="N/A",N53="N/A",N57="N/A",N60="N/A",N66="N/A"),"N/A", (N(N5)*$F5+ N(N6)*$F6+ N(N7)*$F7+ N(N8)*$F8+ N(N10)*$F10+ N(N11)*$F11+ N(N12)*$F12+ N(N13)*$F13+ N(N15)*$F15+ N(N16)*$F16+ N(N17)*$F17+ N(N18)*$F18+ N(N19)*$F19+ N(N20)*$F20+ N(N21)*$F21+ N(N23)*$F23+ N(N24)*$F24+ N(N25)*$F25+ N(N27)*$F27+ N(N28)*$F28+ N(N29)*$F29+ N(N30)*$F30+ N(N31)*$F31+ N(N32)*$F32+ N(N34)*$F34+ N(N35)*$F35+ N(N37)*$F37+ N(N38)*$F38+ N(N39)*$F39+ N(N41)*$F41+ N(N42)*$F42+ N(N43)*$F43+ N(N44)*$F44+ N(N45)*$F45+ N(N46)*$F46+ N(N47)*$F47+ N(N48)*$F48+ N(N50)*$F50+ N(N51)*$F51+ N(N51)*$F52+ N(N54)*$F54+ N(N55)*$F55+ N(N56)*$F56+ N(N58)*$F58+ N(N59)*$F59+ N(N61)*$F61+ N(N62)*$F62+ N(N63)*$F63+ N(N64)*$F64+ N(N65)*$F65+ N(N67)*$F67+ N(N68)*$F68)/ (IF(N5="N/A",0,$F5*5)+ IF(N6="N/A",0,$F6*5)+ IF(N7="N/A",0,$F7*5)+ IF(N8="N/A",0,$F8*5)+ IF(N10="N/A",0,$F10*5)+ IF(N11="N/A",0,$F11*5)+ IF(N12="N/A",0,$F12*5)+ IF(N13="N/A",0,$F13*5)+ IF(N15="N/A",0,$F15*5)+ IF(N16="N/A",0,$F16*5)+ IF(N17="N/A",0,$F17*5)+ IF(N18="N/A",0,$F18*5)+ IF(N19="N/A",0,$F19*5)+ IF(N20="N/A",0,$F20*5)+ IF(N21="N/A",0,$F21*5)+ IF(N23="N/A",0,$F23*5)+ IF(N24="N/A",0,$F24*5)+ IF(N25="N/A",0,$F25*5)+ IF(N27="N/A",0,$F27*5)+ IF(N28="N/A",0,$F28*5)+ IF(N29="N/A",0,$F29*5)+ IF(N30="N/A",0,$F30*5)+ IF(N31="N/A",0,$F31*5)+ IF(N32="N/A",0,$F32*5)+ IF(N34="N/A",0,$F34*5)+ IF(N35="N/A",0,$F35*5)+ IF(N37="N/A",0,$F37*5)+ IF(N38="N/A",0,$F38*5)+ IF(N39="N/A",0,$F39*5)+ IF(N41="N/A",0,$F41*5)+ IF(N42="N/A",0,$F42*5)+ IF(N43="N/A",0,$F43*5)+ IF(N44="N/A",0,$F44*5)+ IF(N45="N/A",0,$F45*5)+ IF(N46="N/A",0,$F46*5)+ IF(N47="N/A",0,$F47*5)+ IF(N48="N/A",0,$F48*5)+ IF(N50="N/A",0,$F50*5)+ IF(N51="N/A",0,$F51*5)+ IF(N52="N/A",0,$F52*5)++ IF(N54="N/A",0,$F54*5)+ IF(N55="N/A",0,$F55*5)+ IF(N56="N/A",0,$F56*5)+ IF(N58="N/A",0,$F58*5)+ IF(N59="N/A",0,$F59*5)+ IF(N61="N/A",0,$F61*5)+ IF(N62="N/A",0,$F62*5)+ IF(N63="N/A",0,$F63*5)+ IF(N64="N/A",0,$F64*5)+ IF(N65="N/A",0,$F65*5)+ IF(N67="N/A",0,$F67*5)+ IF(N68="N/A",0,$F68*5)))) -> #DIV/0! | O3: =IF(COUNTBLANK(O4:O68)>0,"-", IF(AND(O4="N/A",O9="N/A",O14="N/A",O22="N/A",O26="N/A",O33="N/A",O36="N/A",O40="N/A",O49="N/A",O53="N/A",O57="N/A",O60="N/A",O66="N/A"),"N/A", (N(O5)*$F5+ N(O6)*$F6+ N(O7)*$F7+ N(O8)*$F8+ N(O10)*$F10+ N(O11)*$F11+ N(O12)*$F12+ N(O13)*$F13+ N(O15)*$F15+ N(O16)*$F16+ N(O17)*$F17+ N(O18)*$F18+ N(O19)*$F19+ N(O20)*$F20+ N(O21)*$F21+ N(O23)*$F23+ N(O24)*$F24+ N(O25)*$F25+ N(O27)*$F27+ N(O28)*$F28+ N(O29)*$F29+ N(O30)*$F30+ N(O31)*$F31+ N(O32)*$F32+ N(O34)*$F34+ N(O35)*$F35+ N(O37)*$F37+ N(O38)*$F38+ N(O39)*$F39+ N(O41)*$F41+ N(O42)*$F42+ N(O43)*$F43+ N(O44)*$F44+ N(O45)*$F45+ N(O46)*$F46+ N(O47)*$F47+ N(O48)*$F48+ N(O50)*$F50+ N(O51)*$F51+ N(O51)*$F52+ N(O54)*$F54+ N(O55)*$F55+ N(O56)*$F56+ N(O58)*$F58+ N(O59)*$F59+ N(O61)*$F61+ N(O62)*$F62+ N(O63)*$F63+ N(O64)*$F64+ N(O65)*$F65+ N(O67)*$F67+ N(O68)*$F68)/ (IF(O5="N/A",0,$F5*5)+ IF(O6="N/A",0,$F6*5)+ IF(O7="N/A",0,$F7*5)+ IF(O8="N/A",0,$F8*5)+ IF(O10="N/A",0,$F10*5)+ IF(O11="N/A",0,$F11*5)+ IF(O12="N/A",0,$F12*5)+ IF(O13="N/A",0,$F13*5)+ IF(O15="N/A",0,$F15*5)+ IF(O16="N/A",0,$F16*5)+ IF(O17="N/A",0,$F17*5)+ IF(O18="N/A",0,$F18*5)+ IF(O19="N/A",0,$F19*5)+ IF(O20="N/A",0,$F20*5)+ IF(O21="N/A",0,$F21*5)+ IF(O23="N/A",0,$F23*5)+ IF(O24="N/A",0,$F24*5)+ IF(O25="N/A",0,$F25*5)+ IF(O27="N/A",0,$F27*5)+ IF(O28="N/A",0,$F28*5)+ IF(O29="N/A",0,$F29*5)+ IF(O30="N/A",0,$F30*5)+ IF(O31="N/A",0,$F31*5)+ IF(O32="N/A",0,$F32*5)+ IF(O34="N/A",0,$F34*5)+ IF(O35="N/A",0,$F35*5)+ IF(O37="N/A",0,$F37*5)+ IF(O38="N/A",0,$F38*5)+ IF(O39="N/A",0,$F39*5)+ IF(O41="N/A",0,$F41*5)+ IF(O42="N/A",0,$F42*5)+ IF(O43="N/A",0,$F43*5)+ IF(O44="N/A",0,$F44*5)+ IF(O45="N/A",0,$F45*5)+ IF(O46="N/A",0,$F46*5)+ IF(O47="N/A",0,$F47*5)+ IF(O48="N/A",0,$F48*5)+ IF(O50="N/A",0,$F50*5)+ IF(O51="N/A",0,$F51*5)+ IF(O52="N/A",0,$F52*5)++ IF(O54="N/A",0,$F54*5)+ IF(O55="N/A",0,$F55*5)+ IF(O56="N/A",0,$F56*5)+ IF(O58="N/A",0,$F58*5)+ IF(O59="N/A",0,$F59*5)+ IF(O61="N/A",0,$F61*5)+ IF(O62="N/A",0,$F62*5)+ IF(O63="N/A",0,$F63*5)+ IF(O64="N/A",0,$F64*5)+ IF(O65="N/A",0,$F65*5)+ IF(O67="N/A",0,$F67*5)+ IF(O68="N/A",0,$F68*5)))) -> 0 | P3: =IF(COUNTBLANK(P4:P68)>0,"-", IF(AND(P4="N/A",P9="N/A",P14="N/A",P22="N/A",P26="N/A",P33="N/A",P36="N/A",P40="N/A",P49="N/A",P53="N/A",P57="N/A",P60="N/A",P66="N/A"),"N/A", (N(P5)*$F5+ N(P6)*$F6+ N(P7)*$F7+ N(P8)*$F8+ N(P10)*$F10+ N(P11)*$F11+ N(P12)*$F12+ N(P13)*$F13+ N(P15)*$F15+ N(P16)*$F16+ N(P17)*$F17+ N(P18)*$F18+ N(P19)*$F19+ N(P20)*$F20+ N(P21)*$F21+ N(P23)*$F23+ N(P24)*$F24+ N(P25)*$F25+ N(P27)*$F27+ N(P28)*$F28+ N(P29)*$F29+ N(P30)*$F30+ N(P31)*$F31+ N(P32)*$F32+ N(P34)*$F34+ N(P35)*$F35+ N(P37)*$F37+ N(P38)*$F38+ N(P39)*$F39+ N(P41)*$F41+ N(P42)*$F42+ N(P43)*$F43+ N(P44)*$F44+ N(P45)*$F45+ N(P46)*$F46+ N(P47)*$F47+ N(P48)*$F48+ N(P50)*$F50+ N(P51)*$F51+ N(P51)*$F52+ N(P54)*$F54+ N(P55)*$F55+ N(P56)*$F56+ N(P58)*$F58+ N(P59)*$F59+ N(P61)*$F61+ N(P62)*$F62+ N(P63)*$F63+ N(P64)*$F64+ N(P65)*$F65+ N(P67)*$F67+ N(P68)*$F68)/ (IF(P5="N/A",0,$F5*5)+ IF(P6="N/A",0,$F6*5)+ IF(P7="N/A",0,$F7*5)+ IF(P8="N/A",0,$F8*5)+ IF(P10="N/A",0,$F10*5)+ IF(P11="N/A",0,$F11*5)+ IF(P12="N/A",0,$F12*5)+ IF(P13="N/A",0,$F13*5)+ IF(P15="N/A",0,$F15*5)+ IF(P16="N/A",0,$F16*5)+ IF(P17="N/A",0,$F17*5)+ IF(P18="N/A",0,$F18*5)+ IF(P19="N/A",0,$F19*5)+ IF(P20="N/A",0,$F20*5)+ IF(P21="N/A",0,$F21*5)+ IF(P23="N/A",0,$F23*5)+ IF(P24="N/A",0,$F24*5)+ IF(P25="N/A",0,$F25*5)+ IF(P27="N/A",0,$F27*5)+ IF(P28="N/A",0,$F28*5)+ IF(P29="N/A",0,$F29*5)+ IF(P30="N/A",0,$F30*5)+ IF(P31="N/A",0,$F31*5)+ IF(P32="N/A",0,$F32*5)+ IF(P34="N/A",0,$F34*5)+ IF(P35="N/A",0,$F35*5)+ IF(P37="N/A",0,$F37*5)+ IF(P38="N/A",0,$F38*5)+ IF(P39="N/A",0,$F39*5)+ IF(P41="N/A",0,$F41*5)+ IF(P42="N/A",0,$F42*5)+ IF(P43="N/A",0,$F43*5)+ IF(P44="N/A",0,$F44*5)+ IF(P45="N/A",0,$F45*5)+ IF(P46="N/A",0,$F46*5)+ IF(P47="N/A",0,$F47*5)+ IF(P48="N/A",0,$F48*5)+ IF(P50="N/A",0,$F50*5)+ IF(P51="N/A",0,$F51*5)+ IF(P52="N/A",0,$F52*5)++ IF(P54="N/A",0,$F54*5)+ IF(P55="N/A",0,$F55*5)+ IF(P56="N/A",0,$F56*5)+ IF(P58="N/A",0,$F58*5)+ IF(P59="N/A",0,$F59*5)+ IF(P61="N/A",0,$F61*5)+ IF(P62="N/A",0,$F62*5)+ IF(P63="N/A",0,$F63*5)+ IF(P64="N/A",0,$F64*5)+ IF(P65="N/A",0,$F65*5)+ IF(P67="N/A",0,$F67*5)+ IF(P68="N/A",0,$F68*5)))) -> 0 | Q3: =IF(COUNTBLANK(Q4:Q68)>0,"-", IF(AND(Q4="N/A",Q9="N/A",Q14="N/A",Q22="N/A",Q26="N/A",Q33="N/A",Q36="N/A",Q40="N/A",Q49="N/A",Q53="N/A",Q57="N/A",Q60="N/A",Q66="N/A"),"N/A", (N(Q5)*$F5+ N(Q6)*$F6+ N(Q7)*$F7+ N(Q8)*$F8+ N(Q10)*$F10+ N(Q11)*$F11+ N(Q12)*$F12+ N(Q13)*$F13+ N(Q15)*$F15+ N(Q16)*$F16+ N(Q17)*$F17+ N(Q18)*$F18+ N(Q19)*$F19+ N(Q20)*$F20+ N(Q21)*$F21+ N(Q23)*$F23+ N(Q24)*$F24+ N(Q25)*$F25+ N(Q27)*$F27+ N(Q28)*$F28+ N(Q29)*$F29+ N(Q30)*$F30+ N(Q31)*$F31+ N(Q32)*$F32+ N(Q34)*$F34+ N(Q35)*$F35+ N(Q37)*$F37+ N(Q38)*$F38+ N(Q39)*$F39+ N(Q41)*$F41+ N(Q42)*$F42+ N(Q43)*$F43+ N(Q44)*$F44+ N(Q45)*$F45+ N(Q46)*$F46+ N(Q47)*$F47+ N(Q48)*$F48+ N(Q50)*$F50+ N(Q51)*$F51+ N(Q51)*$F52+ N(Q54)*$F54+ N(Q55)*$F55+ N(Q56)*$F56+ N(Q58)*$F58+ N(Q59)*$F59+ N(Q61)*$F61+ N(Q62)*$F62+ N(Q63)*$F63+ N(Q64)*$F64+ N(Q65)*$F65+ N(Q67)*$F67+ N(Q68)*$F68)/ (IF(Q5="N/A",0,$F5*5)+ IF(Q6="N/A",0,$F6*5)+ IF(Q7="N/A",0,$F7*5)+ IF(Q8="N/A",0,$F8*5)+ IF(Q10="N/A",0,$F10*5)+ IF(Q11="N/A",0,$F11*5)+ IF(Q12="N/A",0,$F12*5)+ IF(Q13="N/A",0,$F13*5)+ IF(Q15="N/A",0,$F15*5)+ IF(Q16="N/A",0,$F16*5)+ IF(Q17="N/A",0,$F17*5)+ IF(Q18="N/A",0,$F18*5)+ IF(Q19="N/A",0,$F19*5)+ IF(Q20="N/A",0,$F20*5)+ IF(Q21="N/A",0,$F21*5)+ IF(Q23="N/A",0,$F23*5)+ IF(Q24="N/A",0,$F24*5)+ IF(Q25="N/A",0,$F25*5)+ IF(Q27="N/A",0,$F27*5)+ IF(Q28="N/A",0,$F28*5)+ IF(Q29="N/A",0,$F29*5)+ IF(Q30="N/A",0,$F30*5)+ IF(Q31="N/A",0,$F31*5)+ IF(Q32="N/A",0,$F32*5)+ IF(Q34="N/A",0,$F34*5)+ IF(Q35="N/A",0,$F35*5)+ IF(Q37="N/A",0,$F37*5)+ IF(Q38="N/A",0,$F38*5)+ IF(Q39="N/A",0,$F39*5)+ IF(Q41="N/A",0,$F41*5)+ IF(Q42="N/A",0,$F42*5)+ IF(Q43="N/A",0,$F43*5)+ IF(Q44="N/A",0,$F44*5)+ IF(Q45="N/A",0,$F45*5)+ IF(Q46="N/A",0,$F46*5)+ IF(Q47="N/A",0,$F47*5)+ IF(Q48="N/A",0,$F48*5)+ IF(Q50="N/A",0,$F50*5)+ IF(Q51="N/A",0,$F51*5)+ IF(Q52="N/A",0,$F52*5)++ IF(Q54="N/A",0,$F54*5)+ IF(Q55="N/A",0,$F55*5)+ IF(Q56="N/A",0,$F56*5)+ IF(Q58="N/A",0,$F58*5)+ IF(Q59="N/A",0,$F59*5)+ IF(Q61="N/A",0,$F61*5)+ IF(Q62="N/A",0,$F62*5)+ IF(Q63="N/A",0,$F63*5)+ IF(Q64="N/A",0,$F64*5)+ IF(Q65="N/A",0,$F65*5)+ IF(Q67="N/A",0,$F67*5)+ IF(Q68="N/A",0,$F68*5)))) -> #DIV/0! | R3: =IF(COUNTBLANK(R4:R68)>0,"-", IF(AND(R4="N/A",R9="N/A",R14="N/A",R22="N/A",R26="N/A",R33="N/A",R36="N/A",R40="N/A",R49="N/A",R53="N/A",R57="N/A",R60="N/A",R66="N/A"),"N/A", (N(R5)*$F5+ N(R6)*$F6+ N(R7)*$F7+ N(R8)*$F8+ N(R10)*$F10+ N(R11)*$F11+ N(R12)*$F12+ N(R13)*$F13+ N(R15)*$F15+ N(R16)*$F16+ N(R17)*$F17+ N(R18)*$F18+ N(R19)*$F19+ N(R20)*$F20+ N(R21)*$F21+ N(R23)*$F23+ N(R24)*$F24+ N(R25)*$F25+ N(R27)*$F27+ N(R28)*$F28+ N(R29)*$F29+ N(R30)*$F30+ N(R31)*$F31+ N(R32)*$F32+ N(R34)*$F34+ N(R35)*$F35+ N(R37)*$F37+ N(R38)*$F38+ N(R39)*$F39+ N(R41)*$F41+ N(R42)*$F42+ N(R43)*$F43+ N(R44)*$F44+ N(R45)*$F45+ N(R46)*$F46+ N(R47)*$F47+ N(R48)*$F48+ N(R50)*$F50+ N(R51)*$F51+ N(R51)*$F52+ N(R54)*$F54+ N(R55)*$F55+ N(R56)*$F56+ N(R58)*$F58+ N(R59)*$F59+ N(R61)*$F61+ N(R62)*$F62+ N(R63)*$F63+ N(R64)*$F64+ N(R65)*$F65+ N(R67)*$F67+ N(R68)*$F68)/ (IF(R5="N/A",0,$F5*5)+ IF(R6="N/A",0,$F6*5)+ IF(R7="N/A",0,$F7*5)+ IF(R8="N/A",0,$F8*5)+ IF(R10="N/A",0,$F10*5)+ IF(R11="N/A",0,$F11*5)+ IF(R12="N/A",0,$F12*5)+ IF(R13="N/A",0,$F13*5)+ IF(R15="N/A",0,$F15*5)+ IF(R16="N/A",0,$F16*5)+ IF(R17="N/A",0,$F17*5)+ IF(R18="N/A",0,$F18*5)+ IF(R19="N/A",0,$F19*5)+ IF(R20="N/A",0,$F20*5)+ IF(R21="N/A",0,$F21*5)+ IF(R23="N/A",0,$F23*5)+ IF(R24="N/A",0,$F24*5)+ IF(R25="N/A",0,$F25*5)+ IF(R27="N/A",0,$F27*5)+ IF(R28="N/A",0,$F28*5)+ IF(R29="N/A",0,$F29*5)+ IF(R30="N/A",0,$F30*5)+ IF(R31="N/A",0,$F31*5)+ IF(R32="N/A",0,$F32*5)+ IF(R34="N/A",0,$F34*5)+ IF(R35="N/A",0,$F35*5)+ IF(R37="N/A",0,$F37*5)+ IF(R38="N/A",0,$F38*5)+ IF(R39="N/A",0,$F39*5)+ IF(R41="N/A",0,$F41*5)+ IF(R42="N/A",0,$F42*5)+ IF(R43="N/A",0,$F43*5)+ IF(R44="N/A",0,$F44*5)+ IF(R45="N/A",0,$F45*5)+ IF(R46="N/A",0,$F46*5)+ IF(R47="N/A",0,$F47*5)+ IF(R48="N/A",0,$F48*5)+ IF(R50="N/A",0,$F50*5)+ IF(R51="N/A",0,$F51*5)+ IF(R52="N/A",0,$F52*5)++ IF(R54="N/A",0,$F54*5)+ IF(R55="N/A",0,$F55*5)+ IF(R56="N/A",0,$F56*5)+ IF(R58="N/A",0,$F58*5)+ IF(R59="N/A",0,$F59*5)+ IF(R61="N/A",0,$F61*5)+ IF(R62="N/A",0,$F62*5)+ IF(R63="N/A",0,$F63*5)+ IF(R64="N/A",0,$F64*5)+ IF(R65="N/A",0,$F65*5)+ IF(R67="N/A",0,$F67*5)+ IF(R68="N/A",0,$F68*5)))) -> 0
B4: SIF Y GESTIÓN DE INCIDENTES | L4: =IF(COUNTIF(L5:L8,"=N/A")=4,"N/A", ((N(L5)*$F5)+(N(L6)*$F6)+(N(L7)*$F7)+(N(L8)*$F8))/(IF(L5="N/A",0,(5*$F5))+IF(L6="N/A",0,(5*$F6))+IF(L7="N/A",0,(5*$F7))+IF(L8="N/A",0,(5*$F8)))) -> 0 | M4: =IF(COUNTIF(M5:M8,"=N/A")=4,"N/A", ((N(M5)*$F5)+(N(M6)*$F6)+(N(M7)*$F7)+(N(M8)*$F8))/(IF(M5="N/A",0,(5*$F5))+IF(M6="N/A",0,(5*$F6))+IF(M7="N/A",0,(5*$F7))+IF(M8="N/A",0,(5*$F8)))) -> 0 | N4: =IF(COUNTIF(N5:N8,"=N/A")=4,"N/A", ((N(N5)*$F5)+(N(N6)*$F6)+(N(N7)*$F7)+(N(N8)*$F8))/(IF(N5="N/A",0,(5*$F5))+IF(N6="N/A",0,(5*$F6))+IF(N7="N/A",0,(5*$F7))+IF(N8="N/A",0,(5*$F8)))) -> N/A | O4: =IF(COUNTIF(O5:O8,"=N/A")=4,"N/A", ((N(O5)*$F5)+(N(O6)*$F6)+(N(O7)*$F7)+(N(O8)*$F8))/(IF(O5="N/A",0,(5*$F5))+IF(O6="N/A",0,(5*$F6))+IF(O7="N/A",0,(5*$F7))+IF(O8="N/A",0,(5*$F8)))) -> 0 | P4: =IF(COUNTIF(P5:P8,"=N/A")=4,"N/A", ((N(P5)*$F5)+(N(P6)*$F6)+(N(P7)*$F7)+(N(P8)*$F8))/(IF(P5="N/A",0,(5*$F5))+IF(P6="N/A",0,(5*$F6))+IF(P7="N/A",0,(5*$F7))+IF(P8="N/A",0,(5*$F8)))) -> 0 | Q4: =IF(COUNTIF(Q5:Q8,"=N/A")=4,"N/A", ((N(Q5)*$F5)+(N(Q6)*$F6)+(N(Q7)*$F7)+(N(Q8)*$F8))/(IF(Q5="N/A",0,(5*$F5))+IF(Q6="N/A",0,(5*$F6))+IF(Q7="N/A",0,(5*$F7))+IF(Q8="N/A",0,(5*$F8)))) -> N/A | R4: =IF(COUNTIF(R5:R8,"=N/A")=4,"N/A", ((N(R5)*$F5)+(N(R6)*$F6)+(N(R7)*$F7)+(N(R8)*$F8))/(IF(R5="N/A",0,(5*$F5))+IF(R6="N/A",0,(5*$F6))+IF(R7="N/A",0,(5*$F7))+IF(R8="N/A",0,(5*$F8)))) -> 0
A5: 7_1_32_102 | B5: SIF Y GESTIÓN DE INCIDENTES | C5: 1.1 | D5: Reporte de incidentes/accidentes | E5: SÍ | F5: 1 | G5: Propósito: Ingresar todos los datos en la herramienta nos permite realizar análisis de datos en varios niveles (distribuidor, región). Asegurar visibilidad y responsabilidad en nuestro rendimiento. Con el fin de reducir incidentes/accidentes, se debe implementar un proceso para registrar el entrenamiento y las condiciones inseguras. Asegurar que en el distribuidor exista un proceso y una herramienta para las condiciones inseguras y los comportamientos seguros/inseguros es fundamental para tener éxito en todas las preguntas de ejecución segura (OWD) que siguen en el pilar. Ejemplos de herramientas para informar sobre condiciones inseguras y comportamientos seguros/inseguros en el distribuidor puede ser un formulario interno. | H5: R1.1.1 - El 100% de los Incidentes/accidentes Registrables Totales se documentan en la Herramienta de Informes. No existen brechas. R1.1.2 - El 100% de los Incidentes de Casi Accidente y Primeros Auxilios se documentan en la Herramienta de Informes de Incidentes. No existen brechas. R1.1.3 - Existe un proceso con una herramienta digital para registrar condiciones inseguras y entrenamiento conductual (seguro/insseguro) para permitir la recopilación de datos y el análisis de tendencias. R1.1.4 - Existe una forma saludable en forma de pirámide de seguridad para el distribuidor. El forms de HSMA debe ser ídem al TRI reportado en los GKPIs mensualmente. | I5: Nivel 5 - Todos los requisitos cumplidos. Nivel 3 - Se cumplen R1.1.1, R1.1.2 y R1.1.3, PERO no se cumple R1.1.4. Nivel 1 - Se cumple R1.1.1 con brechas. Nivel 0 - No se cumple R1.1.1. | J5: 1.-Verificar la herramienta de informes de incidentes en busca de posibles brechas en la notificación. 2.-Revisar el proceso y la herramienta de informes de entrenamiento conductual y condiciones inseguras. 3.-Revisar que los datos en la herramienta de entrenamiento conductual y condiciones inseguras estén registrados. 4.-Revisar la pirámide de seguridad del centro de distribución (Pirámide de Bird) para asegurar que exista una forma saludable de pirámide. | L5: =IF(AND(M5="N/A",N5="N/A"),"N/A",IF(OR(M5="",N5=""),"",SMALL(M5:N5,1))) -> 0 | M5: 0 | N5: N/A | O5: =IF(AND(P5="N/A",Q5="N/A"),"N/A",IF(OR(P5="",Q5=""),"",SMALL(P5:Q5,1))) -> 0 | P5: 0 | Q5: N/A | R5: =IF(OR(L5="",O5=""),"",IF(AND(L5="N/A",O5="N/A"),"N/A",AVERAGE(L5,O5))) -> 0
A6: 7_1_32_103 | B6: SIF Y GESTIÓN DE INCIDENTES | C6: 1.2 | D6: Notificacion de incidentes/accidentes | E6: No | F6: 1 | G6: Propósito: Las notificaciones de 24 horas están destinadas a notificar de inmediato el sitio, región a de los incidentes que se han producido. Esto nos permite responder rápidamente e implementar acciones correctivas en todas las ubicaciones. El intercambio de alertas de seguridad al final de nuestra investigación garantiza que la información completa de un caso se distribuya y que los aprendizajes completos sean posibles en todos nuestros sitios. | H6: R1.2.1 - Notificacion al EDV enviada dentro de las 24 horas para cada LTI, MDI, MTI , FAI, Incidentes y SIF actual y potencial. R1.2.2 - Investigación completa para cada LTI, MDI, MTI , FAI y SIF en Gestión de Incidentes dentro de los 7 días. R1.2.3 - Alerta de seguridad publicada y comunicada para cada incidente, LTI, MDI, MTI, FAI, Incidentes SIF Actual y SIF Potencial dentro de los 7 días. | I6: 5 - Cumplimiento de todos los requisitos para el 100% de los casos aplicables 3 - R1.2.1 y R1.2.2 para el 100% de los casos aplicables pero R1.2.3 para <100% de los casos aplicables 1 - R1.2.1 para el 100% de los casos aplicables pero R1.2.2 para <100% de los casos aplicables 0 - R1.2.1 cumplido para <100% de los casos aplicables | J6: 1. Compruebe para el registro notificación de correo electrónico dentro de las 24 horas. 2. Compruebe la herramienta de gestión de incidentes, asegúrese de que los campos de investigación se han completado. 3. Compruebe la ficha de auditoría para verificar la puntualidad de la investigación y que se cierre en un plazo de 7 días. 4. Comprobar si hay constancia de la alerta de seguridad comunicada por cada SIF actual y SIF potencial. | L6: =IF(AND(M6="N/A",N6="N/A"),"N/A",IF(OR(M6="",N6=""),"",SMALL(M6:N6,1))) -> 0 | M6: 0 | N6: N/A | O6: =IF(AND(P6="N/A",Q6="N/A"),"N/A",IF(OR(P6="",Q6=""),"",SMALL(P6:Q6,1))) -> 0 | P6: 0 | Q6: N/A | R6: =IF(OR(L6="",O6=""),"",IF(AND(L6="N/A",O6="N/A"),"N/A",AVERAGE(L6,O6))) -> 0
A7: 7_1_32_104 | B7: SIF Y GESTIÓN DE INCIDENTES | C7: 1.3 | D7: Investigación de incidentes/accidentes y análisis de causa raíz | E7: No | F7: 1 | G7: Propósito: Debemos identificar una causa raíz para cada incidente para que podamos crear acciones correctivas que prevengan la recurrencia de ese incidente. El análisis de la causa raíz debe realizarse utilizando una metodología de resolución de problemas y las acciones correctivas deben administrarse hasta su finalización. | H7: R1.3.1 - Análisis de causa raíz para cada incidente. R1.3.2 - 5 Por qué u otra herramienta del sistema de gestión documentada para cada investigación. Analizar el historico de los involucrados R1.3.3 - Acciones correctivas - deben ser más de 1 acción correctiva. R1.3.4 - Evidencia de la gestión de la acción correctiva. R1.3.5 - Actualización de la evaluación de riesgos. | I7: 5 - Cumplimiento de todos los requisitos para el 100% de los casos aplicables 3 - R1.3.1, R1.3.2 y R1.3.3 para el 100% de los casos aplicables pero R1.3.4 <100% de los casos aplicables 1 - R1.3.3 para el 100% pero R1.3.2 para <100% de los casos 0 - R1.3.1 o R1.3.3 para <100% de los casos cumplidos | J7: 1. Compruebe la herramienta de notificación de incidentes y revise el análisis de causa raíz (Compruebe si el 5 por qué está documentado y si es de buena calidad). 2. Comprobar el instrumento de notificación de incidentes y revisar las medidas correctivas. Compruebe si hay varias acciones, que se relacionen con la causa raíz y que las acciones son más que simplemente el re-entrenamiento. 3. Comprobar el registro de acciones correctivas para verificar que las medidas se hayan cerrado oportunamente. 4. Comprobar la evaluación de riesgo de las instalaciones y validar su actualización como consecuencia de la causa raiz. | L7: =IF(AND(M7="N/A",N7="N/A"),"N/A",IF(OR(M7="",N7=""),"",SMALL(M7:N7,1))) -> 0 | M7: 0 | N7: N/A | O7: =IF(AND(P7="N/A",Q7="N/A"),"N/A",IF(OR(P7="",Q7=""),"",SMALL(P7:Q7,1))) -> 0 | P7: 0 | Q7: N/A | R7: =IF(OR(L7="",O7=""),"",IF(AND(L7="N/A",O7="N/A"),"N/A",AVERAGE(L7,O7))) -> 0
A8: 7_1_32_105 | B8: SIF Y GESTIÓN DE INCIDENTES | C8: 1.4 | D8: Proceso de revisión de rutina de gestión de incidentes/accidentes | E8: No | F8: 1 | G8: Propósito: Es crucial revisar los incidentes/accidentes individuales que ocurren, los detalles de esos casos, la causa raíz y las acciones individuales. Es igualmente importante analizar las tendencias de lo que está causando los incidentes, qué tipos de lesiones están ocurriendo, etc. Este análisis empoderará al sitio para seleccionar acciones correctivas que tengan el poder de impactar en múltiples lesiones y ayudará al sitio a priorizar qué acciones deben tomarse primero. El cascado de la información tiene que ser 100% presencial en las team room. | H8: R1.4.1 - Los incidentes/accidentes se integran en el proceso de revisión rutinario en todos los niveles (Evidencia de notificación de incidentes en salas de equipo, reuniones de entrega, reuniones de gerencia, etc.). El cascado de la información tiene que ser 100% presencial en las team room. R1.4.2 - Análisis de tendencias de incidentes y datos de causa raíz disponibles. R1.4.3 - Identificación de áreas con carteleras de piramide de seguridad. para mejorar la estrategia de conocimiento de los equipos. | I8: Nivel 5 - Todos los requisitos cumplidos con acciones tomadas y ejecutadas que pueden resolver efectivamente el problema. Nivel 3 - Todos los requisitos cumplidos. Nivel 1 - Se cumplen R1.4.1 y R1.4.2. Nivel 0 - No se cumple R1.4.1. | J8: 1. Verificar si los incidentes se analizan como el primer punto en las reuniones de rutina diaria, en el cambio de turno y en las reuniones semanales, y si se abordan de manera eficaz para impulsar el comportamiento de seguridad, generar conciencia y tomar medidas. 2. Verificar si existe un análisis de tendencias de los incidentes y si se identifican las causas fundamentales. 3. Verificar si se identifican áreas de enfoque estratégico para la instalación. | L8: =IF(AND(M8="N/A",N8="N/A"),"N/A",IF(OR(M8="",N8=""),"",SMALL(M8:N8,1))) -> 0 | M8: 0 | N8: N/A | O8: =IF(AND(P8="N/A",Q8="N/A"),"N/A",IF(OR(P8="",Q8=""),"",SMALL(P8:Q8,1))) -> 0 | P8: 0 | Q8: N/A | R8: =IF(OR(L8="",O8=""),"",IF(AND(L8="N/A",O8="N/A"),"N/A",AVERAGE(L8,O8))) -> 0
B9: GESTIÓN DE PROCESOS DE ALTO RIESGO | L9: =IF(COUNTIF(L10:L13,"=N/A")=4,"N/A", ((N(L10)*$F10)+(N(L11)*$F11)+(N(L12)*$F12)+(N(L13)*$F13))/(IF(L10="N/A",0,(5*$F10))+IF(L11="N/A",0,(5*$F11))+IF(L12="N/A",0,(5*$F12))+IF(L13="N/A",0,(5*$F13)))) -> 0 | M9: =IF(COUNTIF(M10:M13,"=N/A")=4,"N/A", ((N(M10)*$F10)+(N(M11)*$F11)+(N(M12)*$F12)+(N(M13)*$F13))/(IF(M10="N/A",0,(5*$F10))+IF(M11="N/A",0,(5*$F11))+IF(M12="N/A",0,(5*$F12))+IF(M13="N/A",0,(5*$F13)))) -> 0 | N9: =IF(COUNTIF(N10:N13,"=N/A")=4,"N/A", ((N(N10)*$F10)+(N(N11)*$F11)+(N(N12)*$F12)+(N(N13)*$F13))/(IF(N10="N/A",0,(5*$F10))+IF(N11="N/A",0,(5*$F11))+IF(N12="N/A",0,(5*$F12))+IF(N13="N/A",0,(5*$F13)))) -> N/A | O9: =IF(COUNTIF(O10:O13,"=N/A")=4,"N/A", ((N(O10)*$F10)+(N(O11)*$F11)+(N(O12)*$F12)+(N(O13)*$F13))/(IF(O10="N/A",0,(5*$F10))+IF(O11="N/A",0,(5*$F11))+IF(O12="N/A",0,(5*$F12))+IF(O13="N/A",0,(5*$F13)))) -> 0 | P9: =IF(COUNTIF(P10:P13,"=N/A")=4,"N/A", ((N(P10)*$F10)+(N(P11)*$F11)+(N(P12)*$F12)+(N(P13)*$F13))/(IF(P10="N/A",0,(5*$F10))+IF(P11="N/A",0,(5*$F11))+IF(P12="N/A",0,(5*$F12))+IF(P13="N/A",0,(5*$F13)))) -> 0 | Q9: =IF(COUNTIF(Q10:Q13,"=N/A")=4,"N/A", ((N(Q10)*$F10)+(N(Q11)*$F11)+(N(Q12)*$F12)+(N(Q13)*$F13))/(IF(Q10="N/A",0,(5*$F10))+IF(Q11="N/A",0,(5*$F11))+IF(Q12="N/A",0,(5*$F12))+IF(Q13="N/A",0,(5*$F13)))) -> N/A | R9: =IF(COUNTIF(R10:R13,"=N/A")=4,"N/A", ((N(R10)*$F10)+(N(R11)*$F11)+(N(R12)*$F12)+(N(R13)*$F13))/(IF(R10="N/A",0,(5*$F10))+IF(R11="N/A",0,(5*$F11))+IF(R12="N/A",0,(5*$F12))+IF(R13="N/A",0,(5*$F13)))) -> 0
A10: 7_1_33_106 | B10: GESTIÓN DE PROCESOS DE ALTO RIESGO | C10: 2.1 | D10: Control y gestión de entornos con déficit de oxígeno | E10: No | F10: 1 | G10: Documente procedimiento de Gestión de procesos de alto riesgo y la supervisión de entornos con deficiencia de oxígeno. | H10: R2.1.1 - Evaluación del riesgo de la unidad realizada para identificar áreas con déficit de oxígeno. R2.1.2 - Áreas potencialmente deficientes de oxígeno equipadas con sistemas de detección y/o programas de monitoreo y gestión. R2.1.3 - Se han establecido controles para las áreas potencialmente deficientes de oxígeno. R2.1.4 - Cuando se utiliza un sistema de detección, es inspeccionado por los operadores con una intervención rutinaria debidamente documentada. | I10: 5 - Todos los requisitos se cumplen 3 - R 2.1.1, R 2.1.2 y R 2.1.3 cumple pero R2.1.4 no cumple 1 - R2.1.1 y R2.1.2 cumple 0 - R2.1.1 no cumple | J10: 1. Revisar la evaluación de riesgos para ver si se han identificado zonas. 2. Comprobar si existen programas de seguimiento y gestión y un sistema de detección. 3. Compruebe si existen controles en su lugar. 4. Hable con los operadores y pregunte sobre estas áreas y si siguen las rutinas de intervención. | L10: =IF(AND(M10="N/A",N10="N/A"),"N/A",IF(OR(M10="",N10=""),"",SMALL(M10:N10,1))) -> 0 | M10: 0 | N10: N/A | O10: =IF(AND(P10="N/A",Q10="N/A"),"N/A",IF(OR(P10="",Q10=""),"",SMALL(P10:Q10,1))) -> 0 | P10: 0 | Q10: N/A | R10: =IF(OR(L10="",O10=""),"",IF(AND(L10="N/A",O10="N/A"),"N/A",AVERAGE(L10,O10))) -> 0
A11: 7_1_33_107 | B11: GESTIÓN DE PROCESOS DE ALTO RIESGO | C11: 2.2 | D11: Monitoreo y gestión de sistemas de amoníaco | E11: No | F11: 1 | G11: Documente procedimiento de gestión de procesos de alto riesgo y la supervisión y gestión de los sistemas de amoníaco. | H11: R2.2.1 - Evaluación de riesgo de las instalaciones realizada para identificar áreas que utilizan el sistema de amoniaco. R2.2.2 - Instalaciones de amoniaco equipadas con sistemas de detección y/o programas de monitoreo y gestión. R2.2.3 - Existen controles para las áreas que utilizan amoniaco. R2.2.4 - Cuando se utiliza un sistema de detección, es inspeccionado por los operadores con una intervención rutinaria debidamente documentada. | I11: 5 - Todos los requisitos cumplieron 3 - R2.2.1, R2.2.2 y R2.2.3 cumplieron pero R2.2.4 no cumplió 1 - R2.2.1 y R2.2.2 cumplió 0 - R2.2.1 no cumplió | J11: 1. Examinar la evaluación de riesgo para ver si se han identificado zonas que utilizan amoniaco. 2. Compruebe si existe un programa de seguimiento y gestión y un sistema de detección. 3. Compruebe si existen controles. 4. Hable con los operadores y pregunte sobre estas áreas y si siguen las rutinas de intervención. | L11: =IF(AND(M11="N/A",N11="N/A"),"N/A",IF(OR(M11="",N11=""),"",SMALL(M11:N11,1))) -> 0 | M11: 0 | N11: N/A | O11: =IF(AND(P11="N/A",Q11="N/A"),"N/A",IF(OR(P11="",Q11=""),"",SMALL(P11:Q11,1))) -> 0 | P11: 0 | Q11: N/A | R11: =IF(OR(L11="",O11=""),"",IF(AND(L11="N/A",O11="N/A"),"N/A",AVERAGE(L11,O11))) -> 0
A12: 7_1_33_108 | B12: GESTIÓN DE PROCESOS DE ALTO RIESGO | C12: 2.3 | D12: Monitoreo y gestión de prevención de explosiones | E12: No | F12: 1 | G12: Identificar áreas con potencial riesgo de explosión, dichas áreas deben estar equipadas con sistema de protección y detección de explosiones dentro del distribuidor. (aplicable para GLP, Diesel, equipos eléctricos, baterias de litio, aceites, grasas y/o lubricantes) | H12: R2.3.1 - Evaluación de riesgo de la instalación realizada para identificar áreas con potencial riesgo de explosión. Se realizo carga de fuego que cubra todas áreas del distribuidor R2.3.2 - Áreas con potencial de explosión equipadas con sistema de detección y/o programas de monitoreo y gestión. R2.3.3 - Los controles están disponibles para áreas con potencial de explosión. R2.3.4 - Cuando se utiliza un sistema de detección, es inspeccionado por los operadores con una intervención rutinaria debidamente documentada. | I12: 5 - Todos los requisitos cumplieron 3 - R2.3.1, R2.3.2 y R2.3.3 se cumplieron pero R2.3.4 no se cumplieron 1 - R2.3.1 y R2.3.2 no se cumplieron 0 - R2.3.1 no se cumplieron | J12: 1. Revisar la evaluación de riesgo para comprobar si se han identificado zonas con potencial de explosión. 2. Compruebe si existe un programa de seguimiento y gestión y un sistema de detección. 3. Compruebe si existen controles. 4. Hable con los operadores y pregunte sobre estas áreas y si siguen las rutinas de intervención. | L12: =IF(AND(M12="N/A",N12="N/A"),"N/A",IF(OR(M12="",N12=""),"",SMALL(M12:N12,1))) -> 0 | M12: 0 | N12: N/A | O12: =IF(AND(P12="N/A",Q12="N/A"),"N/A",IF(OR(P12="",Q12=""),"",SMALL(P12:Q12,1))) -> 0 | P12: 0 | Q12: N/A | R12: =IF(OR(L12="",O12=""),"",IF(AND(L12="N/A",O12="N/A"),"N/A",AVERAGE(L12,O12))) -> 0
A13: 7_1_33_109 | B13: GESTIÓN DE PROCESOS DE ALTO RIESGO | C13: 2.4 | D13: Gestión de sistemas eléctricos | E13: SÍ | F13: 1 | G13: Documente gestión de sistemas eléctricos. | H13: R2.4.1 - No se observaron violaciones eléctricas - Sistemas/equipos eléctricos mantenidos en buenas condiciones y seguros. Plan de acción por el analisis de puesta a tierra, deben mirar las conclusiones identificadas en los resultados. R2.4.2 - Permisos de trabajo eléctrico completados. R2.4.3 - Todos los trabajos eléctricos completados por un empleado calificado propio o externo. | I13: 5 - Todos los requisitos se cumplieron sin violaciones 3 - R2.4.3 cumplió y 1 violación de R2.4.1 o R2.4.2 1 - R2.4.3 cumplió y 2-3 violaciones totales de R2.4.1 o R2.4.2 0 - R2.4.3 no cumplió o >3 violaciones totales de R2.4.1 o R2.4.2 | J13: 1. Revisar las instalaciones y comprobar el estado de los sistemas/equipos eléctricos (conductos eléctricos, tapas de salida faltantes, cubiertas de paneles no aseguradas, cableado expuesto, etc). 2. Revisar los permisos de trabajo y los proyectos, comprobar si se ha completado. 3. Comprobar si hay trabajos eléctricos realizados por trabajadores no cualificados. | L13: =IF(AND(M13="N/A",N13="N/A"),"N/A",IF(OR(M13="",N13=""),"",SMALL(M13:N13,1))) -> 0 | M13: 0 | N13: N/A | O13: =IF(AND(P13="N/A",Q13="N/A"),"N/A",IF(OR(P13="",Q13=""),"",SMALL(P13:Q13,1))) -> 0 | P13: 0 | Q13: N/A | R13: =IF(OR(L13="",O13=""),"",IF(AND(L13="N/A",O13="N/A"),"N/A",AVERAGE(L13,O13))) -> 0
B14: SEGURIDAD EN EL TRANSPORTE EN EL LUGAR DE TRABAJO | L14: =IF(COUNTIF(L15:L18,"=N/A")=4,"N/A", ((N(L15)*$F15)+(N(L16)*$F16)+(N(L17)*$F17)+(N(L18)*$F18))/(IF(L15="N/A",0,(5*$F15))+IF(L16="N/A",0,(5*$F16))+IF(L17="N/A",0,(5*$F17))+IF(L18="N/A",0,(5*$F18)))) -> 0 | M14: =IF(COUNTIF(M15:M21,"=N/A")=4,"N/A", ((N(M15)*$F15)+(N(M16)*$F16)+(N(M17)*$F17)+(N(M18)*$F18)+(N(M19)*$F19)+(N(M20)*$F20)+(N(M21)*$F21))/(IF(M15="N/A",0,(5*$F15))+IF(M16="N/A",0,(5*$F16))+IF(M17="N/A",0,(5*$F17))+IF(M18="N/A",0,(5*$F18))+IF(M19="N/A",0,(5*$F19))+IF(M20="N/A",0,(5*$F20))+IF(M21="N/A",0,(5*$F21)))) -> 0 | N14: =IF(COUNTIF(N15:N21,"=N/A")=4,"N/A", ((N(N15)*$F15)+(N(N16)*$F16)+(N(N17)*$F17)+(N(N18)*$F18)+(N(N19)*$F19)+(N(N20)*$F20)+(N(N21)*$F21))/(IF(N15="N/A",0,(5*$F15))+IF(N16="N/A",0,(5*$F16))+IF(N17="N/A",0,(5*$F17))+IF(N18="N/A",0,(5*$F18))+IF(N19="N/A",0,(5*$F19))+IF(N20="N/A",0,(5*$F20))+IF(N21="N/A",0,(5*$F21)))) -> #DIV/0! | O14: =IF(COUNTIF(O15:O21,"=N/A")=4,"N/A", ((N(O15)*$F15)+(N(O16)*$F16)+(N(O17)*$F17)+(N(O18)*$F18)+(N(O19)*$F19)+(N(O20)*$F20)+(N(O21)*$F21))/(IF(O15="N/A",0,(5*$F15))+IF(O16="N/A",0,(5*$F16))+IF(O17="N/A",0,(5*$F17))+IF(O18="N/A",0,(5*$F18))+IF(O19="N/A",0,(5*$F19))+IF(O20="N/A",0,(5*$F20))+IF(O21="N/A",0,(5*$F21)))) -> 0 | P14: =IF(COUNTIF(P15:P21,"=N/A")=4,"N/A", ((N(P15)*$F15)+(N(P16)*$F16)+(N(P17)*$F17)+(N(P18)*$F18)+(N(P19)*$F19)+(N(P20)*$F20)+(N(P21)*$F21))/(IF(P15="N/A",0,(5*$F15))+IF(P16="N/A",0,(5*$F16))+IF(P17="N/A",0,(5*$F17))+IF(P18="N/A",0,(5*$F18))+IF(P19="N/A",0,(5*$F19))+IF(P20="N/A",0,(5*$F20))+IF(P21="N/A",0,(5*$F21)))) -> 0 | Q14: =IF(COUNTIF(Q15:Q21,"=N/A")=4,"N/A", ((N(Q15)*$F15)+(N(Q16)*$F16)+(N(Q17)*$F17)+(N(Q18)*$F18)+(N(Q19)*$F19)+(N(Q20)*$F20)+(N(Q21)*$F21))/(IF(Q15="N/A",0,(5*$F15))+IF(Q16="N/A",0,(5*$F16))+IF(Q17="N/A",0,(5*$F17))+IF(Q18="N/A",0,(5*$F18))+IF(Q19="N/A",0,(5*$F19))+IF(Q20="N/A",0,(5*$F20))+IF(Q21="N/A",0,(5*$F21)))) -> #DIV/0! | R14: =IF(COUNTIF(R15:R21,"=N/A")=4,"N/A", ((N(R15)*$F15)+(N(R16)*$F16)+(N(R17)*$F17)+(N(R18)*$F18)+(N(R19)*$F19)+(N(R20)*$F20)+(N(R21)*$F21))/(IF(R15="N/A",0,(5*$F15))+IF(R16="N/A",0,(5*$F16))+IF(R17="N/A",0,(5*$F17))+IF(R18="N/A",0,(5*$F18))+IF(R19="N/A",0,(5*$F19))+IF(R20="N/A",0,(5*$F20))+IF(R21="N/A",0,(5*$F21)))) -> 0
A15: 7_1_34_110 | B15: SEGURIDAD EN EL TRANSPORTE EN EL LUGAR DE TRABAJO | C15: 3.1 | D15: Gestión del plan de tráfico | E15: No | F15: 1 | G15: Finalidad: definir el flujo de tráfico y los controles dentro de las instalaciones y el patio de camiones y comunicarlo visualmente a todos los empleados. El plan de tráfico debe utilizarse como medio visual de resolución de problemas y actualizarse cuando se identifiquen nuevos riesgos.. | H15: R3.1.1 - Plan de tráfico implementado. Circulación clara, apilabilidad correspondiente, sendas perimetrales, reductores de velcidad en portones. R3.1.2 - Layout con el plan de tráfico publicado en un área accesible. R3.1.3 - Operadores conscientes del plan de tráfico. R3.1.4 - Señalización suficiente de las normas de seguridad descritas en el plan de tráfico. Identificar zonas habilitadas para fumadores en caso de aplicar. R3.1.5 - Zona Cero al momento del ingreso al almacén, el mismo debe contar con carteleras acerca del layout y debe ser presentado por la operación al momento de una inducción para el ingreso de visitas, auditorias. (Cruzar con almacén) | I15: 5 - Todos los requisitos cumplen 3 - R3.1.1, R3.1.2 y R3.1.4 cumplen 1 - R3.1.1 y R3.1.2 cumplen 0 - R3.1.1 no cumplen | J15: 1. Revise el plan de tráfico establecido por el sitio. 2. Compruebe si el diseño con el plan de tráfico está publicado en áreas donde la gente puede acceder. 3. Hablar con los operadores para asegurarse de que conocen el plan y pueden consultar los detalles del mismo. 4. Compruebe si hay señalización suficiente para cumplir las normas de seguridad establecidas en el plan general de tráfico. | L15: =IF(AND(M15="N/A",N15="N/A"),"N/A",IF(OR(M15="",N15=""),"",SMALL(M15:N15,1))) -> 0 | M15: 0 | N15: N/A | O15: =IF(AND(P15="N/A",Q15="N/A"),"N/A",IF(OR(P15="",Q15=""),"",SMALL(P15:Q15,1))) -> 0 | P15: 0 | Q15: N/A | R15: =IF(OR(L15="",O15=""),"",IF(AND(L15="N/A",O15="N/A"),"N/A",AVERAGE(L15,O15))) -> 0
A16: 7_1_34_111 | B16: SEGURIDAD EN EL TRANSPORTE EN EL LUGAR DE TRABAJO | C16: 3.2 | D16: Carga y descarga de forma segura | E16: No | F16: 1 | G16: Propósito: Un proceso escrito para la carga y descarga debe estar disponible para los empleados. La adhesión a este proceso debe mantenerse a través de nuestras rutinas de Observación del Trabajo Diario (OWD) y sesiones de entrenamiento. Un control que impide físicamente que el vehículo pueda moverse es el estilo de control más robusto. Un candado gladhand es un control simple y económico que impide físicamente que un camión se mueva durante la carga o descarga. | H16: R3.2.1 - Procedimiento de carga/descarga escrito, completo y disponible para los empleados. Dentro del procedimiento, se deben identificar la zona segura del chofer y se debe cumplor 100% (debe contar con segregación) R3.2.2 - Proceso de carga/descarga bien ejecutado (Los neumáticos están bloqueados/asegurados por trabaruedas que son colocados por autoelevadores, las llaves están controladas, los operadores de vehículos están libres de interacción y los operadores de autoelevadores son dueños del proceso). R3.2.3 - Los operadores de autoelevadores controlan completamente la operación de carga/descarga. R3.2.4 - Entrenamiento completo para asegurar que los operadores lleven a cabo la carga/descarga respetando el procedimiento. R3.2.5 - La dirección lleva a cabo los procedimientos de carga/descarga. | I16: 5 - Se cumplieron todos los requisitos y mejoró la tendencia en resultados de coaching/OWD 3 - Todos los requisitos se cumplieron pero los resultados de coaching/OWD no mostraron tendencia de mejora 1 - R3.2.1 y R3.2.3 se cumplieron pero R3.2.2 no se cumplió (un potencial SIF o SIF Actual relacionado con R3.2.2) 0 - R3.1 o R3.3 no se cumplió | J16: 1. Revisar el proceso de carga/descarga: comprobar si está documentado en un SOP. 2. Observe el proceso de carga/descarga: compruebe si el proceso se ejecuta como está documentado (compruebe si el camión está asegurado mediante trabaruedas y control de llave). 3. Compruebe si existe la posibilidad de que el camión se mueva y que el conductor del camión o el conductor del autoelevador resulten heridos. 4. Compruebe la Gestión de Incidentes: ¿ha habido un Potencial SIF o SIF Actual relacionado con reglas de operación seguras que no se siguen? 5. Compruebe el registro de entrenamiento de la instalación - compruebe si hay entrenamiento en la carga/ descarga (positivo y correctivo). 6. Comprobar las OWD de la instalación - comprobar si se están realizando diagnósticos sobre los procedimientos de carga/descarga. | L16: =IF(AND(M16="N/A",N16="N/A"),"N/A",IF(OR(M16="",N16=""),"",SMALL(M16:N16,1))) -> 0 | M16: 0 | N16: N/A | O16: =IF(AND(P16="N/A",Q16="N/A"),"N/A",IF(OR(P16="",Q16=""),"",SMALL(P16:Q16,1))) -> 0 | P16: 0 | Q16: N/A | R16: =IF(OR(L16="",O16=""),"",IF(AND(L16="N/A",O16="N/A"),"N/A",AVERAGE(L16,O16))) -> 0
A17: 7_1_34_112 | B17: SEGURIDAD EN EL TRANSPORTE EN EL LUGAR DE TRABAJO | C17: 3.3 | D17: Utilización segura de equipos industriales motorizados | E17: No | F17: 1 | G17: Proposito: garantizar que los equipos funcionen de forma segura en nuestras operaciones. Los procedimientos de funcionamiento seguro deben recogerse en un procedimiento escrito y estar a disposición de los empleados. La adherencia a estos procedimientos debe mantenerse a través de nuestras rutinas de formación y OWD. | H17: R3.3.1 - Reglas de operación seguras para equipos motorizados son seguidas por los conductores (usando bocinas, siguiendo los límites de velocidad, acercándose a las intersecciones con precaución, revisando espejos convexos, respetando los requisitos de segregacion, vehículos debidamente desactivados). Los equipos , autoelevadores/apiladoras eléctricas cumplen con el estandar correctamente. y so conducidos correctamente, no circulan fuera del distribuidor R3.3.2 -Habilitaciones anuales del conductor completadas y documentadas. R3.3.3 - Entrenamiento completo para asegurar que los operadores operen equipos motorizados de acuerdo con las reglas de operación seguras. R3.3.4- Se realiza un chequeo por turno , diario del autoelevador. R3.3.5 - La gerencia conduce OWD para equipamientos motorizados de acuerdo con las reglas de operación seguras. | I17: 5 - Se cumplieron todos los requisitos y se mejoró la tendencia en resultados de coaching/OWD 3 - Se cumplieron todos los requisitos pero no hay evolucion en los resultados de coaching/OWD 1 - R3.3.2 cumplió pero R3.3.1 no cumplió (se produjo un SIF potencial o SIF real relacionado con R3.3.1) 0 - R3.3.2 y R3.3.1 no se cumplió | J17: 1.- Observar la operación de los Equipos de Transporte Industrial, autoelevadores. Verificar si los conductores operan de manera segura, utilizando bocinas, respetando los límites de velocidad, aproximándose a las intersecciones con precaución, verificando espejos, respetando los requisitos de separación y desactivando adecuadamente el vehículo. 2.- Revisar la herramienta de Gestión de Incidentes: ¿se ha registrado algún Incidente Crítico Potencial (SIF Potential) o Incidente Crítico Real (SIF Actual) relacionado con el incumplimiento de las reglas de operación segura? 3.- Revisar la documentación de la revisión anual. La documentación debe estar cerrada dentro del año en curso o un máximo de 13 meses en relación con la emisión anterior. 4.- Verificar el registro de entrenamiento del centro: revisar si hay entrenamiento sobre las reglas seguras de operación de los equipos de transporte industrial (tanto positivo como correctivo). 5.- Revisar las Observaciones del Trabajo Diario (OWDs) del centro: verificar si se están realizando diagnósticos sobre las reglas seguras de operación de los equipos de transporte industrial. | L17: =IF(AND(M17="N/A",N17="N/A"),"N/A",IF(OR(M17="",N17=""),"",SMALL(M17:N17,1))) -> 0 | M17: 0 | N17: N/A | O17: =IF(AND(P17="N/A",Q17="N/A"),"N/A",IF(OR(P17="",Q17=""),"",SMALL(P17:Q17,1))) -> 0 | P17: 0 | Q17: N/A | R17: =IF(OR(L17="",O17=""),"",IF(AND(L17="N/A",O17="N/A"),"N/A",AVERAGE(L17,O17))) -> 0
A18: 7_1_34_113 | B18: SEGURIDAD EN EL TRANSPORTE EN EL LUGAR DE TRABAJO | C18: 3.4 | D18: Gestión de seguridad de los peatones | E18: SÍ | F18: 1 | G18: Propósito: Debemos eliminar la interacción con peatones en nuestros almacenes y patios. Esto incluye la interacción con peatones que se produce cuando alguien estaba en un equipo industrial motorizado y se bajó por cualquier motivo. Si va a haber acceso peatonal a una parte de nuestras operaciones, debemos implementar controles de ingeniería para separar a esos peatones de los equipos motorizados. También debemos asegurarnos de que nunca se permita que equipos diferentes interactúen entre sí. | H18: R3.4.1 - Controles de ingeniería para eliminar la interacción potencial de peatones. (deben estar incluidas todas las áreas con potencial de riesgo en el distribuidor) | I18: 5 - Eliminación de la interacción peatonal mediante controles de ingeniería (barreras, puertas, sirenas, sistemas sonoros, semaforos). 3 - Interacción peatonal controlada con algunos controles de ingenieria PERO principalmente a traves de controles administrativos (proceso) 1 - Control de la interacción peatonal únicamente mediante medidas administrativas 0 - Interacción peatonal incontrolada en el almacén o patio, se visualizan comportamientos criticos inseguros y se podrá cobrar y Anular la pregunta. | J18: Revisar el plan/sistemas de tráfico implementados en el área: Verificar si hay controles de ingeniería que lo hacen casi imposible/difícil de evitar (Comprobar si la interacción peatonal se ELIMINA siempre que sea posible. Verificar si hay barricadas significativas para evitar que los empleados sean golpeados en pasillos. Comprobar si las áreas de transición están protegidas por barreras para evitar la entrada de vehículos elevadores). Verificar si se observa a peatones dentro de los 5 metros de un montacargas en movimiento (interacción peatonal no controlada). | L18: =IF(AND(M18="N/A",N18="N/A"),"N/A",IF(OR(M18="",N18=""),"",SMALL(M18:N18,1))) -> 0 | M18: 0 | N18: N/A | O18: =IF(AND(P18="N/A",Q18="N/A"),"N/A",IF(OR(P18="",Q18=""),"",SMALL(P18:Q18,1))) -> 0 | P18: 0 | Q18: N/A | R18: =IF(OR(L18="",O18=""),"",IF(AND(L18="N/A",O18="N/A"),"N/A",AVERAGE(L18,O18))) -> 0
A19: 7_1_34_114 | B19: SEGURIDAD EN EL TRANSPORTE EN EL LUGAR DE TRABAJO | C19: 3.5 | D19: Inspección previa al uso de equipos industriales motorizados y ejecucion segura | E19: No | F19: 1 | G19: Propósito: debemos definir el proceso para completar las inspecciones previas a los turnos de nuestros equipos industriales motorizados, proporcionar estos procedimientos a nuestros equipos y garantizar el cumplimiento de estos procedimientos mediante nuestras rutinas de formación y OWD. | H19: R3.5.1 - Proceso establecido para evaluar equipos motorizados. R3.5.2 - Identificación de elementos críticos en la inspección previa al uso. Se debe realizar un checklist previo al uso, por turno. R3.5.3 - El equipo se retira de servicio si se observan deficiencias y se corrigen antes del próximo uso. R3.5.4 - Documentación de las inspecciones disponible para todos los equipos de transporte industrial (zorras, paleteras, transpaletas) y mantenida según el protocolo. (Tener SOP y OPL) R3.5.5 - Capacitación completada para garantizar que los operadores utilicen equipos de transporte industrial motorizados de acuerdo con el proceso de inspección previa al uso. R3.5.6 - La gerencia realiza Observaciones del Trabajo Diario (OWD) a los equipos de transporte industrial motorizados de acuerdo con el proceso de inspección previa al uso. | I19: Nivel 5 - Todos los requisitos cumplidos Y tendencia positiva en los resultados de coaching/ (OWD). Nivel 3 - Todos los requisitos cumplidos, PERO los resultados de coaching/OWD no muestran una tendencia positiva. Nivel 1 - Se cumplen R3.5.1, R3.5.2 y R3.5.3, PERO no se cumple R3.5.4. Nivel 0 - No se cumplen R3.5.1, R3.5.2 O R3.5.3. | J19: 1.-Verificar si hay un proceso documentado de inspección previa al uso en marcha. 2.-Hablar con los operadores para asegurarse de que estén informados sobre los elementos críticos y que no operen si los elementos críticos no están en buen estado de funcionamiento. 3.-Verificar si hay deficiencias en los vehículos de transporte industrial/equipos y si se corrigen antes del próximo uso. 4.-Revisar documentos de inspección y verificar si están disponibles. 5.-Revisar el registro de entrenamiento del centro: verificar si hay entrenamiento sobre el proceso de inspección previa al uso (tanto positivo como correctivo). 6.-Revisar las Observaciones del Trabajo Diario (OWDs) del centro: verificar si se están realizando diagnósticos sobre el proceso de inspección previa al uso | L19: =IF(AND(M19="N/A",N19="N/A"),"N/A",IF(OR(M19="",N19=""),"",SMALL(M19:N19,1))) -> 0 | M19: 0 | N19: N/A | O19: =IF(AND(P19="N/A",Q19="N/A"),"N/A",IF(OR(P19="",Q19=""),"",SMALL(P19:Q19,1))) -> 0 | P19: 0 | Q19: N/A | R19: =IF(OR(L19="",O19=""),"",IF(AND(L19="N/A",O19="N/A"),"N/A",AVERAGE(L19,O19))) -> 0
A20: 7_1_34_115 | B20: SEGURIDAD EN EL TRANSPORTE EN EL LUGAR DE TRABAJO | C20: 3.6 | D20: Ejecución Segura de control de llaves | E20: SÍ | F20: 1 | G20: Proposito: debemos definir el proceso de control de llaves/acceso a vehículos para evitar movimientos inesperados. Estos procedimientos deben estar a disposición del equipo y debemos garantizar el cumplimiento del proceso a través de nuestras rutinas de OWD y coaching. | H20: R3.6.1 - Proceso de control de llaves escrito, completo y disponible para los empleados. R3.6.2 - Operadores que ejecutan el control de llaves en cumplimiento del proceso. R3.6.3 - Entrenamiento completo para asegurar que los operadores ejecuten el procedimiento de control de llaves. R3.6.4 - La gerencia conduce OWD a los procedimientos de control de llaves. | I20: 5 - Se cumplieron todos los requisitos y se mejoró la tendencia en resultados de coaching/OWD 3 - Se cumplieron todos los requisitos pero no hay mejora en los resultados de coaching/OWD 1 - R3.6.1 cumplió pero R3.6.2 no cumplió (se produjo un SIF potencial o SIF real relacionado con R3.6.2) 0 - R3.6.1 no se cumple | J20: 1. Compruebe el proceso de control de llaves y si hay lagunas visibles en el procedimiento. Hable con los operadores para asegurarse de que entienden el proceso de control llave. 2. Compruebe los vehículos estacionados para ver si las llaves están colocadas y controladas (compruebe si es posible que lleve una llave). 3. Compruebe el Herramienta de Gestión de Incidentes: ¿ha habido un SIF potencial o SIF actual relacionado con reglas de funcionamiento seguras que no se siguen? 4. Compruebe el registro de entrenamiento de la instalación - compruebe si hay entrenamiento en el control de la llave (positivo y correctivo). 5. Comprobar las OWD de las instalaciones - comprobar si se están realizando diagnósticos en procedimientos de control de llaves. | L20: =IF(AND(M20="N/A",N20="N/A"),"N/A",IF(OR(M20="",N20=""),"",SMALL(M20:N20,1))) -> 0 | M20: 0 | N20: N/A | O20: =IF(AND(P20="N/A",Q20="N/A"),"N/A",IF(OR(P20="",Q20=""),"",SMALL(P20:Q20,1))) -> 0 | P20: 0 | Q20: N/A | R20: =IF(OR(L20="",O20=""),"",IF(AND(L20="N/A",O20="N/A"),"N/A",AVERAGE(L20,O20))) -> 0
A21: 7_1_34_116 | B21: SEGURIDAD EN EL TRANSPORTE EN EL LUGAR DE TRABAJO | C21: 3.7 | D21: Gestión de puertas muelles | E21: No | F21: 1 | G21: Documentar procedimiento de Seguridad en el Transporte Laboral. | H21: R3.7.1 - Todas las puertas de muelle se mantienen en buenas condiciones y cumplen con el protocolo. R3.7.2 - Sistema de anticaídas implementado o la puerta está diseñada para fallar abierta. R3.7.3 - Rutina de mantenimiento preventivo implementada. | I21: Nivel 5 - Todos los requisitos cumplidos Y todas las acciones actuales del Rutina de Mantenimiento Preventivo. Nivel 3 - Todos los requisitos cumplidos PERO <100% de las acciones actuales de la Rutina de Mantenimiento Preventivo. Nivel 1 - Se cumplen R3.7.1 y R3.7.2, PERO no se cumple R3.7.3. Nivel 0 - No se cumple R3.7.1. | J21: 1.-Observar las puertas del muelle: verificar si están en buen estado. 2.-Verificar si están diseñadas para fallar abiertas o si existe la posibilidad de fallar y cerrarse sobre un operador. 3.-Verificar si hay una Rutina de Mantenimiento Preventivo implementada. | L21: =IF(AND(M21="N/A",N21="N/A"),"N/A",IF(OR(M21="",N21=""),"",SMALL(M21:N21,1))) -> 0 | M21: 0 | N21: N/A | O21: =IF(AND(P21="N/A",Q21="N/A"),"N/A",IF(OR(P21="",Q21=""),"",SMALL(P21:Q21,1))) -> 0 | P21: 0 | Q21: N/A | R21: =IF(OR(L21="",O21=""),"",IF(AND(L21="N/A",O21="N/A"),"N/A",AVERAGE(L21,O21))) -> 0
B22: MANIPULACIÓN DE MATERIALES Y ERGONOMÍA | L22: =IF(COUNTIF(L23:L26,"=N/A")=4,"N/A", ((N(L23)*$F23)+(N(L24)*$F24)+(N(L25)*$F25)+(N(L26)*$F26))/(IF(L23="N/A",0,(5*$F23))+IF(L24="N/A",0,(5*$F24))+IF(L25="N/A",0,(5*$F25))+IF(L26="N/A",0,(5*$F26)))) -> 0 | M22: =IF(COUNTIF(M23:M25,"=N/A")=4,"N/A", ((N(M23)*$F23)+(N(M24)*$F24)+(N(M25)*$F25))/(IF(M23="N/A",0,(5*$F23))+IF(M24="N/A",0,(5*$F24))+IF(M25="N/A",0,(5*$F25)))) -> 0 | N22: =IF(COUNTIF(N23:N25,"=N/A")=4,"N/A", ((N(N23)*$F23)+(N(N24)*$F24)+(N(N25)*$F25))/(IF(N23="N/A",0,(5*$F23))+IF(N24="N/A",0,(5*$F24))+IF(N25="N/A",0,(5*$F25)))) -> #DIV/0! | O22: =IF(COUNTIF(O23:O25,"=N/A")=4,"N/A", ((N(O23)*$F23)+(N(O24)*$F24)+(N(O25)*$F25))/(IF(O23="N/A",0,(5*$F23))+IF(O24="N/A",0,(5*$F24))+IF(O25="N/A",0,(5*$F25)))) -> 0 | P22: =IF(COUNTIF(P23:P25,"=N/A")=4,"N/A", ((N(P23)*$F23)+(N(P24)*$F24)+(N(P25)*$F25))/(IF(P23="N/A",0,(5*$F23))+IF(P24="N/A",0,(5*$F24))+IF(P25="N/A",0,(5*$F25)))) -> 0 | Q22: =IF(COUNTIF(Q23:Q25,"=N/A")=4,"N/A", ((N(Q23)*$F23)+(N(Q24)*$F24)+(N(Q25)*$F25))/(IF(Q23="N/A",0,(5*$F23))+IF(Q24="N/A",0,(5*$F24))+IF(Q25="N/A",0,(5*$F25)))) -> #DIV/0! | R22: =IF(COUNTIF(R23:R25,"=N/A")=4,"N/A", ((N(R23)*$F23)+(N(R24)*$F24)+(N(R25)*$F25))/(IF(R23="N/A",0,(5*$F23))+IF(R24="N/A",0,(5*$F24))+IF(R25="N/A",0,(5*$F25)))) -> 0
A23: 7_1_35_118 | B23: MANIPULACIÓN DE MATERIALES Y ERGONOMÍA | C23: 4.1 | D23: Ejecución segura de manipulación manual de materiales | E23: No | F23: 1 | G23: Proposito: garantizar que se aplican las técnicas de elevación y la configuración del puesto de trabajo adecuadas para evitar lesiones. | H23: R4.1.1 - Prácticas de elevación seguras implementadas durante la manipulación manual de materiales según lo definido. R4.1.2 - Estación de trabajo evaluada con controles/soluciones ergonómicas adecuadas identificadas. Resolución 886/15 (estudio de ergonomia) R4.1.3 - Plan de acción para cerrar las brechas en los controles ergonómicos de los puestos de trabajo. | I23: 5 - Todos los requisitos cumplen y 0 lesiones relacionadas con la manipulación manual de materiales 3 - R4.1.2, R4.1.3 se cumplen y no más de 1 lesión relacionada con la manipulación manual de materiales 1 - R4.1.2 se cumple pero R4.1.3 no está en proceso o > 1 lesión relacionada con la manipulación manual de materiales 0 - R4.1.2 no se cumple | J23: 1. Comprobar si los operadores aplican prácticas de elevación seguras durante la manipulación manual de materiales tal como se define en el protocolo. 2. Observar los puestos de trabajo para evaluar si cumplen los controles ergonómicos definidos en la evaluación de riesgos de instalaciones/zonas - con adecuaciones ergonomicas realizadas. 3. Compruebe la herramienta de notificación de incidentes - compruebe si hay lesiones relacionadas con la manipulación manual de materiales. Compruebe si hay un plan de acción para cerrar las brechas. | L23: =IF(AND(M23="N/A",N23="N/A"),"N/A",IF(OR(M23="",N23=""),"",SMALL(M23:N23,1))) -> 0 | M23: 0 | N23: N/A | O23: =IF(AND(P23="N/A",Q23="N/A"),"N/A",IF(OR(P23="",Q23=""),"",SMALL(P23:Q23,1))) -> 0 | P23: 0 | Q23: N/A | R23: =IF(OR(L23="",O23=""),"",IF(AND(L23="N/A",O23="N/A"),"N/A",AVERAGE(L23,O23))) -> 0
A24: 7_1_35_119 | B24: MANIPULACIÓN DE MATERIALES Y ERGONOMÍA | C24: 4.2 | D24: Gestión de equipos de elevación mecánica, racks y estantes | E24: No | F24: 1 | G24: Proposito: garantizar que los equipos de elevación se inspeccionan y mantienen adecuadamente. Esto también garantiza que las estanterías de la instalación se inspeccionen, mantengan y utilicen adecuadamente. | H24: R4.2.1 - Inspecciones anuales documentadas de todos los equipos de elevación. (racks, estanterias) R4.2.2 - Registro de acciones para completar cualquier problema que se encuentre en la inspección anual. R4.2.3 Inspecciones trimestrales documentadas para todas las estanterías y racks. R4.2.4 Inspecciones anuales documentadas para todas las estanterías y racks. R4.2.5 Registro de acciones para completar cualquier problema como se encuentra en las inspecciones trimestrales y anuales. R4.2.6 - Asegurar estandar de racks y estanterias (OPL, etiquetado con capacidad máxima, condiciones optimas, analisis de bastidores chocados, cobertores en los extremos de bastidores y transversales, red de contención para racks). R4.2.7 - Operadores conscientes de los puntos críticos y qué hacer si un punto crítico no está en condiciones de funcionar. R4.2.8 - Si se detectan problemas, el equipo de elevación se retira del servicio y se corrige antes del próximo uso. | I24: 5 - Todos los requisitos cumplieron 3 - Todos los requisitos excepto 4.2.7 cumplieron 1 - R4.2.1, R4.2.3, R4.2.4, R4.2.6 y R4.2.8 pero R4.2.2 o R4.2.5 no actualizados 0 - R4.2.1, R4.2.3, R4.2.4, R4.2.6 o R4.8 no cumplió | J24: 1. Revisar los documentos de inspección anuales tanto para el equipo de elevación como para los racks y estantes; comprobar si la inspección ha sido completada por una parte cualificada según los requisitos legales locales. 2. Examinar los documentos de inspección trimestrales para comprobar si el equipo está cualificado para hacerlo 3. Comprobar si hay resultados en las inspecciones anuales, revisar el registro de medidas para cerrar las lagunas y comprobar si está actualizado. 4. Hablar con los operadores: comprobar que puedan explicar el proceso de inspección previo al uso. 5. Comprobar si los operadores conocen los puntos críticos y qué hacer si no funcionan. 6. Comprobar si el aparato de elevación presenta deficiencias en los puntos críticos y si está en servicio. | L24: =IF(AND(M24="N/A",N24="N/A"),"N/A",IF(OR(M24="",N24=""),"",SMALL(M24:N24,1))) -> 0 | M24: 0 | N24: N/A | O24: =IF(AND(P24="N/A",Q24="N/A"),"N/A",IF(OR(P24="",Q24=""),"",SMALL(P24:Q24,1))) -> 0 | P24: 0 | Q24: N/A | R24: =IF(OR(L24="",O24=""),"",IF(AND(L24="N/A",O24="N/A"),"N/A",AVERAGE(L24,O24))) -> 0
A25: 7_1_35_120 | B25: MANIPULACIÓN DE MATERIALES Y ERGONOMÍA | C25: 4.3 | D25: Ejecución segura de equipos de elevación mecánica | E25: SÍ | F25: 1 | G25: Propósito: Garantizar que el equipo de elevación se utilice correctamente siguiendo un procedimiento escrito disponible para los empleados. El cumplimiento del protocolo debe mantenerse a través de nuestras rutinas de Observación del Trabajo Diario (OWD) y sesiones de entrenamiento. El término "equipo de elevación" se refiere de manera general a cualquier equipo que pueda utilizarse para levantar y bajar cargas (ejemplos: gato hidráulico, plataformas elevadoras y grúas). En esta solicitud, los elementos en la pregunta 3.5 no serán evaluados. | H25: R4.3.1 - Procedimientos de equipos de elevación escritos, completos y disponibles para los empleados. R4.3.2 - Operadores ejecutan equipos de elevación siguiendo el procedimiento. R4.3.3 - Coaching completado para garantizar que los operadores ejecuten equipos de elevación de acuerdo con el procedimiento. R4.3.4 - La gerencia realiza Observaciones del Trabajo Diario (OWD) a los procedimientos de equipos de elevación. | I25: Nivel 5 - Todos los requisitos cumplidos Y tendencia positiva en los resultados de coaching/Observaciones del Trabajo Diario (OWD). Nivel 3 - Todos los requisitos cumplidos, PERO los resultados de coaching/OWD no muestran una tendencia positiva. Nivel 1 - Se cumple R4.3.1, PERO no se cumple R4.3.2 (ha ocurrido un Incidente Crítico Potencial o Incidente Crítico Real relacionado con R4.3.2). Nivel 0 - No se cumple R4.3.1. | J25: Verificar si los procedimientos de equipos de elevación están escritos, completos y disponibles para los empleados. 1.-Observar a los operadores utilizando equipos de elevación: verificar si los operadores siguen de manera segura los procedimientos de equipos de elevación. 2.-Revisar la Gestión de Incidentes: ¿ha habido un Incidente Crítico Potencial o Incidente Crítico Real relacionado con el incumplimiento de las reglas de operación segura? 3.-Verificar el registro de entrenamiento del centro: verificar si hay entrenamiento sobre la ejecución de equipos de elevación (tanto positivo como correctivo). 4.-Revisar las Observaciones del Trabajo Diario (OWDs) del centro: verificar si se están realizando diagnósticos sobre los procedimientos de equipos de elevación. | L25: =IF(AND(M25="N/A",N25="N/A"),"N/A",IF(OR(M25="",N25=""),"",SMALL(M25:N25,1))) -> 0 | M25: 0 | N25: N/A | O25: =IF(AND(P25="N/A",Q25="N/A"),"N/A",IF(OR(P25="",Q25=""),"",SMALL(P25:Q25,1))) -> 0 | P25: 0 | Q25: N/A | R25: =IF(OR(L25="",O25=""),"",IF(AND(L25="N/A",O25="N/A"),"N/A",AVERAGE(L25,O25))) -> 0
B26: SUSTANCIAS PELIGROSAS | L26: =IF(COUNTIF(L27:L32,"=N/A")=6,"N/A", ((N(L27)*$F27)+(N(L28)*$F28)+(N(L29)*$F29)+(N(L30)*$F30)+(N(L31)*$F31)+(N(L32)*$F32))/(IF(L27="N/A",0,(5*$F27))+IF(L28="N/A",0,(5*$F28))+IF(L29="N/A",0,(5*$F29))+IF(L30="N/A",0,(5*$F30))+IF(L31="N/A",0,(5*$F31))+IF(L32="N/A",0,(5*$F32)))) -> 0 | M26: =IF(COUNTIF(M27:M32,"=N/A")=6,"N/A", ((N(M27)*$F27)+(N(M28)*$F28)+(N(M29)*$F29)+(N(M30)*$F30)+(N(M31)*$F31)+(N(M32)*$F32))/(IF(M27="N/A",0,(5*$F27))+IF(M28="N/A",0,(5*$F28))+IF(M29="N/A",0,(5*$F29))+IF(M30="N/A",0,(5*$F30))+IF(M31="N/A",0,(5*$F31))+IF(M32="N/A",0,(5*$F32)))) -> 0 | N26: =IF(COUNTIF(N27:N32,"=N/A")=6,"N/A", ((N(N27)*$F27)+(N(N28)*$F28)+(N(N29)*$F29)+(N(N30)*$F30)+(N(N31)*$F31)+(N(N32)*$F32))/(IF(N27="N/A",0,(5*$F27))+IF(N28="N/A",0,(5*$F28))+IF(N29="N/A",0,(5*$F29))+IF(N30="N/A",0,(5*$F30))+IF(N31="N/A",0,(5*$F31))+IF(N32="N/A",0,(5*$F32)))) -> N/A | O26: =IF(COUNTIF(O27:O32,"=N/A")=6,"N/A", ((N(O27)*$F27)+(N(O28)*$F28)+(N(O29)*$F29)+(N(O30)*$F30)+(N(O31)*$F31)+(N(O32)*$F32))/(IF(O27="N/A",0,(5*$F27))+IF(O28="N/A",0,(5*$F28))+IF(O29="N/A",0,(5*$F29))+IF(O30="N/A",0,(5*$F30))+IF(O31="N/A",0,(5*$F31))+IF(O32="N/A",0,(5*$F32)))) -> 0 | P26: =IF(COUNTIF(P27:P32,"=N/A")=6,"N/A", ((N(P27)*$F27)+(N(P28)*$F28)+(N(P29)*$F29)+(N(P30)*$F30)+(N(P31)*$F31)+(N(P32)*$F32))/(IF(P27="N/A",0,(5*$F27))+IF(P28="N/A",0,(5*$F28))+IF(P29="N/A",0,(5*$F29))+IF(P30="N/A",0,(5*$F30))+IF(P31="N/A",0,(5*$F31))+IF(P32="N/A",0,(5*$F32)))) -> 0 | Q26: =IF(COUNTIF(Q27:Q32,"=N/A")=6,"N/A", ((N(Q27)*$F27)+(N(Q28)*$F28)+(N(Q29)*$F29)+(N(Q30)*$F30)+(N(Q31)*$F31)+(N(Q32)*$F32))/(IF(Q27="N/A",0,(5*$F27))+IF(Q28="N/A",0,(5*$F28))+IF(Q29="N/A",0,(5*$F29))+IF(Q30="N/A",0,(5*$F30))+IF(Q31="N/A",0,(5*$F31))+IF(Q32="N/A",0,(5*$F32)))) -> N/A | R26: =IF(COUNTIF(R27:R32,"=N/A")=6,"N/A", ((N(R27)*$F27)+(N(R28)*$F28)+(N(R29)*$F29)+(N(R30)*$F30)+(N(R31)*$F31)+(N(R32)*$F32))/(IF(R27="N/A",0,(5*$F27))+IF(R28="N/A",0,(5*$F28))+IF(R29="N/A",0,(5*$F29))+IF(R30="N/A",0,(5*$F30))+IF(R31="N/A",0,(5*$F31))+IF(R32="N/A",0,(5*$F32)))) -> 0
A27: 7_1_36_121 | B27: SUSTANCIAS PELIGROSAS | C27: 5.1 | D27: Ejecucion segura de Carga de GLP | E27: SÍ | F27: 1 | G27: Documentar SOP: sustancias peligrosas y la ejecución segura del repostaje de GLP. | H27: R5.1.1 - Suministro de GLP incluido en la evaluación de riesgo de la unidad. R5.1.2 - Procedimientos para estaciones de servicio de GLP a granel definidas y fijadas en el área de suministro. R5.1.3 - Procedimientos para las estaciones de servicio de GLP a granel seguidos por los operadores y visible en el área. R5.1.4 - Acceso controlado a la estación de GLP. R5.1.5 - Lista fija de operadores autorizados y visible en el área. R5.1.6 - Estaciones de servicio de GLP a granel en buen estado. R5.1.7 - Capacitación completada para garantizar que los operadores realicen el suministro de GLP a granel de acuerdo con el procedimiento. R5.1.8 - La Gerencia realizó procedimientos de OWD de suministro de GLP a granel. | I27: 5 - Se cumplieron todos los requisitos y se mejoró la tendencia en resultados de coaching/OWD 3 - Todos los requisitos se cumplieron pero los resultados de coaching/OWD no mostraron tendencia de mejora 1 - R5.1.1, R5.1.2, R5.1.4, R5.1.5 y R5.1.6 se cumplieron pero R5.1.3 no se cumplió (un SIF potencial o SIF actual relacionado con R5.1.3) 0 - R5.1.1, R5.1.2, R5.1.4, R5.1.5 o R5.1.6 no se cumplen | J27: 1. Revise la evaluación de riesgos para la estación de GLP y observe el área. 2. Compruebe si los procedimientos de las estaciones de llenado de GLP a granel están definidos/ publicados. 3. Comprobar si se siguen las prácticas de trabajo seguras definidas en el protocolo. 4. Comprobar si el acceso está controlado según lo definido en la evaluación del riesgo. 5. Comprobar si la zona está ocupada por personal autorizado. 6. Comprobar si la zona se mantiene en buenas condiciones. 7. Compruebe la Gestión de Incidentes: ¿ha habido un Potencial SIF o SIF actual relacionado con reglas de funcionamiento seguras que no se siguen? 8. Compruebe el registro de entrenamiento de la instalación - compruebe si hay entrenamiento en el llenado a granel de GLP (positivo y correctivo). 9. Compruebe las OWD de la instalación - compruebe si se están realizando diagnósticos en procedimientos de llenado masivo de GLP. | L27: =IF(AND(M27="N/A",N27="N/A"),"N/A",IF(OR(M27="",N27=""),"",SMALL(M27:N27,1))) -> 0 | M27: 0 | N27: N/A | O27: =IF(AND(P27="N/A",Q27="N/A"),"N/A",IF(OR(P27="",Q27=""),"",SMALL(P27:Q27,1))) -> 0 | P27: 0 | Q27: N/A | R27: =IF(OR(L27="",O27=""),"",IF(AND(L27="N/A",O27="N/A"),"N/A",AVERAGE(L27,O27))) -> 0
A28: 7_1_36_122 | B28: SUSTANCIAS PELIGROSAS | C28: 5.2 | D28: Ejecucion segura de Carga de baterías | E28: SÍ | F28: 1 | G28: Documente procedimiento sobre sustancias peligrosas y la ejecución segura de la carga de baterías. | H28: R5.2.1 - Proceso de carga de baterías incluido en la evaluación de riesgos de la instalación. R5.2.2 - Procedimientos de las estaciones de carga de baterías definidos/publicados. R5.2.3 - Procedimientos seguidos por los operadores en las estaciones de carga de baterías y visible en el área.. R5.2.4 - Lista de operadores autorizados publicados y visible en el área. R5.2.5 - Lavaojos/ducha de seguridad en su lugar e inspeccionados. R5.2.6 - Estaciones de carga de baterías mantenidas en buenas condiciones. R5.2.7 - Capacitación completada para garantizar que los operadores realicen la carga/recarga de la batería de acuerdo con el procedimiento. R5.2.8 - La gerencia lleva a cabo OWD para los procedimientos de carga/recarga de las baterías. | I28: 5 - Se cumplieron todos los requisitos y la tendencia de mejora en los resultados de coaching/OWD 3 - Se cumplieron todos los requisitos pero los resultados de coaching/OWD no muestran una tendencia de mejora 1 - R5.2.1, R5.2.2, R5.2.4, R5.2.5 y R5.2.6 cumplieron pero R5.2.3 no cumplieron (se produjo un SIF potencial o SIF actual relacionado con R5.2.3) 0 - R5.2.1, R5.2.2, R5.2.4, R5.2.5 o R5.2.6 no cumplido | J28: 1. Revisar la evaluación de riesgos para la estación de carga de baterías y observe el área. 2. Verifique si los procedimientos de las estaciones de carga de baterías están definidos/publicados. 3. Verificar si se están siguiendo las prácticas de trabajo seguras como se define en el protocolo. 4. Verificar si el área está señalizada con personal autorizado. 5. Verifique si el área se mantiene en buenas condiciones con lavaojos/ducha de seguridad presente e inspeccionada. 6. Verifique la gestión de incidentes: ¿ha habido un SIF potencial o un SIF actual relacionado con las reglas de operación segura que no se siguen? 7. Verifique el registro de entrenamiento de la instalación: verifique si hay entrenamiento sobre la carga/el riego de la batería (positivo y correctivo). 8. Verifique los OWD de las instalaciones: verifique si se están realizando diagnósticos en los procedimientos de carga/recarga de la batería. | L28: =IF(AND(M28="N/A",N28="N/A"),"N/A",IF(OR(M28="",N28=""),"",SMALL(M28:N28,1))) -> 0 | M28: 0 | N28: N/A | O28: =IF(AND(P28="N/A",Q28="N/A"),"N/A",IF(OR(P28="",Q28=""),"",SMALL(P28:Q28,1))) -> 0 | P28: 0 | Q28: N/A | R28: =IF(OR(L28="",O28=""),"",IF(AND(L28="N/A",O28="N/A"),"N/A",AVERAGE(L28,O28))) -> 0
A29: 7_1_36_123 | B29: SUSTANCIAS PELIGROSAS | C29: 5.3 | D29: Ejecucion segura de carga de Diesel/Gasoil | E29: SÍ | F29: 1 | G29: Documente procedimiento sobre sustancias peligrosas y la ejecución segura del gasoil y la gasolina. | H29: R5.3.1 - Proceso de abastecimiento de diésel/gasolina incluido en la evaluación de riesgos de las instalaciones. R5.3.2 - Procedimientos de estaciones de diésel/gasolina definidos y publicados en el área de llenado. R5.3.3 - Procedimientos de estaciones de servicio diésel/gasolina seguidos por los operadores y visible en el área. R5.3.4 - Acceso controlado a la estación de diésel/gasolina y protección necesaria. R5.3.5 - Lista de operadores certificados publicados y visible en el área. R5.3.6 - Estación de servicio diésel/gasolina mantenida en buenas condiciones. R5.3.7 - Entrenamiento completo para asegurar que los operadores realicen el reabastecimiento de gas/ diésel en cumplimiento del procedimiento. R5.3.8 - La dirección lleva a cabo OWD para asegurar los procedimientos de reabastecimiento de gas/diésel. | I29: 5 - Se cumplieron todos los requisitos y se mejoró la tendencia en resultados de coaching/OWD 3 - Todos los requisitos se cumplieron pero los resultados de coaching/OWD no mostraron tendencia de mejora 1 - R5.3.1, R5.3.2, R5.3.4, R5.3.5 y R5.3.6 se cumplieron pero R5.3.3 no se cumplió (un potencial SIF o SIF actual relacionado con R5.3.3.3) 0 - R5.3.1, R5.3.2, R5.3.4, R5.3.5 o R5.3.6 no se cumplen | J29: 1. Revisar la evaluación de riesgos para la estación de diésel/gasolina y observar el área. 2. Verificar si los procedimientos de la estación de diésel/gasolina están definidos/publicados. 3. Comprobar si se siguen las prácticas de trabajo seguras definidas en el protocolo. 4. Compruebe si hay acceso controlado a la estación de diésel/gasolina y las protecciones necesarias. 5. Comprobar si la zona está ocupada por personal autorizado. 6. Comprobar si la zona se mantiene en buenas condiciones. 7. Compruebe la Gestión de Incidentes: ¿ha habido un Potencial SIF o SIF Actual relacionado con reglas de funcionamiento seguras que no se siguen? 8. Compruebe el registro de entrenamiento de la instalación - compruebe si hay entrenamiento en el reabastecimiento de gas/ diésel (positivo y correctivo). 9. Compruebe las OWD de la instalación - compruebe si se están realizando diagnósticos en procedimientos de gas/ diésel. | L29: =IF(AND(M29="N/A",N29="N/A"),"N/A",IF(OR(M29="",N29=""),"",SMALL(M29:N29,1))) -> 0 | M29: 0 | N29: N/A | O29: =IF(AND(P29="N/A",Q29="N/A"),"N/A",IF(OR(P29="",Q29=""),"",SMALL(P29:Q29,1))) -> 0 | P29: 0 | Q29: N/A | R29: =IF(OR(L29="",O29=""),"",IF(AND(L29="N/A",O29="N/A"),"N/A",AVERAGE(L29,O29))) -> 0
A30: 7_1_36_124 | B30: SUSTANCIAS PELIGROSAS | C30: 5.4 | D30: Almacenamiento y transporte seguro de tubos de gas comprimido | E30: No | F30: 1 | G30: Documente procedimiento sobre sustancias peligrosas y el almacenamiento y transporte de bombonas de gas comprimido. | H30: R5.4.1 - Cilindros de gas comprimido almacenados correctamente. R5.4.2 - Cilindros de gas comprimido mantenidos en buen estado. R5.4.3 - Procedimientos de manipulación de cilindros de gas comprimido definidos y almacenados correctamente. R5.4.4 - Transporte de cilindros alineados con el protocolo. R5.4.5 - Señalización y zonas de peligro identificadas dentro del almacen. R5.4.6 - Entrenamiento completo para asegurar que los operadores lleven a cabo la manipulación de cilindros de gas comprimido de conformidad con el procedimiento. R5.4.7 - La dirección lleva a cabo procedimientos de OWD a la manipulacion de cilindros de gas comprimido. | I30: 5 - Se cumplieron todos los requisitos y se mejoró la tendencia en los resultados de coaching/OWD 3 - Todos los requisitos se cumplieron pero los resultados de coaching/OWD no mostraron tendencia de mejora 1 - R5.4.1, R5.4.2, R5.4.3 y R5.4.5 cumplieron pero R5.4.4 no se cumplieron (un potencial SIF o SIF actual relacionado con R5.4.4) 0 - R5.4.1, R5.4.2, R5.4.3 o R5.4.5 no se cumplen | J30: 1. Observar las zonas de almacenamiento: observar si los cilindros de gas comprimido están almacenados según lo definido en el protocolo. 2. Observe si están en buenas condiciones y adecuadamente protegidos. 3. Compruebe si los procedimientos de manipulación de los cilindros de gas comprimido están definidos/fijados. 4. Comprobar si el transporte de cilindros se gestiona según lo definido en el protocolo. 5. Obsérvese si hay señalización y se comunican los peligros de la zona. 6. Compruebe la Gestión de Incidentes: ¿ha habido un Potencial SIF o SIF actual relacionado con reglas de funcionamiento seguras que no se siguen? 7. Compruebe el registro de entrenamiento de la instalación - compruebe si hay entrenamiento en el manejo de cilindros de gas comprimido (positivo y correctivo). 8. Comprobar las OWD de la instalación - comprobar si se están realizando diagnósticos en procedimientos de manipulación de cilindros de gas comprimido. | L30: =IF(AND(M30="N/A",N30="N/A"),"N/A",IF(OR(M30="",N30=""),"",SMALL(M30:N30,1))) -> 0 | M30: 0 | N30: N/A | O30: =IF(AND(P30="N/A",Q30="N/A"),"N/A",IF(OR(P30="",Q30=""),"",SMALL(P30:Q30,1))) -> 0 | P30: 0 | Q30: N/A | R30: =IF(OR(L30="",O30=""),"",IF(AND(L30="N/A",O30="N/A"),"N/A",AVERAGE(L30,O30))) -> 0
A31: 7_1_36_125 | B31: SUSTANCIAS PELIGROSAS | C31: 5.5 | D31: Almacenamiento de sustancias peligrosas | E31: No | F31: 1 | G31: Documente procedimiento sobre sustancias peligrosas y el almacenamiento de sustancias peligrosas. | H31: R5.5.1 - Sustancias peligrosas debidamente almacenadas en contenedor secundario. (bateas de contención, según la capacidad) R5.5.2 - Productos incompatibles almacenados por separado. R5.5.3 - Ventilación adecuada en el área de almacenamiento. R5.5.4 - Área correctamente etiquetada y controlada con matriz de compatibilidad. R5.5.5 - Residuos eliminados correctamente de acuerdo con la reglamentación. | I31: 5 - Todos los requisitos cumplieron 3 - R5.5.2, R5.5.3, R5.5.4 y R5.5.5 cumplieron pero 1 violación de R5.5.1 1 - R5.5.5.2, R5.5.3, R5.5.5 y R5.5 - Se incumplieron >1 violación de R5.5.1 0 - R5.5.2, R5.5.3, R5.5.4 y R5.5.5 no cumplieron | J31: 1. Observación de las zonas de almacenamiento de productos químicos: Comprobar si los productos químicos se almacenan en una batea secundaria para contener derrames. 2. Observar si los productos incompatibles se almacenan por separado. 3. Comprobar si existe una ventilación adecuada en la zona de almacenamiento. 4. Obsérvese si la zona está debidamente etiquetada y controlada, incluida una matriz de compatibilidad. 5. Comprobar si los residuos se eliminan correctamente en conformidad con las directrices reglamentarias. | L31: =IF(AND(M31="N/A",N31="N/A"),"N/A",IF(OR(M31="",N31=""),"",SMALL(M31:N31,1))) -> 0 | M31: 0 | N31: N/A | O31: =IF(AND(P31="N/A",Q31="N/A"),"N/A",IF(OR(P31="",Q31=""),"",SMALL(P31:Q31,1))) -> 0 | P31: 0 | Q31: N/A | R31: =IF(OR(L31="",O31=""),"",IF(AND(L31="N/A",O31="N/A"),"N/A",AVERAGE(L31,O31))) -> 0
A32: 7_1_36_126 | B32: SUSTANCIAS PELIGROSAS | C32: 5.6 | D32: SDS Management | E32: No | F32: 1 | G32: Documente procedimiento sobre sustancias peligrosas y la gestión de FDS. | H32: R5.6.1 - Todos los productos etiquetados. R5.6.2 - Inventario químico con todos los productos químicos de la instalación. R5.6.3 - SDS actualizado para todos los productos químicos y disponible en todos los turnos. R5.6.4 - Proceso en marcha para la aprobación de todos los productos químicos nuevos. | I32: 5 - Todos los requisitos cumplieron 3 - R5.6.1 y R5.6.2 pero R5.6.3 no cumplió 1 - R5.6.1 cumplió pero R5.6.2 no cumplió 0 - R5.6.1 no cumplió | J32: 1. Observar los productos químicos almacenados in situ: comprobar si los productos están etiquetados correctamente. 2. Comprobar si los productos químicos figuran en el inventario. 3. Compruebe si existe una FDS actualizada disponible para cada turno. 4. Compruebe si existe un proceso para la aprobación de todos los nuevos productos químicos. | L32: =IF(AND(M32="N/A",N32="N/A"),"N/A",IF(OR(M32="",N32=""),"",SMALL(M32:N32,1))) -> 0 | M32: 0 | N32: N/A | O32: =IF(AND(P32="N/A",Q32="N/A"),"N/A",IF(OR(P32="",Q32=""),"",SMALL(P32:Q32,1))) -> 0 | P32: 0 | Q32: N/A | R32: =IF(OR(L32="",O32=""),"",IF(AND(L32="N/A",O32="N/A"),"N/A",AVERAGE(L32,O32))) -> 0
B33: ESPACIO CONFINADO | L33: =IF(COUNTIF(L34:L35,"=N/A")=4,"N/A", ((N(L34)*$F34)+(N(L35)*$F35)+(N(L35)*$F35)+(N(L35)*$F35))/(IF(L34="N/A",0,(5*$F34))+IF(L35="N/A",0,(5*$F35))+IF(L35="N/A",0,(5*$F35))+IF(L35="N/A",0,(5*$F35)))) -> 0 | M33: =IF(COUNTIF(M34:M35,"=N/A")=4,"N/A", ((N(M34)*$F34)+(N(M35)*$F35)+(N(M35)*$F35)+(N(M35)*$F35))/(IF(M34="N/A",0,(5*$F34))+IF(M35="N/A",0,(5*$F35))+IF(M35="N/A",0,(5*$F35))+IF(M35="N/A",0,(5*$F35)))) -> 0 | N33: =IF(COUNTIF(N34:N35,"=N/A")=4,"N/A", ((N(N34)*$F34)+(N(N35)*$F35)+(N(N35)*$F35)+(N(N35)*$F35))/(IF(N34="N/A",0,(5*$F34))+IF(N35="N/A",0,(5*$F35))+IF(N35="N/A",0,(5*$F35))+IF(N35="N/A",0,(5*$F35)))) -> #DIV/0! | O33: =IF(COUNTIF(O34:O35,"=N/A")=4,"N/A", ((N(O34)*$F34)+(N(O35)*$F35)+(N(O35)*$F35)+(N(O35)*$F35))/(IF(O34="N/A",0,(5*$F34))+IF(O35="N/A",0,(5*$F35))+IF(O35="N/A",0,(5*$F35))+IF(O35="N/A",0,(5*$F35)))) -> 0 | P33: =IF(COUNTIF(P34:P35,"=N/A")=4,"N/A", ((N(P34)*$F34)+(N(P35)*$F35)+(N(P35)*$F35)+(N(P35)*$F35))/(IF(P34="N/A",0,(5*$F34))+IF(P35="N/A",0,(5*$F35))+IF(P35="N/A",0,(5*$F35))+IF(P35="N/A",0,(5*$F35)))) -> 0 | Q33: =IF(COUNTIF(Q34:Q35,"=N/A")=4,"N/A", ((N(Q34)*$F34)+(N(Q35)*$F35)+(N(Q35)*$F35)+(N(Q35)*$F35))/(IF(Q34="N/A",0,(5*$F34))+IF(Q35="N/A",0,(5*$F35))+IF(Q35="N/A",0,(5*$F35))+IF(Q35="N/A",0,(5*$F35)))) -> #DIV/0! | R33: =IF(COUNTIF(R34:R35,"=N/A")=4,"N/A", ((N(R34)*$F34)+(N(R35)*$F35)+(N(R35)*$F35)+(N(R35)*$F35))/(IF(R34="N/A",0,(5*$F34))+IF(R35="N/A",0,(5*$F35))+IF(R35="N/A",0,(5*$F35))+IF(R35="N/A",0,(5*$F35)))) -> 0
A34: 7_1_37_127 | B34: ESPACIO CONFINADO | C34: 6.1 | D34: Identificación, señalizacion e inventario de espacios confinados | E34: No | F34: 1 | G34: Documente procedimiento de espacios confinados y la identificación, el etiquetado y el inventario de espacios confinados. | H34: R6.1.1 - Todos los espacios confinados identificados. R6.1.2 - Todos los espacios confinados etiquetados. R6.1.3 - Inventario disponible para los empleados. | I34: 5 - Todos los requisitos cumplieron 3 - Todos los requisitos se cumplieron pero 1 espacio no identificado. 1 - Todos los requisitos se cumplieron pero 2 espacios no identificados. 0 - R6.1.1 no se cumplieron o >2 espacios no identificados | J34: 1. Comprobar si todos los espacios confinados están identificados. 2. Comprobar si todos los espacios confinados están etiquetados adecuadamente. 3. Comprobar si los empleados disponen de un inventario de espacios confinados. | L34: =IF(AND(M34="N/A",N34="N/A"),"N/A",IF(OR(M34="",N34=""),"",SMALL(M34:N34,1))) -> 0 | M34: 0 | N34: N/A | O34: =IF(AND(P34="N/A",Q34="N/A"),"N/A",IF(OR(P34="",Q34=""),"",SMALL(P34:Q34,1))) -> 0 | P34: 0 | Q34: N/A | R34: =IF(OR(L34="",O34=""),"",IF(AND(L34="N/A",O34="N/A"),"N/A",AVERAGE(L34,O34))) -> 0
A35: 7_1_37_128 | B35: ESPACIO CONFINADO | C35: 6.2 | D35: Ejecucion segura de entrada en espacios confinados | E35: No | F35: 1 | G35: Documente procedimiento de espacios confinados y la ejecución segura de entradas en espacios confinados. | H35: R6.2.1 - Capacitación en el aula de entrenamiento para los empleados que realizan la entrada de espacio confinado. R6.2.2 - Procedimientos de entrada en espacios confinados escritos y disponibles para los empleados y revisados. R6.2.3 - Procedimientos de entrada al espacio confinado seguidos por los empleados. R6.2.4 - Permisos en espacios confinados completos y firmados. R6.2.5 - Permisos de espacio confinado realizados antes del 100% de las entradas. R6.2.6 - Controles finales realizados a los permisos de espacio confinado. R6.2.7 - Dispositivos de entrada en espacios reducidos y equipos de monitoreo disponibles. R6.2.8 - Dispositivos de entrada al espacio confinado y equipo de monitoreo en buen estado. R6.2.9 - Equipo de rescate definido y entrenado en procedimientos de rescate. R6.2.10 - Equipo de rescate disponible y en su lugar. R6.2.11 - Simulaciones realizadas. R6.2.12 - Entrenamiento completo para asegurar que los operadores realicen la entrada al espacio confinado en conformidad con el procedimiento. R6.2.13 - La gerencia lleva a cabo OWD del procedimientos de entrada en espacios confinados. | I35: 5 - Se cumplieron todos los requisitos y no se produjo SIF potencial o SIF actual relacionado con la entrada a espacios confinados y hay tendencia hacia la mejora en los resultados de entrenamiento y OWD 3 - Se cumplieron todos los requisitos y no se produjo SIF potencial o SIF actual relacionado con la entrada a espacios confinados pero los resultados de entrenamiento y OWD no muestran una tendencia de mejora 1 - Se cumplieron todos los requisitos pero se produjo un SIF potencial o SIF real relacionado con la entrada a espacios confinados 0 - Cualquier requisito no cumplido | J35: 1. Verificar que la unidad califique a los empleados con capacitación en la sala y en el sitio de entrada antes de permitirles realizar la entrada. 2. Verificar que los procedimientos de entrada estén documentados y revisados, completos y cumplidos por los empleados. 3. Verificar que se hayan completado los permisos y que los campos estén completos antes de que la persona autorizada ingrese al espacio confinado y que se utilicen para todas las entradas. 4. Verificar que se haya realizado un control final previo a la autorización. 5. Asegúrese de que los dispositivos y equipos de monitoreo estén en buen estado de funcionamiento y disponibles para el personal antes de ingresar al espacio confinado. 6. Verificar que exista un equipo de rescate definido y capacitado en los procedimientos de rescate. 7. Asegúrese de que el personal esté disponible y notificado antes de la entrada al espacio confinado. 8. Verifique que se realicen los ejercicios. 9. Verifique La gestión de incidentes: ¿hubo un SIF potencial o un SIF actual relacionado con las reglas de operación segura que no se están siguiendo? 10. Revisar la herramienta de entrenamiento/informes de la unidad: verificar el entrenamiento de entrada a espacios confinados (positivo y correctivo). 11. Verifique las OWD de la unidad: verifique que se esté monitoreando los procedimientos de entrada a espacios confinados | L35: =IF(AND(M35="N/A",N35="N/A"),"N/A",IF(OR(M35="",N35=""),"",SMALL(M35:N35,1))) -> 0 | M35: 0 | N35: N/A | O35: =IF(AND(P35="N/A",Q35="N/A"),"N/A",IF(OR(P35="",Q35=""),"",SMALL(P35:Q35,1))) -> 0 | P35: 0 | Q35: N/A | R35: =IF(OR(L35="",O35=""),"",IF(AND(L35="N/A",O35="N/A"),"N/A",AVERAGE(L35,O35))) -> 0
B36: PREVENCIÓN DE VIOLENCIA | L36: =IF(COUNTIF(L37:L38,"=N/A")=4,"N/A", ((N(L37)*$F37)+(N(L38)*$F38)+(N(L38)*$F38)+(N(L38)*$F38))/(IF(L37="N/A",0,(5*$F37))+IF(L38="N/A",0,(5*$F38))+IF(L38="N/A",0,(5*$F38))+IF(L38="N/A",0,(5*$F38)))) -> 0 | M36: =IF(COUNTIF(M37:M39,"=N/A")=4,"N/A", ((N(M37)*$F37)+(N(M38)*$F38)+(N(M38)*$F38)+(N(M38)*$F38)+(N(M39)*$F39))/(IF(M37="N/A",0,(5*$F37))+IF(M38="N/A",0,(5*$F38))+IF(M38="N/A",0,(5*$F38))+IF(M38="N/A",0,(5*$F38))+IF(M39="N/A",0,(5*$F39)))) -> 0 | N36: =IF(COUNTIF(N37:N39,"=N/A")=4,"N/A", ((N(N37)*$F37)+(N(N38)*$F38)+(N(N38)*$F38)+(N(N38)*$F38)+(N(N39)*$F39))/(IF(N37="N/A",0,(5*$F37))+IF(N38="N/A",0,(5*$F38))+IF(N38="N/A",0,(5*$F38))+IF(N38="N/A",0,(5*$F38))+IF(N39="N/A",0,(5*$F39)))) -> #DIV/0! | O36: =IF(COUNTIF(O37:O39,"=N/A")=4,"N/A", ((N(O37)*$F37)+(N(O38)*$F38)+(N(O38)*$F38)+(N(O38)*$F38)+(N(O39)*$F39))/(IF(O37="N/A",0,(5*$F37))+IF(O38="N/A",0,(5*$F38))+IF(O38="N/A",0,(5*$F38))+IF(O38="N/A",0,(5*$F38))+IF(O39="N/A",0,(5*$F39)))) -> 0 | P36: =IF(COUNTIF(P37:P39,"=N/A")=4,"N/A", ((N(P37)*$F37)+(N(P38)*$F38)+(N(P38)*$F38)+(N(P38)*$F38)+(N(P39)*$F39))/(IF(P37="N/A",0,(5*$F37))+IF(P38="N/A",0,(5*$F38))+IF(P38="N/A",0,(5*$F38))+IF(P38="N/A",0,(5*$F38))+IF(P39="N/A",0,(5*$F39)))) -> 0 | Q36: =IF(COUNTIF(Q37:Q39,"=N/A")=4,"N/A", ((N(Q37)*$F37)+(N(Q38)*$F38)+(N(Q38)*$F38)+(N(Q38)*$F38)+(N(Q39)*$F39))/(IF(Q37="N/A",0,(5*$F37))+IF(Q38="N/A",0,(5*$F38))+IF(Q38="N/A",0,(5*$F38))+IF(Q38="N/A",0,(5*$F38))+IF(Q39="N/A",0,(5*$F39)))) -> #DIV/0! | R36: =IF(COUNTIF(R37:R39,"=N/A")=4,"N/A", ((N(R37)*$F37)+(N(R38)*$F38)+(N(R38)*$F38)+(N(R38)*$F38)+(N(R39)*$F39))/(IF(R37="N/A",0,(5*$F37))+IF(R38="N/A",0,(5*$F38))+IF(R38="N/A",0,(5*$F38))+IF(R38="N/A",0,(5*$F38))+IF(R39="N/A",0,(5*$F39)))) -> 0
A37: 7_1_38_129 | B37: PREVENCIÓN DE VIOLENCIA | C37: 7.1 | D37: Gestión de dinero efectivo en ruta | E37: No | F37: 1 | G37: Propósito: debemos eliminar el manejo de efectivo de nuestras operaciones. Hasta que hayamos conseguido eliminar el 100% del efectivo, debemos aplicar estrategias de control eficaces para evitar los robos y debemos asegurarnos de que todos los miembros de nuestro equipo se adhieren a dichas estrategias a través de nuestras rutinas de OWD y coaching. Documente procedimiento de Prevención de la Violencia para obtener orientación adicional. | H37: R7.1.1 - Estrategia de gestión de efectivo implementada con prioridad en eliminar el manejo de efectivo. R7.1.2 - Plan de acción para la eliminación de efectivo. R7.1.3 - Sistema implementado para revisión de camiones (caja fuerte) y caja unitaria. R7.1.4 - Estrategia de comunicación efectiva implementada para minimizar el robo. R7.1.5 - Si se maneja efectivo, existen medidas de seguridad para reducir los riesgos del manejo de efectivo en el mercado. R7.1.6 - Procedimientos de manejo de efectivo seguidos por los empleados. R7.1.7 - Capacitación completada para garantizar que los empleados realicen el manejo de efectivo de acuerdo con el procedimiento. R7.1.8 - La gerencia instruye la OWD para los procedimientos de manejo de efectivo. | I37: 5 - la unidad eliminó el efectivo o cumplió con todos los requisitos y mejoró la tendencia en los resultados de entrenamiento y OWD 3 - Se cumplieron todos los requisitos pero los resultados de entrenamiento y OWD no muestran una tendencia de mejora 1 - R7.1.1, R7.1.2, R7.1.3, R7.1.4 y R7.1.5 cumplieron pero R7.1.6 no cumplieron (ocurrió un SIF potencial o SIF real relacionado con R7.1.6) 0 - R7.1.1, R7.1.2, R7.1.3, R7.1.4 o R7.1.5 no cumplido | J37: 1. Comprobar que existe una estrategia de gestión de efectivo con prioridad en eliminar el manejo de efectivo 2. Asegúrese de tener un plan de acción para eliminar el efectivo. 3. Verificar que exista un sistema de verificación de camiones (camiones equipados con caja fuerte y funcionando correctamente). 4. Verificar que exista un sistema de verificación de caja unitaria. 5. Verificar que se haya implementado la estrategia de comunicación. 6. Si se maneja efectivo, verifique que existan medidas de seguridad para reducir el riesgo del manejo de efectivo mientras se está en el negocio. 7. Verifique si hay incidentes de robo o violencia que involucren efectivo: verifique que se hayan seguido los procedimientos de manejo de efectivo. 8. Verifique la gestión de incidentes: ¿hubo un SIF potencial o un SIF actual relacionado con las reglas de operación segura que no se están siguiendo? 9. Verifique la herramienta de capacitación/informes de la unidad: verifique la capacitación sobre el manejo del dinero (positiva y correctiva). 10. Verificar las OWD de las unidades: asegurarse de que se lleve a cabo un seguimiento de los procedimientos de manejo de efectivo | L37: =IF(AND(M37="N/A",N37="N/A"),"N/A",IF(OR(M37="",N37=""),"",SMALL(M37:N37,1))) -> 0 | M37: 0 | N37: N/A | O37: =IF(AND(P37="N/A",Q37="N/A"),"N/A",IF(OR(P37="",Q37=""),"",SMALL(P37:Q37,1))) -> 0 | P37: 0 | Q37: N/A | R37: =IF(OR(L37="",O37=""),"",IF(AND(L37="N/A",O37="N/A"),"N/A",AVERAGE(L37,O37))) -> 0
A38: 7_1_38_130 | B38: PREVENCIÓN DE VIOLENCIA | C38: 7.2 | D38: Ejecución segura de la prevención de la violencia | E38: No | F38: 1 | G38: Propósito: debemos identificar los procedimientos de trabajo seguros que los empleados deben ejecutar para prevenir la violencia. Estos procedimientos deben estar por escrito y a disposición de los empleados. El cumplimiento de estos procedimientos debe gestionarse a través de nuestro OWD y las rutinas de entrenamiento. Documente procedimiento de Prevención de la Violencia para obtener orientación adicional. | H38: R7.2.1 - Procedimientos de prevención de violencia escritos, completos y disponibles para los empleados. R7.2.2 - Los operadores ejecutan procedimientos de prevención de violencia adheridos al programa. R7.2.3 - Capacitación completa para garantizar que los operadores ejecuten procedimientos de prevención de violencia. R7.2.4 - La dirección realiza OWD a los procedimientos de prevención de la violencia. | I38: 5 - Se cumplieron todos los requisitos y la tendencia de mejora en los resultados de coaching/OWD 3 - Se cumplieron todos los requisitos pero los resultados de coaching/OWD no muestran una tendencia de mejora 1 - R7.2.1 cumplió pero R7.2.2 no cumplió (se produjo un SIF potencial o SIF actual relacionado con R7.2.2) 0 - R7.2.1 no cumplido | J38: 1. Verificar si los procedimientos para la prevención de la violencia están escritos, completos y disponibles para los empleados. 2. Verificar si los operadores están ejecutando procedimientos de prevención de violencia y se adhieren al programa. 3. Verifique la gestión de incidentes: ¿ha habido un SIF potencial o un SIF actual relacionado con las reglas de operación segura que no se siguen? 4. Revisar la herramienta de coaching del establecimiento - verificar si hay coaching en prevención de violencia (positivo y correctivo). 5. Verifique las OWD de las instalaciones: verifique si se están realizando diagnósticos sobre los procedimientos de prevención de la violencia. | L38: =IF(AND(M38="N/A",N38="N/A"),"N/A",IF(OR(M38="",N38=""),"",SMALL(M38:N38,1))) -> 0 | M38: 0 | N38: N/A | O38: =IF(AND(P38="N/A",Q38="N/A"),"N/A",IF(OR(P38="",Q38=""),"",SMALL(P38:Q38,1))) -> 0 | P38: 0 | Q38: N/A | R38: =IF(OR(L38="",O38=""),"",IF(AND(L38="N/A",O38="N/A"),"N/A",AVERAGE(L38,O38))) -> 0
A39: 7_1_38_132 | B39: PREVENCIÓN DE VIOLENCIA | C39: 7.3 | D39: Toolkit Violence Prevention | E39: No | F39: 1 | G39: Propósito: la evaluación de riesgos y el kit de prevención de la violencia están diseñados para eliminar incidentes mortales relacionados con la violencia en nuestras operaciones. El sitio debe determinar su nivel de riesgo utilizando la herramienta de evaluación de riesgos, y luego implementar el kit según los requisitos de ese nivel de riesgo. Consulte el kit global de prevención de la violencia para obtener orientación adicional. | H39: R7.431 - Evaluación del Nivel de Prevención de Violencia completada y precisa. R7.3.2 - Kit de Prevención de Violencia implementado en el nivel correspondiente. R7.3.3 - Logro del Kit de Prevención de Violencia superior al 90%. R7.3.4 - Planes de acción en marcha para abordar las brechas en el logro del kit. | I39: 5Nivel 5: Todos los requisitos cumplidos. Nivel 3: Se cumplen R7.3.2, R7.3.1 y R7.3.3, pero no se cumple R7.3.4. Nivel 1: Se cumple R7.3.2, pero no se cumple R7.3.1. Nivel 0: No se cumple R7.3.2. | J39: 1.-Revisar el nivel del sitio: verificar cómo realizaron la evaluación y si su evaluación de nivel es precisa. 2.-Verificar la autoevaluación del sitio en relación con el logro del Kit de Prevención de Violencia y revisar el sitio/vehículos: verificar si la autoevaluación es precisa. 3.-Verificar si el sitio mantiene un plan de acción para cerrar las brechas en el logro del kit y si está actualizado. | L39: =IF(AND(M39="N/A",N39="N/A"),"N/A",IF(OR(M39="",N39=""),"",SMALL(M39:N39,1))) -> 0 | M39: 0 | N39: N/A | O39: =IF(AND(P39="N/A",Q39="N/A"),"N/A",IF(OR(P39="",Q39=""),"",SMALL(P39:Q39,1))) -> 0 | P39: 0 | Q39: N/A | R39: =IF(OR(L39="",O39=""),"",IF(AND(L39="N/A",O39="N/A"),"N/A",AVERAGE(L39,O39))) -> 0
B40: SEGURIDAD VIAL Y DE CONDUCCIÓN | L40: =IF(COUNTIF(L41:L48,"=N/A")=8,"N/A", ((N(L41)*$F41)+(N(L42)*$F42)+(N(L43)*$F43)+(N(L44)*$F44)+(N(L45)*$F45)+(N(L46)*$F46)+(N(L47)*$F47)+(N(L48)*$F48))/(IF(L41="N/A",0,(5*$F41))+IF(L42="N/A",0,(5*$F42))+IF(L43="N/A",0,(5*$F43))+IF(L44="N/A",0,(5*$F44))+IF(L45="N/A",0,(5*$F45))+IF(L46="N/A",0,(5*$F46))+IF(L47="N/A",0,(5*$F47))+IF(L48="N/A",0,(5*$F48)))) -> 0 | M40: =IF(COUNTIF(M41:M48,"=N/A")=8,"N/A", ((N(M41)*$F41)+(N(M42)*$F42)+(N(M43)*$F43)+(N(M44)*$F44)+(N(M45)*$F45)+(N(M46)*$F46)+(N(M47)*$F47)+(N(M48)*$F48))/(IF(M41="N/A",0,(5*$F41))+IF(M42="N/A",0,(5*$F42))+IF(M43="N/A",0,(5*$F43))+IF(M44="N/A",0,(5*$F44))+IF(M45="N/A",0,(5*$F45))+IF(M46="N/A",0,(5*$F46))+IF(M47="N/A",0,(5*$F47))+IF(M48="N/A",0,(5*$F48)))) -> 0 | N40: =IF(COUNTIF(N41:N48,"=N/A")=8,"N/A", ((N(N41)*$F41)+(N(N42)*$F42)+(N(N43)*$F43)+(N(N44)*$F44)+(N(N45)*$F45)+(N(N46)*$F46)+(N(N47)*$F47)+(N(N48)*$F48))/(IF(N41="N/A",0,(5*$F41))+IF(N42="N/A",0,(5*$F42))+IF(N43="N/A",0,(5*$F43))+IF(N44="N/A",0,(5*$F44))+IF(N45="N/A",0,(5*$F45))+IF(N46="N/A",0,(5*$F46))+IF(N47="N/A",0,(5*$F47))+IF(N48="N/A",0,(5*$F48)))) -> N/A | O40: =IF(COUNTIF(O41:O48,"=N/A")=8,"N/A", ((N(O41)*$F41)+(N(O42)*$F42)+(N(O43)*$F43)+(N(O44)*$F44)+(N(O45)*$F45)+(N(O46)*$F46)+(N(O47)*$F47)+(N(O48)*$F48))/(IF(O41="N/A",0,(5*$F41))+IF(O42="N/A",0,(5*$F42))+IF(O43="N/A",0,(5*$F43))+IF(O44="N/A",0,(5*$F44))+IF(O45="N/A",0,(5*$F45))+IF(O46="N/A",0,(5*$F46))+IF(O47="N/A",0,(5*$F47))+IF(O48="N/A",0,(5*$F48)))) -> 0 | P40: =IF(COUNTIF(P41:P48,"=N/A")=8,"N/A", ((N(P41)*$F41)+(N(P42)*$F42)+(N(P43)*$F43)+(N(P44)*$F44)+(N(P45)*$F45)+(N(P46)*$F46)+(N(P47)*$F47)+(N(P48)*$F48))/(IF(P41="N/A",0,(5*$F41))+IF(P42="N/A",0,(5*$F42))+IF(P43="N/A",0,(5*$F43))+IF(P44="N/A",0,(5*$F44))+IF(P45="N/A",0,(5*$F45))+IF(P46="N/A",0,(5*$F46))+IF(P47="N/A",0,(5*$F47))+IF(P48="N/A",0,(5*$F48)))) -> 0 | Q40: =IF(COUNTIF(Q41:Q48,"=N/A")=8,"N/A", ((N(Q41)*$F41)+(N(Q42)*$F42)+(N(Q43)*$F43)+(N(Q44)*$F44)+(N(Q45)*$F45)+(N(Q46)*$F46)+(N(Q47)*$F47)+(N(Q48)*$F48))/(IF(Q41="N/A",0,(5*$F41))+IF(Q42="N/A",0,(5*$F42))+IF(Q43="N/A",0,(5*$F43))+IF(Q44="N/A",0,(5*$F44))+IF(Q45="N/A",0,(5*$F45))+IF(Q46="N/A",0,(5*$F46))+IF(Q47="N/A",0,(5*$F47))+IF(Q48="N/A",0,(5*$F48)))) -> N/A | R40: =IF(COUNTIF(R41:R48,"=N/A")=8,"N/A", ((N(R41)*$F41)+(N(R42)*$F42)+(N(R43)*$F43)+(N(R44)*$F44)+(N(R45)*$F45)+(N(R46)*$F46)+(N(R47)*$F47)+(N(R48)*$F48))/(IF(R41="N/A",0,(5*$F41))+IF(R42="N/A",0,(5*$F42))+IF(R43="N/A",0,(5*$F43))+IF(R44="N/A",0,(5*$F44))+IF(R45="N/A",0,(5*$F45))+IF(R46="N/A",0,(5*$F46))+IF(R47="N/A",0,(5*$F47))+IF(R48="N/A",0,(5*$F48)))) -> 0
A41: 7_1_39_133 | B41: SEGURIDAD VIAL Y DE CONDUCCIÓN | C41: 8.1 | D41: Gestión de la calificacion de los conductores | E41: No | F41: 1 | G41: Propósito: La unidad debe definir lo que significa ser un conductor cualificado. Al definir las cualificaciones, asegúrese de tener en cuenta la diferencia en los requisitos de cualificación de los distintos tipos de vehículos. Se deberá implantar un proceso que garantice que nadie conduce un vehículo si no está cualificado. | H41: R8.1.1 - La unidad dispone de una definición de conductor cualificado que incorpora todos los requisitos reglamentarios locales. R8.1.2 - Todos los conductores cualificados y autorizados. R8.1.3 - Proceso proactivo para garantizar el cumplimiento. | I41: 5 - Se cumplen todos los requisitos 3 - R8.1.1 y R8.1.2 cumplidas pero 1 violación de R8.1.3 1 - Se cumple R8.1.1 pero no se cumple R8.1.2 0 - R8.1.1 no se cumple | J41: 1. Revisar la definición de la unidad de conductor cualificado: comprobar si contiene la licencia, habilitacion médico, el registro reglamentario, etc., según proceda. 2. Verificar que todos los conductores cumplen todos los requisitos establecidos en la definición de conductor cualificado de la unidad. 3. Comprobar que los conductores pueden presentar un permiso de conducción válido. 4. Verifique que existe un proceso proactivo para controlar el cumplimiento y garantizar que no hay GAPs en la autorización de los conductores. | L41: =IF(AND(M41="N/A",N41="N/A"),"N/A",IF(OR(M41="",N41=""),"",SMALL(M41:N41,1))) -> 0 | M41: 0 | N41: N/A | O41: =IF(AND(P41="N/A",Q41="N/A"),"N/A",IF(OR(P41="",Q41=""),"",SMALL(P41:Q41,1))) -> 0 | P41: 0 | Q41: N/A | R41: =IF(OR(L41="",O41=""),"",IF(AND(L41="N/A",O41="N/A"),"N/A",AVERAGE(L41,O41))) -> 0
A42: 7_1_39_134 | B42: SEGURIDAD VIAL Y DE CONDUCCIÓN | C42: 8.2 | D42: Gestión de rutas peligrosas | E42: No | F42: 1 | G42: Propósito: Nuestro proceso de trazado de rutas críticas nos obliga a evaluar las rutas que recorrerán nuestros conductores y a identificar los riesgos presentes en esas rutas. A continuación, estos riesgos deben comunicarse a nuestros conductores, y los riesgos que identifiquen deben ser comunicados de vuelta y comunicados a los demás. La unidad debe asegurarse de que existe un registro de los riesgos identificados, utilizando la cartelera de la team room, para que los miembros puedan consultar esta información . | H42: R8.2.1 - Los conductores participan en la actualización de la ruta/área crítica en la sala de equipo en el momento de la entrega. R8.2.2 - Proceso de evaluación y revisión de ruta/zona crítica implantado y expresado visualmente en el cuadro de mandos de seguridad de la sala del equipo de distribución. R8.2.3 - Acciones en marcha para resolver los problemas identificados en la sala del equipo de distribución. | I42: 5 - Se cumplen todos los requisitos 3 - R8.2.2 y R8.2.3 cumplidas, pero mala ejecución de R8.2.1 1 - Se cumple R8.2.2 pero no se aplica R8.2.3 0 - R8.2.2 no se cumple | J42: 1. Revisar las rutas críticas definidas: verificar que los conductores están incluidos en el proceso y participan en la actualización de la ruta/zona crítica en la sala del equipo de reparto. 2. Comprobar que el tablero de rutas críticas está actualizado en la team room de entrega. 3. Comprobar que se han tomado medidas para resolver los problemas detectados en la team room de entrega. | L42: =IF(AND(M42="N/A",N42="N/A"),"N/A",IF(OR(M42="",N42=""),"",SMALL(M42:N42,1))) -> 0 | M42: 0 | N42: N/A | O42: =IF(AND(P42="N/A",Q42="N/A"),"N/A",IF(OR(P42="",Q42=""),"",SMALL(P42:Q42,1))) -> 0 | P42: 0 | Q42: N/A | R42: =IF(OR(L42="",O42=""),"",IF(AND(L42="N/A",O42="N/A"),"N/A",AVERAGE(L42,O42))) -> 0
A43: 7_1_39_135 | B43: SEGURIDAD VIAL Y DE CONDUCCIÓN | C43: 8.3 | D43: Ejecución segura de la conducción | E43: No | F43: 1 | G43: Propósito: Garantizar que nuestros conductores siguen prácticas de conducción seguras utilizando nuestra formación y las rutinas OWD. | H43: R8.3.1 - Se describen, completan y ponen a disposición de los empleados prácticas seguras de conducción, ESTACIONAMIENTO y operación. R8.3.2 - Los conductores respetan las políticas de ABI y las normas de conducción segura (uso del cinturón de seguridad entre cada parada, uso de dispositivos electrónicos cuando sea necesario y esté autorizado). En caso de que se verifiquen desvios en el uso de cinturón de seguridad, en campo o auditoria se deberá cobrar el puntaje y se podrá Anular la pregunta. R8.3.3 - Supervisión de la seguridad y seguimiento del entrenamiento para proporcionar retroalimentación correctiva y reconocimiento positivo según corresponda. R8.3.4 - La dirección guía las OWD en la práctica de la conducción segura. | I43: 5 - Se cumplen todos los requisitos y tendencia de mejora en los resultados de coaching y OWD 3 - Se cumplen todos los requisitos, pero los resultados de entrenamiento y OWD no muestran una tendencia de mejora. 1 - Se cumple R8.3.1 pero no se cumple R8.3.2 (se ha producido un SIF potencial o un SIF actual relacionado con R8.3.2) 0 - R8.3.1 no se cumple o el lugar tiene algún incidente mortal relacionado con el tráfico (Empleado propio, Contratista, Comunidad). En caso de que se verifiquen desvios en el no uso de cinturón de seguridad, en campo o auditoria se deberá cobrar el puntaje y se podrá Anular la pregunta. | J43: 1. Observe la salida del conductor, la llegada al PDV, hable con los conductores: verifique si los conductores se adhieren a las políticas de conducción segura (uso del cinturón de seguridad entre cada parada, dispositivo electrónico utilizado cuando sea necesario y autorizado). 2. Verifique el formulario de reporte de incidentes: ¿ha habido un SIF potencial o un SIF real relacionado con las reglas de operación segura que no se siguen? 3. Verifique el registro de entrenamiento de la instalación: verifique si hay entrenamiento sobre prácticas de manejo seguro (positivo y correctivo). 4. Verifique las OWD de las instalaciones: verifique si se están realizando diagnósticos sobre prácticas de conducción segura. 5. Gestion del prontuario de choferes 6. Gestion de multas | L43: =IF(AND(M43="N/A",N43="N/A"),"N/A",IF(OR(M43="",N43=""),"",SMALL(M43:N43,1))) -> 0 | M43: 0 | N43: N/A | O43: =IF(AND(P43="N/A",Q43="N/A"),"N/A",IF(OR(P43="",Q43=""),"",SMALL(P43:Q43,1))) -> 0 | P43: 0 | Q43: N/A | R43: =IF(OR(L43="",O43=""),"",IF(AND(L43="N/A",O43="N/A"),"N/A",AVERAGE(L43,O43))) -> 0
A44: 7_1_39_136 | B44: SEGURIDAD VIAL Y DE CONDUCCIÓN | C44: 8.4 | D44: Gestión de telemetría | E44: SÍ | F44: 1 | G44: Propósito: garantizar que el comportamiento al conducir se monitoree en tiempo real para que los conductores cuenten con el conocimiento de cómo pueden cambiar su comportamiento para reducir el riesgo. La telemetría debe medirse y gestionarse. | H44: R8.4.1 - Todos (MINORISTAS Y LARGA DISTANCIA, PROPIOS Y DE TERCEROS) los vehículos equipados con un sistema de telemetría/GPS, siendo rastreados y con controles adecuados en el total de la flota de los camiones. R8.4.2 - La señal de telemetria del equipo es constante? Se puede evidenciar que el 100% de los camiones cuenta con telemetria activa. cumple con los kpis necesarias(uso de cinto, excesos de velocidad, frenada brusca, giro brusco) - conectividad. R8.4.3 - Existe un analisis de telemetria, se evidencia control interno para evaluar a los choferes en cuanto a los KPIs de telemetria? R8.4.4 - Programa de monitoreo/coaching implementado. R8.4.5 - Reglas de conducción segura establecidas y cumplidas por los conductores (como circular a velocidades seguras, usar cinturones de seguridad, no acelerar/desacelerar demasiado rápidamente y no tomar curvas demasiado rápido). | I44: Nivel 5: Todos los requisitos cumplidos (si están bloqueados por cuestiones legales/laborales y no se pueden lograr). Nivel 3: Todos los requisitos cumplidos, PERO no se cumple R8.4.3 (si están bloqueados por cuestiones legales/laborales y no se pueden lograr). Nivel 1: Se cumplen R8.4.1, R8.4.2 y R8.4.4, A MENOS QUE estén bloqueados por problemas legales/laborales, en cuyo caso solo se cumple R8.4.3 y R8.4.5. Nivel 0: No se cumple R8.4.1, A MENOS QUE estén bloqueados por problemas legales/laborales, en cuyo caso tampoco se cumple R8.4.4. | J44: 1.-Revisar el sistema de telemetría: verificar si hay un sistema de telemetría instalado en cada vehículo. 2.-Verificar si los datos se revisan y monitorean. 3.-Verificar si hay evidencia de que los conductores reciben coaching para mejorar su comportamiento y/o si existen procedimientos disciplinarios en marcha. | L44: =IF(AND(M44="N/A",N44="N/A"),"N/A",IF(OR(M44="",N44=""),"",SMALL(M44:N44,1))) -> 0 | M44: 0 | N44: N/A | O44: =IF(AND(P44="N/A",Q44="N/A"),"N/A",IF(OR(P44="",Q44=""),"",SMALL(P44:Q44,1))) -> 0 | P44: 0 | Q44: N/A | R44: =IF(OR(L44="",O44=""),"",IF(AND(L44="N/A",O44="N/A"),"N/A",AVERAGE(L44,O44))) -> 0
A45: 7_1_39_137 | B45: SEGURIDAD VIAL Y DE CONDUCCIÓN | C45: 8.5 | D45: Gestión de la jornada Laboral | E45: SÍ | F45: 1 | G45: Propósito: Garantizar que nuestros conductores no estén fatigados mientras conducen. Los empleados no deben trabajar más de 12 horas, por lo que las rutas deben planificarse de forma que el trayecto completo de un empleado se complete en menos de 12 horas. Toda superación de esta norma debe gestionarse a través del proceso de investigación de anomalías/incidentes con medidas correctoras diseñadas para evitar que se repita. | H45: R8.5.1 - Las rutas no superan las 12 horas. R8.5.2 - Investigación completa con acciones para evitar que se repita cuando cualquier ruta supere las 12 horas. | I45: 5 - Cero violaciones de R8.5.1 3 - Se cumple R8.5.2, pero se incumple R8.5.1 en <3% de las rutas. 1 - Se cumple R8.5.2, pero se infringe R8.5.1 en el 3-5% de las rutas. 0 - R8.5.2 no se cumple o R8.5.1 no se cumple en >5% de las rutas | J45: 1. Revisar los horarios de los conductores y hablar con ellos: comprobar que se cumplen las normas de itinerario y que los conductores no superan las 12 horas . 2. Si se observan infracciones de las normas sobre horarios, comprueba que se ha llevado a cabo una investigación con medidas para evitar que se repitan. | L45: =IF(AND(M45="N/A",N45="N/A"),"N/A",IF(OR(M45="",N45=""),"",SMALL(M45:N45,1))) -> 0 | M45: 0 | N45: N/A | O45: =IF(AND(P45="N/A",Q45="N/A"),"N/A",IF(OR(P45="",Q45=""),"",SMALL(P45:Q45,1))) -> 0 | P45: 0 | Q45: N/A | R45: =IF(OR(L45="",O45=""),"",IF(AND(L45="N/A",O45="N/A"),"N/A",AVERAGE(L45,O45))) -> 0
A46: 7_1_39_138 | B46: SEGURIDAD VIAL Y DE CONDUCCIÓN | C46: 8.6 | D46: Gestión del control de pesos | E46: SÍ | F46: 1 | G46: Propósito: Nunca debemos enviar un camión a una ruta con una carga que exceda la capacidad del camión o del carril por el que va a operar. Para más información, consulte el protocolo mundial de seguridad vial. | H46: R8.6.1 - Proceso implantado para impedir que se carguen camiones si la carga y las capacidades no coinciden. El distribuidor cuenta con ruteo centralizado R8.6.2 - Camiones con capacidad de carga señalizada. - Maestro de flota actualizado, VTV, RTO al día. R8.6.3 - Controles integrados en el proceso de carga para eliminar el sobrepeso. | I46: 5 - Se cumplen todos los requisitos y 0 casos de sobrecarga 3 - Se cumplen todos los requisitos, pero 1 caso de sobrecarga 1 - 1 requisito no cumplido y 1 sobrecarga 0 - >1 requisito no cumplido o >1 caso de sobrecarga | J46: 1. Compruebe que existe un proceso para impedir que se carguen camiones si la carga y las capacidades no coinciden. 2. Revisar la documentación de carga de los camiones: comprobar que la capacidad de los camiones está indicada en ellos e integrada en el proceso de carga. 3. Compruebe que hay un control integrado en el proceso de carga para eliminar el sobrepeso. | L46: =IF(AND(M46="N/A",N46="N/A"),"N/A",IF(OR(M46="",N46=""),"",SMALL(M46:N46,1))) -> 0 | M46: 0 | N46: N/A | O46: =IF(AND(P46="N/A",Q46="N/A"),"N/A",IF(OR(P46="",Q46=""),"",SMALL(P46:Q46,1))) -> 0 | P46: 0 | Q46: N/A | R46: =IF(OR(L46="",O46=""),"",IF(AND(L46="N/A",O46="N/A"),"N/A",AVERAGE(L46,O46))) -> 0
A47: 7_1_39_139 | B47: SEGURIDAD VIAL Y DE CONDUCCIÓN | C47: 8.7 | D47: Gestión de la seguridad en los desplazamientos/ IN ITINERES | E47: No | F47: 1 | G47: Propósito: Debemos garantizar que los miembros de nuestro equipo tengan los conocimientos necesarios para viajar con seguridad de su casa al trabajo y del trabajo a su casa. Para más información, consulte el toolkit de seguridad vial y el protocolo mundial de seguridad vial. | H47: R8.7.1 - Implementación de la seguridad en las rutas, evidenciada por una buena comunicación y material (carteles, vídeos, etc.). R8.7.2 - Los empleados conocen el material y el programa de conducción segura. R8.7.3 - Evaluación de riesgos de los tipos de viaje completada y revisada. R8.7.4 - Cero víctimas mortales en los desplazamientos al trabajo (in itinere). | I47: 5 - Se cumplen todos los requisitos 3 - Se cumplen todos los requisitos pero no se cumple R8.7.3 1 - R8.7.4 cumplida, pero violación de R8.7.1 0 - R8.7.4 no se cumple | J47: 1. Comprobar que se llevan los EPP adecuados durante el viaje. 2. Revisar el material sobre rutas seguras y hablar con los empleados: comprobar que hay pruebas de una buena comunicación y material para mejorar las prácticas/programas de rutas y que pueden explicar cómo la seguridad de las rutas es relevante para ellos. 3. Compruebe que existe una evaluación de riesgos completa para revisar los tipos de viajes y que el programa se centra en estas áreas. 4. Comprueba en la herramienta de gestión de incidentes si hay víctimas mortales en la unidad. | L47: =IF(AND(M47="N/A",N47="N/A"),"N/A",IF(OR(M47="",N47=""),"",SMALL(M47:N47,1))) -> 0 | M47: 0 | N47: N/A | O47: =IF(AND(P47="N/A",Q47="N/A"),"N/A",IF(OR(P47="",Q47=""),"",SMALL(P47:Q47,1))) -> 0 | P47: 0 | Q47: N/A | R47: =IF(OR(L47="",O47=""),"",IF(AND(L47="N/A",O47="N/A"),"N/A",AVERAGE(L47,O47))) -> 0
A48: 7_1_39_140 | B48: SEGURIDAD VIAL Y DE CONDUCCIÓN | C48: 8.8 | D48: Toolkit seguridad vial | E48: No | F48: 1 | G48: Propósito: la eliminación de accidentes fatales en carreteras y durante la conducción requerirá que tomemos medidas significativas. Los controles avanzados y las medidas identificadas en nuestro kit están diseñados para eliminar accidentes fatales de nuestros representantes, así como de los miembros de la comunidad. La evaluación de riesgos determina qué nivel de protección es necesario para un sitio y el kit dicta la implementación. Consulte la evaluación global de riesgos y el kit de seguridad vial para obtener más información. | H48: R8.8.1 - El Kit de Seguridad Vial está completado para la instalación. R8.8.2 - Hay un plan de acción en marcha y se gestiona para abordar las brechas en el kit. R8.8.3 - Las preguntas fundamentales del kit para el centro de distribución están por encima del 80%. R8.8.4 - Cero fatalidades ocupacionales o comunitarias en carreteras y durante la conducción. | I48: Nivel 5: Todos los requisitos cumplidos. Nivel 3: Todos los requisitos cumplidos, pero no se cumple R8.8.3. Nivel 1: Se cumple R8.8.4 y R8.8.1. Nivel 0: No se cumple R8.8.4. | J48: 1.-Verificar si la evaluación de riesgos se ha completado para la ubicación y si el nivel de riesgo es comprendido por todos los miembros del equipo local. 2.-Revisar el kit, realizar verificaciones aleatorias en varias preguntas para garantizar una puntuación precisa y observar las brechas identificadas en la ejecución. Verificar que la puntuación de las preguntas fundamentales esté por encima del 80%. 3.-Revisar el registro de acciones para asegurarse de que haya acciones en marcha para todas las brechas de ejecución y que estas acciones estén en camino. 4.-Revisar el rendimiento del sitio: determinar si ha habido algún accidente fatal ocupacional o comunitario. | L48: =IF(AND(M48="N/A",N48="N/A"),"N/A",IF(OR(M48="",N48=""),"",SMALL(M48:N48,1))) -> 0 | M48: 0 | N48: N/A | O48: =IF(AND(P48="N/A",Q48="N/A"),"N/A",IF(OR(P48="",Q48=""),"",SMALL(P48:Q48,1))) -> 0 | P48: 0 | Q48: N/A | R48: =IF(OR(L48="",O48=""),"",IF(AND(L48="N/A",O48="N/A"),"N/A",AVERAGE(L48,O48))) -> 0
B49: TRABAJO EN ALTURA | L49: =IF(COUNTIF(L50:L51,"=N/A")=4,"N/A", ((N(L50)*$F50)+(N(L51)*$F51)+(N(L51)*$F51)+(N(L51)*$F51))/(IF(L50="N/A",0,(5*$F50))+IF(L51="N/A",0,(5*$F51))+IF(L51="N/A",0,(5*$F51))+IF(L51="N/A",0,(5*$F51)))) -> 0 | M49: =IF(COUNTIF(M50:M52,"=N/A")=4,"N/A", ((N(M50)*$F50)+(N(M51)*$F51)+(N(M52)*$F52))/(IF(M50="N/A",0,(5*$F50))+IF(M51="N/A",0,(5*$F51))+IF(M52="N/A",0,(5*$F52)))) -> 0 | N49: =IF(COUNTIF(N50:N52,"=N/A")=4,"N/A", ((N(N50)*$F50)+(N(N51)*$F51)+(N(N52)*$F52))/(IF(N50="N/A",0,(5*$F50))+IF(N51="N/A",0,(5*$F51))+IF(N52="N/A",0,(5*$F52)))) -> #DIV/0! | O49: =IF(COUNTIF(O50:O52,"=N/A")=4,"N/A", ((N(O50)*$F50)+(N(O51)*$F51)+(N(O52)*$F52))/(IF(O50="N/A",0,(5*$F50))+IF(O51="N/A",0,(5*$F51))+IF(O52="N/A",0,(5*$F52)))) -> 0 | P49: =IF(COUNTIF(P50:P52,"=N/A")=4,"N/A", ((N(P50)*$F50)+(N(P51)*$F51)+(N(P52)*$F52))/(IF(P50="N/A",0,(5*$F50))+IF(P51="N/A",0,(5*$F51))+IF(P52="N/A",0,(5*$F52)))) -> 0 | Q49: =IF(COUNTIF(Q50:Q52,"=N/A")=4,"N/A", ((N(Q50)*$F50)+(N(Q51)*$F51)+(N(Q52)*$F52))/(IF(Q50="N/A",0,(5*$F50))+IF(Q51="N/A",0,(5*$F51))+IF(Q52="N/A",0,(5*$F52)))) -> #DIV/0! | R49: =IF(COUNTIF(R50:R52,"=N/A")=4,"N/A", ((N(R50)*$F50)+(N(R51)*$F51)+(N(R52)*$F52))/(IF(R50="N/A",0,(5*$F50))+IF(R51="N/A",0,(5*$F51))+IF(R52="N/A",0,(5*$F52)))) -> 0
A50: 7_1_40_141 | B50: TRABAJO EN ALTURA | C50: 9.1 | D50: Protección de Trabajos en Altura | E50: No | F50: 1 | G50: Identificar áreas con potencial de trabajo en altura y protección contra caídas y la Protección en Trabajos en Alturas. | H50: R9.1.1 - No hay bordes expuestos sin protección en la instalación. R9.1.2 - Métodos/equipos de protección adecuados en su lugar. R9.1.3 - Métodos/equipos de protección adecuados inspeccionados antes de su uso y utilizados cuando se realiza trabajo en alturas. R9.1.4 - Si está presente en la instalación, el sistema de línea de vida se inspecciona anualmente por una parte calificada. R9.1.5 - Se implementan controles de ingeniería para eliminar el trabajo en alturas. R9.1.6 - Si el trabajo en alturas no se elimina, se utiliza la jerarquía de controles para garantizar una protección adecuada. | I50: Nivel 5: Todos los requisitos cumplidos. Nivel 3: Se cumplen R9.1.1, R9.1.2, R9.1.3, R9.1.4 y R9.1.6, PERO no se cumple R9.1.5. Nivel 1: Se cumplen R9.1.1, R9.1.2, R9.1.3 y R9.1.4, PERO no se cumple R9.1.6. Nivel 0: No se cumplen R9.1.1, R9.1.2, R9.1.3 o R9.1.4. | J50: 1.-Realizar un recorrido por la instalación: verificar si hay bordes expuestos sin protección. 2.-Verificar si hay métodos de protección adecuados en su lugar, inspeccionados (la documentación debe tener fecha del año en curso o un máximo de 3 meses en relación con la emisión anterior) y en uso (como barandas, líneas de vida, andamios portátiles, escaleras rodantes, etc.). 3.-Verificar si se siguen y priorizan jerarquías de controles, centrándose primero en los controles de ingeniería y secundariamente en EPP/línea de vida. | L50: =IF(AND(M50="N/A",N50="N/A"),"N/A",IF(OR(M50="",N50=""),"",SMALL(M50:N50,1))) -> 0 | M50: 0 | N50: N/A | O50: =IF(AND(P50="N/A",Q50="N/A"),"N/A",IF(OR(P50="",Q50=""),"",SMALL(P50:Q50,1))) -> 0 | P50: 0 | Q50: N/A | R50: =IF(OR(L50="",O50=""),"",IF(AND(L50="N/A",O50="N/A"),"N/A",AVERAGE(L50,O50))) -> 0
A51: 7_1_40_142 | B51: TRABAJO EN ALTURA | C51: 9.2 | D51: Ejecución Segura de Trabajos en Altura | E51: No | F51: 1 | G51: Existen los controles y procedimientos anticaídas en trabajos en altura y la ejecución segura de trabajos en altura. | H51: R9.2.1 - Procedimientos de trabajo en altura escritos, completos y puestos a disposición de los empleados. R9.2.2 - Empleados realizan trabajos en altura de acuerdo con el procedimiento. R9.2.3 - Entrenamiento completado para garantizar que los empleados realizan el trabajo en altura de acuerdo con el procedimiento. R9.2.4 - La dirección lleva a cabo procedimientos de OWD para trabajos en altura. | I51: 5 - Se cumplen todos los requisitos y tendencia de mejora en los resultados de coaching y OWD 3 - Si se cumplen todos los requisitos, pero los resultados de capacitación y OWD no muestran una tendencia de mejora. 1 - R9.2.1 se cumple pero R9.2.2 no se cumple (si se ha producido un SIF potencial o un SIF real relacionado con R9.2.2) 0 - R9.2.1 no se cumple | J51: 1. Revisar el trabajo realizado en altura: comprobar que los procedimientos para este trabajo están escritos, son completos y están a disposición de los empleados. 2. Compruebe que los empleados realizan los trabajos en altura de acuerdo con el procedimiento. 3. Compruebe la gestión de incidentes: ¿se ha producido un SIF potencial o un SIF actual relacionado con el incumplimiento de las normas de seguridad operativa? 4. Comprobar la herramienta/los informes de formación de la unidad: comprobar si existe formación sobre el trabajo en altura (positiva y correctiva). 5. Comprueba las OWD de la unidad: comprueba que se está llevando a cabo un seguimiento de los procedimientos de trabajo en altura. | L51: =IF(AND(M51="N/A",N51="N/A"),"N/A",IF(OR(M51="",N51=""),"",SMALL(M51:N51,1))) -> 0 | M51: 0 | N51: N/A | O51: =IF(AND(P51="N/A",Q51="N/A"),"N/A",IF(OR(P51="",Q51=""),"",SMALL(P51:Q51,1))) -> 0 | P51: 0 | Q51: N/A | R51: =IF(OR(L51="",O51=""),"",IF(AND(L51="N/A",O51="N/A"),"N/A",AVERAGE(L51,O51))) -> 0
A52: 7_1_40_143 | B52: TRABAJO EN ALTURA | C52: 9.3 | D52: Gestión de trabajos en techos | E52: No | F52: 1 | G52: Existen los controles y procedimientos protección en trabajos en altura y la ejecución segura de trabajos en altura. | H52: R9.3.1 - Plan/Procedimiento operativo estándar (SOP) de acceso a techos revisado y aprobado por el equipo de seguridad de la zona antes de acceder, según los requisitos estándar globales. R9.3.2 - Permisos de trabajo en techos disponibles y completados en los trabajos en altura, en el año actual. R9.3.3 - Control de acceso a techos implementado. | I52: Nivel 5: Todos los requisitos cumplidos. Nivel 0: Cualquier requisito que no se cumpla. | J52: 1.- Verificar si hay evidencia de que los planes de acceso a techos fueron revisados y aprobados por el equipo de seguridad de la zona antes de acceder al techo. 2.- Verificar si el trabajo de techo aprobado tiene un procedimiento/Procedimiento Operativo Estándar (SOP) correspondiente. 3.- Revisar proyectos de trabajos anteriores en techos/planes de acceso a techos y permisos de trabajo en techos: verificar si los permisos de trabajo en techos están disponibles, completados y verificados por un gerente o especialista en el lugar para todas las áreas. 4.- Verificar si el acceso al techo está asegurado. | L52: =IF(AND(M52="N/A",N52="N/A"),"N/A",IF(OR(M52="",N52=""),"",SMALL(M52:N52,1))) -> 0 | M52: 0 | N52: N/A | O52: =IF(AND(P52="N/A",Q52="N/A"),"N/A",IF(OR(P52="",Q52=""),"",SMALL(P52:Q52,1))) -> 0 | P52: 0 | Q52: N/A | R52: =IF(OR(L52="",O52=""),"",IF(AND(L52="N/A",O52="N/A"),"N/A",AVERAGE(L52,O52))) -> 0
B53: LOTO/SAM | L53: =IF(COUNTIF(L54:L56,"=N/A")=4,"N/A", ((N(L54)*$F54)+(N(L55)*$F55)+(N(L55)*$F55)+(N(L55)*$F55))/(IF(L54="N/A",0,(5*$F54))+IF(L55="N/A",0,(5*$F55))+IF(L55="N/A",0,(5*$F55))+IF(L55="N/A",0,(5*$F55)))) -> 0 | M53: =IF(COUNTIF(M54:M56,"=N/A")=4,"N/A", ((N(M54)*$F54)+(N(M55)*$F55)+(N(M55)*$F55)+(N(M56)*$F56))/(IF(M54="N/A",0,(5*$F54))+IF(M55="N/A",0,(5*$F55))+IF(M55="N/A",0,(5*$F55))+IF(M56="N/A",0,(5*$F56)))) -> 0 | N53: =IF(COUNTIF(N54:N56,"=N/A")=4,"N/A", ((N(N54)*$F54)+(N(N55)*$F55)+(N(N55)*$F55)+(N(N56)*$F56))/(IF(N54="N/A",0,(5*$F54))+IF(N55="N/A",0,(5*$F55))+IF(N55="N/A",0,(5*$F55))+IF(N56="N/A",0,(5*$F56)))) -> #DIV/0! | O53: =IF(COUNTIF(O54:O56,"=N/A")=4,"N/A", ((N(O54)*$F54)+(N(O55)*$F55)+(N(O55)*$F55)+(N(O56)*$F56))/(IF(O54="N/A",0,(5*$F54))+IF(O55="N/A",0,(5*$F55))+IF(O55="N/A",0,(5*$F55))+IF(O56="N/A",0,(5*$F56)))) -> 0 | P53: =IF(COUNTIF(P54:P56,"=N/A")=4,"N/A", ((N(P54)*$F54)+(N(P55)*$F55)+(N(P55)*$F55)+(N(P56)*$F56))/(IF(P54="N/A",0,(5*$F54))+IF(P55="N/A",0,(5*$F55))+IF(P55="N/A",0,(5*$F55))+IF(P56="N/A",0,(5*$F56)))) -> 0 | Q53: =IF(COUNTIF(Q54:Q56,"=N/A")=4,"N/A", ((N(Q54)*$F54)+(N(Q55)*$F55)+(N(Q55)*$F55)+(N(Q56)*$F56))/(IF(Q54="N/A",0,(5*$F54))+IF(Q55="N/A",0,(5*$F55))+IF(Q55="N/A",0,(5*$F55))+IF(Q56="N/A",0,(5*$F56)))) -> #DIV/0! | R53: =IF(COUNTIF(R54:R56,"=N/A")=4,"N/A", ((N(R54)*$F54)+(N(R55)*$F55)+(N(R55)*$F55)+(N(R56)*$F56))/(IF(R54="N/A",0,(5*$F54))+IF(R55="N/A",0,(5*$F55))+IF(R55="N/A",0,(5*$F55))+IF(R56="N/A",0,(5*$F56)))) -> 0
A54: 7_1_41_144 | B54: LOTO/SAM | C54: 10.1 | D54: Ejecución segura de SAM | E54: No | F54: 1 | G54: Existen controles de LOTOTO y seguridad de las máquinas y los requisitos de SAM. | H54: R10.1.1 - Flujo de determinación de SAM utilizado correctamente. R10.1.2 - Procedimiento SAM escrito y disponible para cada equipo. R10.1.3 - Procedimiento SAM bien ejecutado para cada equipo. R10.1.4 - Entrenamiento completado para asegurar que los operadores de SAM se adhieren al procedimiento. R10.1.5 - La dirección lleva a cabo procedimientos OWD para SAM. | I54: 5 - Se cumplen todos los requisitos y los resultados de coaching y OWD tienden a mejorar 3 - Se cumplen todos los requisitos, pero los resultados de entrenamiento y OWD no muestran una tendencia de mejora. 1 - Se cumplen R10.1.1 y R10.1.2 pero no se cumple R10.1.3 (se ha producido un SIF Potencial o un SIF Actual relacionado con R10.1.3) 0 - R10.1.1 o R10.1.2 no se cumple. | J54: 1. Compruebe que el flujo de determinación SAM se utiliza correctamente. 2. Compruebe que los procedimientos SAM están escritos y disponibles para cada equipo. 3. Verificar que los procedimientos SAM se realizan correctamente para cada equipo. 4. Compruebe si en el formulario de reporte de incidentes: ¿se ha producido un SIF potencial o un SIF actual relacionado con el incumplimiento de las normas de seguridad operativa? 5. Comprobar la herramienta/los informes de coaching de la unidad - comprobar que hay coaching en el SAM (positivo y correctivo). 6. Compruebe los OWD de las instalaciones: verifique que se está realizando un seguimiento de los procedimientos SAM. | L54: =IF(AND(M54="N/A",N54="N/A"),"N/A",IF(OR(M54="",N54=""),"",SMALL(M54:N54,1))) -> 0 | M54: 0 | N54: N/A | O54: =IF(AND(P54="N/A",Q54="N/A"),"N/A",IF(OR(P54="",Q54=""),"",SMALL(P54:Q54,1))) -> 0 | P54: 0 | Q54: N/A | R54: =IF(OR(L54="",O54=""),"",IF(AND(L54="N/A",O54="N/A"),"N/A",AVERAGE(L54,O54))) -> 0
A55: 7_1_41_145 | B55: LOTO/SAM | C55: 10.2 | D55: Ejecución segura de LOTO | E55: No | F55: 1 | G55: Existe un protocolo de LOTOTO y seguridad de los equipos para obtener más detalles sobre los requisitos de LOTO. | H55: R10.2.1 - Flujograma de determinación de LOTO utilizado apropiadamente. R10.2.2 - Procedimiento LOTO escrito y disponible para cada equipo. R10.2.3 - Procedimiento LOTO bien ejecutado para cada equipo. R10.2.4 - Entrenamiento completo para asegurar que los operadores cumplen con el procedimiento LOTO. R10.2.5 - Los lideres realizan OWD a los procedimientos LOTO. | I55: 5 - Se cumplen todos los requisitos y los resultados de coaching y OWD tienden a mejorar 3 - Se cumplen todos los requisitos, pero los resultados de entrenamiento y OWD no muestran una tendencia de mejora. 1 - Se cumplen R10.1.1 y R10.1.2 pero no se cumple R10.2.3 (se ha producido un SIF Potencial o un SIF Actual relacionado con R10.2.3) 0 - R10.2.1 o R10.2.2 no se cumple. | J55: 1. Compruebe que el flujo de determinación LOTO se utiliza correctamente. 2. Revisar el trabajo que requiere LOTO: verificar que los procedimientos para este trabajo están escritos, completos y a disposición de los empleados para cada tipo de equipo. 3. Verifique que los procedimientos LOTO se realizan correctamente para cada pieza del equipo. 4. Compruebe si en el formulario de reporte de incidentes: ¿hubo un SIF potencial o un SIF actual relacionado con el incumplimiento de las normas de seguridad operativa? 5. Compruebe la herramienta/los informes de entrenamiento de la unidad: compruebe el entrenamiento LOTO (positivo y correctivo). 6. Compruebe las OWD de la unidad: compruebe que se está realizando un seguimiento de los procedimientos LOTO. | L55: =IF(AND(M55="N/A",N55="N/A"),"N/A",IF(OR(M55="",N55=""),"",SMALL(M55:N55,1))) -> 0 | M55: 0 | N55: N/A | O55: =IF(AND(P55="N/A",Q55="N/A"),"N/A",IF(OR(P55="",Q55=""),"",SMALL(P55:Q55,1))) -> 0 | P55: 0 | Q55: N/A | R55: =IF(OR(L55="",O55=""),"",IF(AND(L55="N/A",O55="N/A"),"N/A",AVERAGE(L55,O55))) -> 0
A56: 7_1_41_146 | B56: LOTO/SAM | C56: 10.3 | D56: Gestión de equipos LOTO | E56: No | F56: 1 | G56: Existe un protocolo para LOTOTO y la seguridad de los equipos y los requisitos de los equipos LOTO. | H56: R10.3.1 - Equipo LOTO disponible. R10.3.2 - El equipo LOTO cumple con los requisitos del protocolo en cuanto a color y uso. R10.3.3 - El equipo LOTO se mantiene en buenas condiciones de funcionamiento (cerraduras de llave única, cajas de cerraduras múltiples disponibles, etc.). | I56: 5 - Se cumplen todos los requisitos 3 - R10.3.1 y R10.3.2 se cumplen pero R10.3.3 no se cumple 1 - Se cumple R10.3.1 pero no se cumple R10.3.2 0 - R10.3.1 no se cumple | J56: 1. Revise las zonas de almacenamiento del equipo LOTO: compruebe que el equipo LOTO está disponible de acuerdo con el protocolo._x000D_ 2. Compruebe que los equipos LOTO se mantienen en buen estado de funcionamiento, accesibles y mantenidos/5S (los candados son de llave única; existen cajas de cerraduras múltiples). | L56: =IF(AND(M56="N/A",N56="N/A"),"N/A",IF(OR(M56="",N56=""),"",SMALL(M56:N56,1))) -> 0 | M56: 0 | N56: N/A | O56: =IF(AND(P56="N/A",Q56="N/A"),"N/A",IF(OR(P56="",Q56=""),"",SMALL(P56:Q56,1))) -> 0 | P56: 0 | Q56: N/A | R56: =IF(OR(L56="",O56=""),"",IF(AND(L56="N/A",O56="N/A"),"N/A",AVERAGE(L56,O56))) -> 0
B57: SALUD OCUPACIONAL | L57: =IF(COUNTIF(L58:L59,"=N/A")=2,"N/A", ((N(L58)*$F58)+(N(L59)*$F59))/(IF(L58="N/A",0,(5*$F58))+IF(L59="N/A",0,(5*$F59)))) -> 0 | M57: =IF(COUNTIF(M58:M59,"=N/A")=2,"N/A", ((N(M58)*$F58)+(N(M59)*$F59))/(IF(M58="N/A",0,(5*$F58))+IF(M59="N/A",0,(5*$F59)))) -> 0 | N57: =IF(COUNTIF(N58:N59,"=N/A")=2,"N/A", ((N(N58)*$F58)+(N(N59)*$F59))/(IF(N58="N/A",0,(5*$F58))+IF(N59="N/A",0,(5*$F59)))) -> N/A | O57: =IF(COUNTIF(O58:O59,"=N/A")=2,"N/A", ((N(O58)*$F58)+(N(O59)*$F59))/(IF(O58="N/A",0,(5*$F58))+IF(O59="N/A",0,(5*$F59)))) -> 0 | P57: =IF(COUNTIF(P58:P59,"=N/A")=2,"N/A", ((N(P58)*$F58)+(N(P59)*$F59))/(IF(P58="N/A",0,(5*$F58))+IF(P59="N/A",0,(5*$F59)))) -> 0 | Q57: =IF(COUNTIF(Q58:Q59,"=N/A")=2,"N/A", ((N(Q58)*$F58)+(N(Q59)*$F59))/(IF(Q58="N/A",0,(5*$F58))+IF(Q59="N/A",0,(5*$F59)))) -> N/A | R57: =IF(COUNTIF(R58:R59,"=N/A")=2,"N/A", ((N(R58)*$F58)+(N(R59)*$F59))/(IF(R58="N/A",0,(5*$F58))+IF(R59="N/A",0,(5*$F59)))) -> 0
A58: 7_1_42_147 | B58: SALUD OCUPACIONAL | C58: 11.1 | D58: Notificación, investigación y gestión de las causas de las enfermedades profesionales | E58: SÍ | F58: 1 | G58: El propósito de la notificación e investigación de enfermedades es garantizar que los casos considerados no KPI desde el punto de vista de las lesiones se sigan investigando y se tomen medidas para evitar que se repitan. | H58: R11.1.1 - Proceso de notificación de enfermedades en marcha. Incluyendo a los FAI con trastornos músculo-esqueléticos. R11.1.2 - Enfermedades 100% documentadas en el sistema de gestión de incidentes (enfermedades por movimientos repetitivos, conservación de la audición). R11.1.3 - Casos con investigación finalizada. R11.1.4 - Gestionar campañas preventivas (adicciones, nutrición, deporte, etc) | I58: 5 - Se cumplen todos los requisitos 3 - R11.1.1 y R11.1.2 cumplidas, pero 1 violación de R11.1.3 1 - R11.1.1 cumplida pero 1 violación de R11.1.2 0 - R11.1.1 no se cumple o más de 2 violaciones de R11.1.2. | J58: 1. Revisar los informes sobre enfermedades y el sistema de documentación. 2. Compruebe que hay pruebas que demuestren que se notifican todas las enfermedades. 3. Comprobar que se ha completado la investigación de todas las enfermedades notificadas. 4. Comprueba si hay fallos en el proceso del sistema. | L58: =IF(AND(M58="N/A",N58="N/A"),"N/A",IF(OR(M58="",N58=""),"",SMALL(M58:N58,1))) -> 0 | M58: 0 | N58: N/A | O58: =IF(AND(P58="N/A",Q58="N/A"),"N/A",IF(OR(P58="",Q58=""),"",SMALL(P58:Q58,1))) -> 0 | P58: 0 | Q58: N/A | R58: =IF(OR(L58="",O58=""),"",IF(AND(L58="N/A",O58="N/A"),"N/A",AVERAGE(L58,O58))) -> 0
A59: 7_1_42_148 | B59: SALUD OCUPACIONAL | C59: 11.2 | D59: Gestión de Mediciones Iluminación y Ruido | E59: No | F59: 1 | G59: El Propósito es garantizar que, cuando proceda, se aplique y gestione un programa de conservación de la audición. Las pruebas para determinar los decibelios pueden ser realizadas por el personal del lugar y mediante un dosímetro o una aplicación en un smartphone. Si las lecturas son superiores a 85 dBa, el lugar debe trabajar con un especialista certificado para realizar una evaluación. | H59: R11.2.1 - Pruebas de decibelios, iluminación realizadas en zonas o tareas ruidosas dentro de la unidad. (no solo en depósito sino en camiónes, equipos, etc) R11.2.2 - Si las pruebas de decibelios, iluminación superan los niveles establecidos, programa de conservación de la audición en su lugar. (generar PDA para las obsevaciones o recomendaciones realizadas por el profesional que llevó a cabo el protocolo de medición) R11.2.3 - Programa de conservación de la audición bien gestionado, actualizado y que cubra todos los requisitos según el protocolo. R11.2.4 - Cambios documentados de los límites estándar. | I59: 5 - Se cumplen todos los requisitos 3 - Se cumplen R11.2.1 y R11.2.2 pero no se cumple R11.2.3 1 - Se cumple R11.2.1 pero no se cumple R11.2.2 0 - R11.2.1 no se cumple. | J59: 1. Revisar la evaluación de ruido y observar el funcionamiento: comprobar si se ha realizado una prueba de decibelios en las zonas o tareas ruidosas de la instalación. 2. Comprobar si existe un programa de conservación de la audición y si la prueba de decibelios supera los niveles definidos en el protocolo. 3. Comprobar si el programa está bien gestionado y cubre todos los requisitos según el protocolo. 4. Comprobar si se realizan evaluaciones médicas y se documentan los cambios de umbral. | L59: =IF(AND(M59="N/A",N59="N/A"),"N/A",IF(OR(M59="",N59=""),"",SMALL(M59:N59,1))) -> 0 | M59: 0 | N59: N/A | O59: =IF(AND(P59="N/A",Q59="N/A"),"N/A",IF(OR(P59="",Q59=""),"",SMALL(P59:Q59,1))) -> 0 | P59: 0 | Q59: N/A | R59: =IF(OR(L59="",O59=""),"",IF(AND(L59="N/A",O59="N/A"),"N/A",AVERAGE(L59,O59))) -> 0
B60: RESPUESTA ANTE EMERGENCIAS | L60: =IF(COUNTIF(L61:L65,"=N/A")=5,"N/A", ((N(L61)*$F61)+(N(L62)*$F62)+(N(L63)*$F63)+(N(L64)*$F64)+(N(L65)*$F65))/(IF(L61="N/A",0,(5*$F61))+IF(L62="N/A",0,(5*$F62))+IF(L63="N/A",0,(5*$F63))+IF(L64="N/A",0,(5*$F64))+IF(L65="N/A",0,(5*$F65)))) -> 0 | M60: =IF(COUNTIF(M61:M65,"=N/A")=5,"N/A", ((N(M61)*$F61)+(N(M62)*$F62)+(N(M63)*$F63)+(N(M64)*$F64)+(N(M65)*$F65))/(IF(M61="N/A",0,(5*$F61))+IF(M62="N/A",0,(5*$F62))+IF(M63="N/A",0,(5*$F63))+IF(M64="N/A",0,(5*$F64))+IF(M65="N/A",0,(5*$F65)))) -> 0 | N60: =IF(COUNTIF(N61:N65,"=N/A")=5,"N/A", ((N(N61)*$F61)+(N(N62)*$F62)+(N(N63)*$F63)+(N(N64)*$F64)+(N(N65)*$F65))/(IF(N61="N/A",0,(5*$F61))+IF(N62="N/A",0,(5*$F62))+IF(N63="N/A",0,(5*$F63))+IF(N64="N/A",0,(5*$F64))+IF(N65="N/A",0,(5*$F65)))) -> N/A | O60: =IF(COUNTIF(O61:O65,"=N/A")=5,"N/A", ((N(O61)*$F61)+(N(O62)*$F62)+(N(O63)*$F63)+(N(O64)*$F64)+(N(O65)*$F65))/(IF(O61="N/A",0,(5*$F61))+IF(O62="N/A",0,(5*$F62))+IF(O63="N/A",0,(5*$F63))+IF(O64="N/A",0,(5*$F64))+IF(O65="N/A",0,(5*$F65)))) -> 0 | P60: =IF(COUNTIF(P61:P65,"=N/A")=5,"N/A", ((N(P61)*$F61)+(N(P62)*$F62)+(N(P63)*$F63)+(N(P64)*$F64)+(N(P65)*$F65))/(IF(P61="N/A",0,(5*$F61))+IF(P62="N/A",0,(5*$F62))+IF(P63="N/A",0,(5*$F63))+IF(P64="N/A",0,(5*$F64))+IF(P65="N/A",0,(5*$F65)))) -> 0 | Q60: =IF(COUNTIF(Q61:Q65,"=N/A")=5,"N/A", ((N(Q61)*$F61)+(N(Q62)*$F62)+(N(Q63)*$F63)+(N(Q64)*$F64)+(N(Q65)*$F65))/(IF(Q61="N/A",0,(5*$F61))+IF(Q62="N/A",0,(5*$F62))+IF(Q63="N/A",0,(5*$F63))+IF(Q64="N/A",0,(5*$F64))+IF(Q65="N/A",0,(5*$F65)))) -> N/A | R60: =IF(COUNTIF(R61:R65,"=N/A")=5,"N/A", ((N(R61)*$F61)+(N(R62)*$F62)+(N(R63)*$F63)+(N(R64)*$F64)+(N(R65)*$F65))/(IF(R61="N/A",0,(5*$F61))+IF(R62="N/A",0,(5*$F62))+IF(R63="N/A",0,(5*$F63))+IF(R64="N/A",0,(5*$F64))+IF(R65="N/A",0,(5*$F65)))) -> 0
A61: 7_1_43_149 | B61: RESPUESTA ANTE EMERGENCIAS | C61: 12.1 | D61: Dispositivos médicos y botiquín de primeros auxilios | E61: No | F61: 1 | G61: El propósito de los dispositivos médicos y los botiquines de primeros auxilios es proporcionar una respuesta médica inmediata en caso de enfermedad o lesión aguda de una persona hasta que se disponga de tratamiento médico profesional. Independientemente de los requisitos normativos locales, en los requisitos se recogen nuestros requisitos. | H61: R12.1.1 - Desfibrilador externo automático (DEA) y botiquines de primeros auxilios disponibles y bien mantenidos. R12.1.2 - Proceso establecido para supervisar el uso de los dispositivos. R12.1.3 - Números de emergencia publicados y disponibles para todos los empleados. | I61: 5 - Se cumplen todos los requisitos. 3- Se cumple con al menos 1 botiquin en deposito y todos los camiones tienen 1 botiquin y capacitación de primero auxilios para su uso 1- Se cumple con al menos 1 botiquin en deposito y todos los camiones tienen 1 botiquin 0 - No se cumple ningún requisito. | J61: 1. Revisar los dispositivos médicos y los botiquines de primeros auxilios: Compruebe si los dispositivos (botiquines de primeros auxilios y DEA) están inspeccionados, bien mantenidos y a disposición de todos los empleados. 2. Comprobar si existe un sistema para controlar el uso del material de los botiquines de primeros auxilios. 3. Compruebe si los números de emergencia están a disposición de los empleados dentro y fuera de las instalaciones. | L61: =IF(AND(M61="N/A",N61="N/A"),"N/A",IF(OR(M61="",N61=""),"",SMALL(M61:N61,1))) -> 0 | M61: 0 | N61: N/A | O61: =IF(AND(P61="N/A",Q61="N/A"),"N/A",IF(OR(P61="",Q61=""),"",SMALL(P61:Q61,1))) -> 0 | P61: 0 | Q61: N/A | R61: =IF(OR(L61="",O61=""),"",IF(AND(L61="N/A",O61="N/A"),"N/A",AVERAGE(L61,O61))) -> 0
A62: 7_1_43_150 | B62: RESPUESTA ANTE EMERGENCIAS | C62: 12.2 | D62: Gestión del sistema de prevención y protección contra incendios | E62: SÍ | F62: 1 | G62: El propósito de la gestión de sistemas de protección contra incendios es garantizar que los sistemas y equipos existentes en una instalación para contener o prevenir un incendio sean funcionales si una situación de emergencia requiere su uso. | H62: R12.2.1 - Estrategia/sistema de prevención y protección contra incendios implantado. Señalización Gestión a la vista de cartelería ante emergencias. R12.2.2 - Estrategia/sistema de prevención y protección contra incendios bien ejecutado (almacenamiento adecuado de inflamables, limpieza, rociadores contra incendios, extintores, mantenimiento de hidrantes, rutas sin obstáculos, etc.). Carga de Fuego R12.2.3 - Comunicación de prevención colocada en las áreas necesarias. | I62: 5 - Se cumplen todos los requisitos. 3 - Se cumplen todos los requisitos excepto 1 caso de problema de limpieza/5S que afecta a la prevención de incendios o a la salida de emergencia. 1 - Se cumplen todos los requisitos excepto 2 casos de problemas de limpieza/5S que afectan a la prevención de incendios o a la salida de emergencia. 0 - Cualquier requisito distinto de la limpieza que no se cumpla o >2 casos de problemas de limpieza/5S que afecten a la prevención de incendios o a la salida. | J62: 1. Revisar las zonas de almacenamiento de inflamables, las vías de evacuación y las zonas generales: Comprobar si existe una Estrategia/Sistema de Prevención y Protección contra Incendios. 2. Comprobar si está bien ejecutada: los materiales inflamables están adecuadamente almacenados, las rutas no están obstruidas, se mantiene la limpieza, los rociadores contra incendios están colocados y con la separación adecuada, se accede adecuadamente a los extintores y a la boca de incendios y el equipo/sistema está dentro de la fecha de caducidad. 3. Compruebe si hay una comunicación de prevención colocada en las zonas necesarias. | L62: =IF(AND(M62="N/A",N62="N/A"),"N/A",IF(OR(M62="",N62=""),"",SMALL(M62:N62,1))) -> 0 | M62: 0 | N62: N/A | O62: =IF(AND(P62="N/A",Q62="N/A"),"N/A",IF(OR(P62="",Q62=""),"",SMALL(P62:Q62,1))) -> 0 | P62: 0 | Q62: N/A | R62: =IF(OR(L62="",O62=""),"",IF(AND(L62="N/A",O62="N/A"),"N/A",AVERAGE(L62,O62))) -> 0
A63: 7_1_43_151 | B63: RESPUESTA ANTE EMERGENCIAS | C63: 12.3 | D63: Plan de Respuesta a Emergencias | E63: No | F63: 1 | G63: Propósito: el propósito del Plan de Respuesta a Emergencias es identificar las emergencias y desastres naturales más probables que pueden ocurrir en la instalación y esbozar el procedimiento para manejar esas emergencias. | H63: R12.3.1 - Plan de Respuesta a Emergencias en su lugar y revisado anualmente. R12.3.2 - El Plan de Respuesta a Emergencias cubre todos los tipos de emergencias. R12.3.3 - El Plan de Respuesta a Emergencias incluye un plan de prevención de enfermedades transmisibles en caso de presentarse alguna situación sanitaria de emergencia (pandemia). | I63: Nivel 5: Todos los requisitos cumplidos. Nivel 3: Se cumplen R12.3.1 y R12.3.2, PERO no se cumple R12.3.3. Nivel 1: Se cumple R12.3.1, PERO no se cumple R12.3.2. Nivel 0: No se cumple R12.3.1. | J63: 1.-Revisar los planes de respuesta a emergencias de la instalación. 2.-Verificar si el plan ha sido revisado en los últimos 12 meses del año actual o un máximo de 13 meses en relación con la revisión anterior. 3.-Verificar si se cubren todas las emergencias relevantes. 4.-Verificar si se aborda la prevención de enfermedades transmisibles. | L63: =IF(AND(M63="N/A",N63="N/A"),"N/A",IF(OR(M63="",N63=""),"",SMALL(M63:N63,1))) -> 0 | M63: 0 | N63: N/A | O63: =IF(AND(P63="N/A",Q63="N/A"),"N/A",IF(OR(P63="",Q63=""),"",SMALL(P63:Q63,1))) -> 0 | P63: 0 | Q63: N/A | R63: =IF(OR(L63="",O63=""),"",IF(AND(L63="N/A",O63="N/A"),"N/A",AVERAGE(L63,O63))) -> 0
A64: 7_1_43_152 | B64: RESPUESTA ANTE EMERGENCIAS | C64: 12.4 | D64: Gestión especializada de Respuesta a Emergencias | E64: No | F64: 1 | G64: Propósito: En algunos lugares se necesitan equipos especializados de respuesta a emergencias debido a la falta de disponibilidad de respuesta inmediata a emergencias por parte de la administración local. Las personas que lleven a cabo estas actividades deben recibir una formación eficaz que garantice su preparación y eficacia. | H64: R12.4.1 - Equipo de respuesta a emergencias comunicado y expuesto visualmente para todos los empleados. R12.4.2 - Equipo de respuesta a emergencias identificado. R12.4.3 - Participación del equipo de respuesta de emergencias en los simulacros. | I64: 5 - Se cumplen todos los requisitos 3 - R12.4.2 y R12.4.1 se cumplen pero R12.4.3 no se cumplen 1 - Se cumple R12.4.2 pero no se cumple R12.4.1 0 - No se cumple R12.4.2. | J64: 1. Revise el procedimiento de respuesta ante emergencias, la señalización, la documentación y los paneles visuales: compruebe si los miembros del equipo de respuesta ante emergencias están señalizados visualmente para todos los empleados. 2. Compruebe si hay empleados que han sido identificados con responsabilidades específicas durante una emergencia. 3. Compruebe si los equipos de respuesta participan activamente en los simulacros. | L64: =IF(AND(M64="N/A",N64="N/A"),"N/A",IF(OR(M64="",N64=""),"",SMALL(M64:N64,1))) -> 0 | M64: 0 | N64: N/A | O64: =IF(AND(P64="N/A",Q64="N/A"),"N/A",IF(OR(P64="",Q64=""),"",SMALL(P64:Q64,1))) -> 0 | P64: 0 | Q64: N/A | R64: =IF(OR(L64="",O64=""),"",IF(AND(L64="N/A",O64="N/A"),"N/A",AVERAGE(L64,O64))) -> 0
A65: 7_1_43_153 | B65: RESPUESTA ANTE EMERGENCIAS | C65: 12.5 | D65: Gestión de Simulacros de Respuesta a Emergencias | E65: No | F65: 1 | G65: El propósito de los simulacros de respuesta ante emergencias es practicar la respuesta esperada ante una situación de emergencia, de modo que los equipos cuenten con las habilidades necesarias para responder a ella en caso de que se produzca. Cuando el bombero identifica GAPs en la ejecución de la respuesta, es crítico que la unidad gestione acciones para cerrar esos GAPs. | H65: R12.5.1 - Simulacros documentados con detalle de tiempos desde que sonó el alerta hasta la pultima persona en llegar al punto de encuentro & conclusiones con oportunidades de mejoras detectadas en caso de corresponder. R12.5.2 - Simulacros cubiertos/realizados para todos los empleados de almacén y distribución, cada tipo de emergencia y para todos los turnos/áreas. 90% de adherencia al simulacro por área (almacén y distribución) R12.5.3 - Acciones en marcha para cerrar los GAPs identificadas durante el simulacro. | I65: 5 - Se cumplen todos los requisitos 3 - R12.5.2 y R12.5.1 cumplidas pero R12.5.3 implementada pero no actualizada 1 - R12.5.2 cumplida pero R12.5.1 no se cumple 0 -R12.5.2 no se cumple | J65: 1. Revisar la documentación del simulacro. 2. Comprobar si se realizan simulacros para responder a cada tipo de emergencia y si se realizan para cada turno/área. 3. Compruebe si se generan acciones claras para cerrar las deficiencias detectadas durante el simulacro. | L65: =IF(AND(M65="N/A",N65="N/A"),"N/A",IF(OR(M65="",N65=""),"",SMALL(M65:N65,1))) -> 0 | M65: 0 | N65: N/A | O65: =IF(AND(P65="N/A",Q65="N/A"),"N/A",IF(OR(P65="",Q65=""),"",SMALL(P65:Q65,1))) -> 0 | P65: 0 | Q65: N/A | R65: =IF(OR(L65="",O65=""),"",IF(AND(L65="N/A",O65="N/A"),"N/A",AVERAGE(L65,O65))) -> 0
B66: FORMACIÓN Y COMPETENCIA | L66: =IF(COUNTIF(L67:L68,"=N/A")=2,"N/A", ((N(L67)*$F67)+(N(L68)*$F68))/(IF(L67="N/A",0,(5*$F67))+IF(L68="N/A",0,(5*$F68)))) -> 0 | M66: =IF(COUNTIF(M67:M68,"=N/A")=2,"N/A", ((N(M67)*$F67)+(N(M68)*$F68))/(IF(M67="N/A",0,(5*$F67))+IF(M68="N/A",0,(5*$F68)))) -> 0 | N66: =IF(COUNTIF(N67:N68,"=N/A")=2,"N/A", ((N(N67)*$F67)+(N(N68)*$F68))/(IF(N67="N/A",0,(5*$F67))+IF(N68="N/A",0,(5*$F68)))) -> N/A | O66: =IF(COUNTIF(O67:O68,"=N/A")=2,"N/A", ((N(O67)*$F67)+(N(O68)*$F68))/(IF(O67="N/A",0,(5*$F67))+IF(O68="N/A",0,(5*$F68)))) -> 0 | P66: =IF(COUNTIF(P67:P68,"=N/A")=2,"N/A", ((N(P67)*$F67)+(N(P68)*$F68))/(IF(P67="N/A",0,(5*$F67))+IF(P68="N/A",0,(5*$F68)))) -> 0 | Q66: =IF(COUNTIF(Q67:Q68,"=N/A")=2,"N/A", ((N(Q67)*$F67)+(N(Q68)*$F68))/(IF(Q67="N/A",0,(5*$F67))+IF(Q68="N/A",0,(5*$F68)))) -> N/A | R66: =IF(COUNTIF(R67:R68,"=N/A")=2,"N/A", ((N(R67)*$F67)+(N(R68)*$F68))/(IF(R67="N/A",0,(5*$F67))+IF(R68="N/A",0,(5*$F68)))) -> 0
A67: 7_1_44_154 | B67: FORMACIÓN Y COMPETENCIA | C67: 13.1 | D67: GESTION DE ENTRENAMIENTOS | E67: No | F67: 1 | G67: Propósito: el propósito de la capacitación anual en seguridad es asegurar que los miembros del equipo reciban un repaso sobre todos los temas relevantes de seguridad para su instalación. Los requisitos enumeran los requisitos mínimos mundialmente obligatorios. Cada sitio puede identificar requisitos de capacitación adicionales. La capacitación debe desarrollarse y entregarse de manera que maximice la comprensión de la audiencia. El objetivo de cualquier capacitación es que la persona que la recibe pueda recordarla y usarla cuando sea necesario. Asegúrese de que la capacitación se cree con este propósito en mente. | H67: R13.1.1 - El contenido de la capacitación aborda los temas requeridos. R13.1.2 - Se proporciona capacitación anual de conciencia a todos los empleados cubriendo AL MENOS los siguientes temas: (1. Reporte de Lesiones, 2. Definición de Situación de Peligro Significativo y Investigación de Incidentes; 3. Seguridad en el Transporte en el Lugar de Trabajo; 4. Manipulación Manual de Materiales; 5. Sustancias Peligrosas; 6. Espacios Confinados; 7. Prevención de la Violencia; 8. Conducción Segura/Conducción Defensiva; 9. PRE IN ITINERES Seguridad en el Desplazamiento; 10. Trabajo en Alturas; 11. SAM / LOTO; 12. Monitoreo de Seguridad / Coaching (enfoque de la gerencia); 13. Conocimientos Básicos de Capa Fundamenta (enfoque de la gerencia); 14. Salud Ocupacional; 15. Respuesta a Emergencias). R13.1.3 - Los empleados demuestran plena competencia en el contenido de la capacitación y pueden explicar cómo se aplica a ellos/relaciona con su trabajo. 90% adherencia al Gantt - por área (o simil formato del pac), 95% adherencia a la asistencia & 80% adherencia a los test de validación conceptual para empleados R13.1.4 - Los resultados del coaching en la instalación se utilizan para actualizar el contenido de la capacitación. | I67: Nivel 5: Todos los temas de capacitación están incluidos con una tasa de finalización >95% para todos los empleados, Y los empleados demuestran competencia al explicar cómo se aplica a su trabajo, Y las tendencias de coaching se utilizan para actualizar el material de capacitación. Nivel 3: Todos los temas de capacitación están incluidos con una tasa de finalización >95% para todos los empleados, Y los empleados demuestran competencia al explicar cómo se aplica a su trabajo. Nivel 1: Todos los temas de capacitación están incluidos PERO 1-3 temas de capacitación tienen una tasa de finalización <95% para todos los empleados O los empleados no demuestran competencia completa. Nivel 0: Cualquier tema de capacitación no está incluido O >3 temas de capacitación tienen una tasa de finalización <95% para todos los empleados. | J67: 1. Revisar el contenido de la capacitación: verificar si se abordan los temas requeridos. 2. Verificar si se ha extendido a todos los empleados / gerentes necesarios. 3. Todas las capacitaciones deben tener una fecha dentro del año actual o un máximo de 13 meses en relación con la anterior. 4. Hablar con empleados / gerentes para asegurarse de que puedan explicar el contenido y cómo se aplica a ellos/se relaciona con su trabajo. 5. Revisar los resultados del coaching: verificar si las tendencias del coaching se utilizan para actualizar el contenido / comunicación de la capacitación. | L67: =IF(AND(M67="N/A",N67="N/A"),"N/A",IF(OR(M67="",N67=""),"",SMALL(M67:N67,1))) -> 0 | M67: 0 | N67: N/A | O67: =IF(AND(P67="N/A",Q67="N/A"),"N/A",IF(OR(P67="",Q67=""),"",SMALL(P67:Q67,1))) -> 0 | P67: 0 | Q67: N/A | R67: =IF(OR(L67="",O67=""),"",IF(AND(L67="N/A",O67="N/A"),"N/A",AVERAGE(L67,O67))) -> 0
A68: 7_1_44_155 | B68: FORMACIÓN Y COMPETENCIA | C68: 13.2 | D68: Gestión de Entrenamientos Calificados | E68: SÍ | F68: 1 | G68: Propósito: el propósito de la capacitación de calificación es calificar a una persona para una tarea compleja o de otro modo regulada. En estas circunstancias, una persona debe estar preparada con capacitación especializada, ya sea según lo establecido por una agencia reguladora o según el diseño y la regulación del equipo . La capacitación de calificación debe incluir tanto elementos teóricos como prácticos, así como una prueba para demostrar competencia. | H68: R13.2.1 - El contenido de la capacitación aborda los temas requeridos. R13.2.2 - Se proporciona capacitación de conciencia de calificación a todos los empleados que realizarán tareas especiales que cubren AL MENOS las siguientes tareas: (1. Operación de Montacargas / Vehículo Industrial Motorizado; 2. Operación de Equipo de Elevación; 3. Suministro de Gas Licuado de Petróleo (GLP); 4. Carga / Riego de Baterías; 5. Suministro de Gasolina / Diesel; 6. Manipulación de Gas Comprimido; 7. Entrada a Espacios Confinados; 8. Rescate en Espacios Confinados; 9. Manejo de Efectivo; 10. Conducción Comercial; 11. Trabajo en Alturas; 12. SAM; 13. LOTO; 14. Primeros Auxilios / RCP / DEA; 15. Brigada contra Incendios; 16. Autorización de Permiso de Trabajo). R13.2.3 - Los empleados demuestran plena competencia en el contenido de la capacitación y pueden explicar cómo se aplica a ellos/relaciona con su trabajo. 90% adherencia al Gantt - por área (o simil formato del pac), 100% adherencia a la asistencia & 80% adherencia a los test de validación conceptual para empleados calificados R13.2.4 - Cuando el protocolo requiere una validación anual documentada de la calificación, se completa. | I68: 5 - Todos los temas de calificación aplicables están incluidos con un 100% de finalización para todos los empleados Y los empleados demuestran plena competencia Y la validación anual se completa según lo requerido. 3 - Todos los temas de calificación aplicables están incluidos con un 100% de finalización para todos los empleados Y la validación anual se completa según lo requerido, PERO los empleados no demuestran plena competencia. 1 - Todos los temas de calificación aplicables están incluidos con un 100% de finalización para todos los empleados PERO falta 1 la capacotación de una persona. 0 - Falta cualquier tema de calificación y certificado, para los empleados, no hay gestión en curso para la capacitación. | J68: 1. Revisar el contenido de la capacitación: verificar si se abordan los temas requeridos. 2. Verificar si se ha implementado para todos los empleados / gerentes requeridos. 3. Todas las capacitaciones deben tener una fecha dentro del año actual o un máximo de 13 meses en relación con la revisión anterior. 4. Hablar con los empleados / gerentes para asegurarse de que puedan explicar el contenido y cómo se aplica a ellos / se relaciona con su trabajo. 5. Revisar la validación anual documentada de la calificación según lo requerido por los protocolos. | L68: =IF(AND(M68="N/A",N68="N/A"),"N/A",IF(OR(M68="",N68=""),"",SMALL(M68:N68,1))) -> 0 | M68: 0 | N68: N/A | O68: =IF(AND(P68="N/A",Q68="N/A"),"N/A",IF(OR(P68="",Q68=""),"",SMALL(P68:Q68,1))) -> 0 | P68: 0 | Q68: N/A | R68: =IF(OR(L68="",O68=""),"",IF(AND(L68="N/A",O68="N/A"),"N/A",AVERAGE(L68,O68))) -> 0
B69: GESTIÓN PARA MANTENER | L69: =IF(COUNTBLANK(L70:L80)>0,"-", IF(AND(L70="N/A",L76="N/A"),"N/A", (N(L71)*$F71+ N(L72)*$F72+ N(L73)*$F73+ N(L74)*$F74+ N(L75)*$F75+ N(L77)*$F77+ N(L78)*$F78+ N(L79)*$F79+ N(L80)*$F80) /(IF(L71="N/A",0,$F71*5)+ IF(L72="N/A",0,$F72*5)+ IF(L73="N/A",0,$F73*5)+ IF(L74="N/A",0,$F74*5)+ IF(L75="N/A",0,$F75*5)+ IF(L77="N/A",0,$F77*5)+ IF(L78="N/A",0,$F78*5)+ IF(L79="N/A",0,$F79*5)+ IF(L80="N/A",0,$F80*5)))) -> 0 | M69: =IF(COUNTBLANK(M70:M80)>0,"-", IF(AND(M70="N/A",M76="N/A"),"N/A", (N(M71)*$F71+ N(M72)*$F72+ N(M73)*$F73+ N(M74)*$F74+ N(M75)*$F75+ N(M77)*$F77+ N(M78)*$F78+ N(M79)*$F79+ N(M80)*$F80) /(IF(M71="N/A",0,$F71*5)+ IF(M72="N/A",0,$F72*5)+ IF(M73="N/A",0,$F73*5)+ IF(M74="N/A",0,$F74*5)+ IF(M75="N/A",0,$F75*5)+ IF(M77="N/A",0,$F77*5)+ IF(M78="N/A",0,$F78*5)+ IF(M79="N/A",0,$F79*5)+ IF(M80="N/A",0,$F80*5)))) -> 0 | N69: =IF(COUNTBLANK(N70:N80)>0,"-", IF(AND(N70="N/A",N76="N/A"),"N/A", (N(N71)*$F71+ N(N72)*$F72+ N(N73)*$F73+ N(N74)*$F74+ N(N75)*$F75+ N(N77)*$F77+ N(N78)*$F78+ N(N79)*$F79+ N(N80)*$F80) /(IF(N71="N/A",0,$F71*5)+ IF(N72="N/A",0,$F72*5)+ IF(N73="N/A",0,$F73*5)+ IF(N74="N/A",0,$F74*5)+ IF(N75="N/A",0,$F75*5)+ IF(N77="N/A",0,$F77*5)+ IF(N78="N/A",0,$F78*5)+ IF(N79="N/A",0,$F79*5)+ IF(N80="N/A",0,$F80*5)))) -> N/A | O69: =IF(COUNTBLANK(O70:O80)>0,"-", IF(AND(O70="N/A",O76="N/A"),"N/A", (N(O71)*$F71+ N(O72)*$F72+ N(O73)*$F73+ N(O74)*$F74+ N(O75)*$F75+ N(O77)*$F77+ N(O78)*$F78+ N(O79)*$F79+ N(O80)*$F80) /(IF(O71="N/A",0,$F71*5)+ IF(O72="N/A",0,$F72*5)+ IF(O73="N/A",0,$F73*5)+ IF(O74="N/A",0,$F74*5)+ IF(O75="N/A",0,$F75*5)+ IF(O77="N/A",0,$F77*5)+ IF(O78="N/A",0,$F78*5)+ IF(O79="N/A",0,$F79*5)+ IF(O80="N/A",0,$F80*5)))) -> 0 | P69: =IF(COUNTBLANK(P70:P80)>0,"-", IF(AND(P70="N/A",P76="N/A"),"N/A", (N(P71)*$F71+ N(P72)*$F72+ N(P73)*$F73+ N(P74)*$F74+ N(P75)*$F75+ N(P77)*$F77+ N(P78)*$F78+ N(P79)*$F79+ N(P80)*$F80) /(IF(P71="N/A",0,$F71*5)+ IF(P72="N/A",0,$F72*5)+ IF(P73="N/A",0,$F73*5)+ IF(P74="N/A",0,$F74*5)+ IF(P75="N/A",0,$F75*5)+ IF(P77="N/A",0,$F77*5)+ IF(P78="N/A",0,$F78*5)+ IF(P79="N/A",0,$F79*5)+ IF(P80="N/A",0,$F80*5)))) -> 0 | Q69: =IF(COUNTBLANK(Q70:Q80)>0,"-", IF(AND(Q70="N/A",Q76="N/A"),"N/A", (N(Q71)*$F71+ N(Q72)*$F72+ N(Q73)*$F73+ N(Q74)*$F74+ N(Q75)*$F75+ N(Q77)*$F77+ N(Q78)*$F78+ N(Q79)*$F79+ N(Q80)*$F80) /(IF(Q71="N/A",0,$F71*5)+ IF(Q72="N/A",0,$F72*5)+ IF(Q73="N/A",0,$F73*5)+ IF(Q74="N/A",0,$F74*5)+ IF(Q75="N/A",0,$F75*5)+ IF(Q77="N/A",0,$F77*5)+ IF(Q78="N/A",0,$F78*5)+ IF(Q79="N/A",0,$F79*5)+ IF(Q80="N/A",0,$F80*5)))) -> N/A | R69: =IF(COUNTBLANK(R70:R80)>0,"-", IF(AND(R70="N/A",R76="N/A"),"N/A", (N(R71)*$F71+ N(R72)*$F72+ N(R73)*$F73+ N(R74)*$F74+ N(R75)*$F75+ N(R77)*$F77+ N(R78)*$F78+ N(R79)*$F79+ N(R80)*$F80) /(IF(R71="N/A",0,$F71*5)+ IF(R72="N/A",0,$F72*5)+ IF(R73="N/A",0,$F73*5)+ IF(R74="N/A",0,$F74*5)+ IF(R75="N/A",0,$F75*5)+ IF(R77="N/A",0,$F77*5)+ IF(R78="N/A",0,$F78*5)+ IF(R79="N/A",0,$F79*5)+ IF(R80="N/A",0,$F80*5)))) -> 0
B70: GESTIÓN DE LA SEGURIDAD OPERACIONAL | L70: =IF(COUNTIF(L71:L75,"=N/A")=5,"N/A", ((N(L71)*$F71)+(N(L72)*$F72)+(N(L73)*$F73)+(N(L74)*$F74)+(N(L75)*$F75))/(IF(L71="N/A",0,(5*$F71))+IF(L72="N/A",0,(5*$F72))+IF(L73="N/A",0,(5*$F73))+IF(L74="N/A",0,(5*$F74))+IF(L75="N/A",0,(5*$F75)))) -> 0 | M70: =IF(COUNTIF(M71:M75,"=N/A")=5,"N/A", ((N(M71)*$F71)+(N(M72)*$F72)+(N(M73)*$F73)+(N(M74)*$F74)+(N(M75)*$F75))/(IF(M71="N/A",0,(5*$F71))+IF(M72="N/A",0,(5*$F72))+IF(M73="N/A",0,(5*$F73))+IF(M74="N/A",0,(5*$F74))+IF(M75="N/A",0,(5*$F75)))) -> 0 | N70: =IF(COUNTIF(N71:N75,"=N/A")=5,"N/A", ((N(N71)*$F71)+(N(N72)*$F72)+(N(N73)*$F73)+(N(N74)*$F74)+(N(N75)*$F75))/(IF(N71="N/A",0,(5*$F71))+IF(N72="N/A",0,(5*$F72))+IF(N73="N/A",0,(5*$F73))+IF(N74="N/A",0,(5*$F74))+IF(N75="N/A",0,(5*$F75)))) -> N/A | O70: =IF(COUNTIF(O71:O75,"=N/A")=5,"N/A", ((N(O71)*$F71)+(N(O72)*$F72)+(N(O73)*$F73)+(N(O74)*$F74)+(N(O75)*$F75))/(IF(O71="N/A",0,(5*$F71))+IF(O72="N/A",0,(5*$F72))+IF(O73="N/A",0,(5*$F73))+IF(O74="N/A",0,(5*$F74))+IF(O75="N/A",0,(5*$F75)))) -> 0 | P70: =IF(COUNTIF(P71:P75,"=N/A")=5,"N/A", ((N(P71)*$F71)+(N(P72)*$F72)+(N(P73)*$F73)+(N(P74)*$F74)+(N(P75)*$F75))/(IF(P71="N/A",0,(5*$F71))+IF(P72="N/A",0,(5*$F72))+IF(P73="N/A",0,(5*$F73))+IF(P74="N/A",0,(5*$F74))+IF(P75="N/A",0,(5*$F75)))) -> 0 | Q70: =IF(COUNTIF(Q71:Q75,"=N/A")=5,"N/A", ((N(Q71)*$F71)+(N(Q72)*$F72)+(N(Q73)*$F73)+(N(Q74)*$F74)+(N(Q75)*$F75))/(IF(Q71="N/A",0,(5*$F71))+IF(Q72="N/A",0,(5*$F72))+IF(Q73="N/A",0,(5*$F73))+IF(Q74="N/A",0,(5*$F74))+IF(Q75="N/A",0,(5*$F75)))) -> N/A | R70: =IF(COUNTIF(R71:R75,"=N/A")=5,"N/A", ((N(R71)*$F71)+(N(R72)*$F72)+(N(R73)*$F73)+(N(R74)*$F74)+(N(R75)*$F75))/(IF(R71="N/A",0,(5*$F71))+IF(R72="N/A",0,(5*$F72))+IF(R73="N/A",0,(5*$F73))+IF(R74="N/A",0,(5*$F74))+IF(R75="N/A",0,(5*$F75)))) -> 0
A71: 7_2_45_156 | B71: GESTIÓN DE LA SEGURIDAD OPERACIONAL | C71: 14.1 | D71: Gestión de inventarios | E71: SÍ | F71: 1 | G71: El propósito de los inventarios de seguridad es catalogar los riesgos conocidos, como los espacios confinados o los bastidores, así como las protecciones, como los procedimientos o los dispositivos LOTO. Estos inventarios nos permiten asegurarnos de que todo está contabilizado, actualizado y de que cualquier persona de la unidad puede acceder a esta información. | H71: R14.1.1 - Inventario de los activos (maquinas, herramientas, equipos industriales, equipos motorizados de almacén y distribución) necesarios definidos en los protocolos. R14.1.2 - Inventario de bienes de la unidad bien mantenido y actualizado. | I71: 5 - El inventario está disponible y completo y actualizado. 3 - El inventario de los activos de la instalación está disponible, pero 1 elemento obligatorio tiene un GAPs 1 - El inventario de activos de las instalaciones está disponible, pero 2 elementos obligatorios tiene un GAPs. 0 - El inventario de activos de la instalación no está disponible y completo o >2 elementos obligatorios tiene un GAPs. | J71: 1. Revisar los inventarios de activos y compararlos la unidad: comprobar que todos los activos están recogidos en el inventario tal y como exige el protocolo (por ejemplo, maquinaria, equipos, espacios confinados, EPP, escaleras, vehículos, etc.) y que el inventario está disponible. 2. Comprueba que el inventario de la unidad está bien mantenido y actualizado. | L71: =IF(AND(M71="N/A",N71="N/A"),"N/A",IF(OR(M71="",N71=""),"",SMALL(M71:N71,1))) -> 0 | M71: 0 | N71: N/A | O71: =IF(AND(P71="N/A",Q71="N/A"),"N/A",IF(OR(P71="",Q71=""),"",SMALL(P71:Q71,1))) -> 0 | P71: 0 | Q71: N/A | R71: =IF(OR(L71="",O71=""),"",IF(AND(L71="N/A",O71="N/A"),"N/A",AVERAGE(L71,O71))) -> 0
A72: 7_2_45_157 | B72: GESTIÓN DE LA SEGURIDAD OPERACIONAL | C72: 14.2 | D72: Gestión de la evaluación de riesgos | E72: SÍ | F72: 1 | G72: El propósito de nuestro proceso de evaluación de riesgos es acceder a todos los procesos a nivel de tarea, determinar qué riesgos existen y qué protecciones se aplican para mitigarlos. Las evaluaciones de riesgos deben realizarse con el empleado del área. Esto significa que los empleados del área deben participar en la creación de una evaluación de riesgos. Una evaluación de riesgos debe detallarse a nivel de tarea para que la persona que realiza el trabajo pueda ver qué riesgos existen en cada paso del proceso, así como qué proceso minimiza ese riesgo. A menudo confiamos en que el comportamiento de la persona que realiza el trabajo forme parte de lo que la mantiene a salvo; éste nunca es nuestro control más eficaz, pero no lo es en absoluto si los miembros del equipo no tienen acceso a cuál es exactamente su actuación. | H72: R14.2.1 - Evaluación de riesgos de áreas, puestos y tareas completada para todas las áreas cubiertas y tareas realizadas en la unidad. R14.2.2 - Se aplican controles jerárquicos con controles técnicos prioritarios y se definen controles para todas las áreas y tareas. R14.2.3 - Dependencia mínima de los controles administrativos/EPP/Proceso. R14.2.4 - Evaluación de riesgos de áreas y tareas actualizada para cada nuevo proceso y equipo añadido antes de su uso y si se modifican los procesos de las tareas. | I72: 5 - Todos los requisitos cumplieron 3 - R14.2.1 y R14.2.4 se cumplen pero 14.2.3 no cumple 1 - R14.2.1 se cumple pero R14.2.4 no cumple 0 - R14.2.1 no cumple | J72: 1. Compruebe que existe una evaluación de riesgos de áreas y tareas que cubre todas las áreas y tareas enumeradas en el mapa de procesos o que se llevan a cabo dentro/fuera de la unidad. 2. Comprobar que se han definido los controles adecuados, dando prioridad a los controles de eliminación/ingeniería. 3. Observe si la unidad depende en exceso de los EPP y de los controles administrativos. 4. Compruebe que la evaluación de riesgos se actualiza a medida que se añaden nuevos procesos y equipos y se modifican los procesos de las tareas, ANTES de su uso. | L72: =IF(AND(M72="N/A",N72="N/A"),"N/A",IF(OR(M72="",N72=""),"",SMALL(M72:N72,1))) -> 0 | M72: 0 | N72: N/A | O72: =IF(AND(P72="N/A",Q72="N/A"),"N/A",IF(OR(P72="",Q72=""),"",SMALL(P72:Q72,1))) -> 0 | P72: 0 | Q72: N/A | R72: =IF(OR(L72="",O72=""),"",IF(AND(L72="N/A",O72="N/A"),"N/A",AVERAGE(L72,O72))) -> 0
A73: 7_2_45_158 | B73: GESTIÓN DE LA SEGURIDAD OPERACIONAL | C73: 14.3 | D73: Gestión de la evaluación del PDV | E73: No | F73: 1 | G73: Propósito: el propósito de nuestro proceso de evaluación de PDV es revisar los lugares que servimos e identificar los riesgos a los que nuestros equipos se enfrentan en estas instalaciones. Una vez que identificamos los riesgos en nuestros PDV, debemos implementar controles que eliminen esos riesgos. Cuando eso no sea posible, debemos dejar de prestar servicios a esas cuentas. Las evaluaciones dePDV no necesitan completarse anualmente en cada cuenta, sino que los equipos deben trabajar hacia tener evaluado el 100% de sus cuentas, y una vez hecho esto, actualizar esas evaluaciones de manera continua. | H73: R14.3.1 - Proceso establecido para evaluar los PDV R14.3.2 - Lista priorizada de PDV con los riesgos más altos disponible. R14.3.3 - Controles implementados para mitigar los riesgos identificados. | I73: 5 - Proceso establecido para evaluar los PDVy lista priorizada de PDV con los mayores peligros disponible, más del 75% de los PDV auditados y acciones cerradas para mitigar los peligros. 3 - Proceso establecido para evaluar PDV y acciones cerradas para mitigar peligros, pero entre el 50% y el 75% de los PDVauditados o tener la evaluación de PDV. 1 - Proceso establecido para evaluar PDV, pero no hay un enfoque sistemático para priorizar PDV, o acciones para mitigar peligros, menos del 25% de los PDVauditados 0 - No hay un proceso establecido para evaluar PDV, o menos del 25% de los PDV auditados, o no hay acciones para mitigar peligros, o tener la evaluación de PDV. | J73: 1. Verificar si hay un proceso establecido para evaluar y revisar los PDV 2. Verificar si los PDV se están evaluando en busca de peligros y si se están priorizando según los peligros identificados y/o los incidentes reales que han ocurrido. 3. Verificar si se han definido acciones y se están rastreando para mitigar los peligros identificados. | L73: =IF(AND(M73="N/A",N73="N/A"),"N/A",IF(OR(M73="",N73=""),"",SMALL(M73:N73,1))) -> 0 | M73: 0 | N73: N/A | O73: =IF(AND(P73="N/A",Q73="N/A"),"N/A",IF(OR(P73="",Q73=""),"",SMALL(P73:Q73,1))) -> 0 | P73: 0 | Q73: N/A | R73: =IF(OR(L73="",O73=""),"",IF(AND(L73="N/A",O73="N/A"),"N/A",AVERAGE(L73,O73))) -> 0
A74: 7_2_45_159 | B74: GESTIÓN DE LA SEGURIDAD OPERACIONAL | C74: 14.4 | D74: Gestión de elementos de protección personal | E74: No | F74: 1 | G74: Propósito: el equipo de protección personal es la última línea de defensa en la jerarquía de controles. Por lo tanto, es crucial no depender excesivamente del uso de EPP como el único método para controlar el riesgo y, cuando sea necesario utilizar EPP, identificarlo adecuadamente y gestionarlo de manera efectiva para garantizar su uso adecuado. | H74: R14.4.1 - Reglas claras para el uso de EPP en todas las actividades y áreas basadas en la evaluación de riesgos de la unidad. R14.4.2 - Señalización adecuada para todas las tareas y áreas. R14.4.3 – Revisión anual del EPP completada”. | I74: 5 - Se cumplen todos los requisitos_x000D_ _x000D_ 3 - Se cumplen R14.4.1 Y R14.4.3 PERO no se cumple R14.4.2_x000D_ _x000D_ 1 - Se cumple R14.4.1 PERO no se cumple R14.4.3_x000D_ _x000D_ 0 - R14.4.1 no se cumple | J74: 1.-Verifique si existen reglas claras, basadas en la evaluación de riesgos de la instalación, para el uso de EPP. 2.-Verifique si hay señalización adecuada para todos los requisitos de EPP publicados para las tareas y áreas. 3.-Verifique si se ha realizado una revisión anual. La revisión debe tener fecha dentro del año actual o un máximo de 13 meses en relación con la revisión anterior. | L74: =IF(AND(M74="N/A",N74="N/A"),"N/A",IF(OR(M74="",N74=""),"",SMALL(M74:N74,1))) -> 0 | M74: 0 | N74: N/A | O74: =IF(AND(P74="N/A",Q74="N/A"),"N/A",IF(OR(P74="",Q74=""),"",SMALL(P74:Q74,1))) -> 0 | P74: 0 | Q74: N/A | R74: =IF(OR(L74="",O74=""),"",IF(AND(L74="N/A",O74="N/A"),"N/A",AVERAGE(L74,O74))) -> 0
A75: 7_2_45_160 | B75: GESTIÓN DE LA SEGURIDAD OPERACIONAL | C75: 14.5 | D75: Rutina de seguridad MCRS | E75: No | F75: 1 | G75: Propósito: el sitio debe llevar a cabo una revisión periódica para analizar su desempeño en seguridad y determinar en qué se enfocarán para mejorar dicho desempeño. Esta revisión periódica debe ser más que simplemente discutir el incidente de seguridad más reciente que haya ocurrido. En lugar de eso, la revisión debe centrarse en las tendencias del sitio y en lo que están haciendo para impactar en este desempeño. El MCRS - Rutina de liderazgo puede incorporarse a una rutina existente o ejecutarse de manera independiente, pero debe incluir los temas establecidos en los requisitos como MÍNIMO. | H75: R14.5.1 - El sitio cubre AL MENOS los siguientes temas para impulsar la mejora:(1. Gestión en incidentes y SIF; 2. Tendencias y logros en el monitoreo y coaching de seguridad; 3. jornada laboral; 4. Resultados de telemetría). R14.5.2 - Se tienen planes de acción para abordar tendencias negativas o el no logro de objetivos. R14.5.3 - Se identifican e implementan necesidades específicas del sitio." | I75: 5 - Todos los requisitos cumplidos Y tendencia de KPI/PI mejorando. 3 - Todos los requisitos cumplidos PERO la tendencia de KPI/PI no mejora. R14.5.1 cumplido PERO R14.5.2 no cumplido. 1 - R14.5.1 cumplido PERO R14.5.2 no cumplido. 0 - R14.5.1 no cumplido. Rutina no implementada. | J75: 1.-Revisar los Términos de Referencia (TORs) de las reuniones de gestión y validar si se abordan los elementos de seguridad requeridos y si los temas necesarios están cubiertos en las revisiones de rutinas de liderazgo . 2.-Verificar las acciones que el sitio está tomando para mejorar las tendencias o abordar fallas en el logro de objetivos. 3.-Comprobar si se han identificado y aplicado las necesidades específicas del sitio. | L75: =IF(AND(M75="N/A",N75="N/A"),"N/A",IF(OR(M75="",N75=""),"",SMALL(M75:N75,1))) -> 0 | M75: 0 | N75: N/A | O75: =IF(AND(P75="N/A",Q75="N/A"),"N/A",IF(OR(P75="",Q75=""),"",SMALL(P75:Q75,1))) -> 0 | P75: 0 | Q75: N/A | R75: =IF(OR(L75="",O75=""),"",IF(AND(L75="N/A",O75="N/A"),"N/A",AVERAGE(L75,O75))) -> 0
B76: GESTIÓN DEL TRABAJO NO ESTÁNDAR | L76: =IF(COUNTIF(L77:L80,"=N/A")=4,"N/A", ((N(L77)*$F77)+(N(L78)*$F78)+(N(L79)*$F79)+(N(L80)*$F80))/(IF(L77="N/A",0,(5*$F77))+IF(L78="N/A",0,(5*$F78))+IF(L79="N/A",0,(5*$F79))+IF(L80="N/A",0,(5*$F80)))) -> 0 | M76: =IF(COUNTIF(M77:M80,"=N/A")=4,"N/A", ((N(M77)*$F77)+(N(M78)*$F78)+(N(M79)*$F79)+(N(M80)*$F80))/(IF(M77="N/A",0,(5*$F77))+IF(M78="N/A",0,(5*$F78))+IF(M79="N/A",0,(5*$F79))+IF(M80="N/A",0,(5*$F80)))) -> 0 | N76: =IF(COUNTIF(N77:N80,"=N/A")=4,"N/A", ((N(N77)*$F77)+(N(N78)*$F78)+(N(N79)*$F79)+(N(N80)*$F80))/(IF(N77="N/A",0,(5*$F77))+IF(N78="N/A",0,(5*$F78))+IF(N79="N/A",0,(5*$F79))+IF(N80="N/A",0,(5*$F80)))) -> N/A | O76: =IF(COUNTIF(O77:O80,"=N/A")=4,"N/A", ((N(O77)*$F77)+(N(O78)*$F78)+(N(O79)*$F79)+(N(O80)*$F80))/(IF(O77="N/A",0,(5*$F77))+IF(O78="N/A",0,(5*$F78))+IF(O79="N/A",0,(5*$F79))+IF(O80="N/A",0,(5*$F80)))) -> 0 | P76: =IF(COUNTIF(P77:P80,"=N/A")=4,"N/A", ((N(P77)*$F77)+(N(P78)*$F78)+(N(P79)*$F79)+(N(P80)*$F80))/(IF(P77="N/A",0,(5*$F77))+IF(P78="N/A",0,(5*$F78))+IF(P79="N/A",0,(5*$F79))+IF(P80="N/A",0,(5*$F80)))) -> 0 | Q76: =IF(COUNTIF(Q77:Q80,"=N/A")=4,"N/A", ((N(Q77)*$F77)+(N(Q78)*$F78)+(N(Q79)*$F79)+(N(Q80)*$F80))/(IF(Q77="N/A",0,(5*$F77))+IF(Q78="N/A",0,(5*$F78))+IF(Q79="N/A",0,(5*$F79))+IF(Q80="N/A",0,(5*$F80)))) -> N/A | R76: =IF(COUNTIF(R77:R80,"=N/A")=4,"N/A", ((N(R77)*$F77)+(N(R78)*$F78)+(N(R79)*$F79)+(N(R80)*$F80))/(IF(R77="N/A",0,(5*$F77))+IF(R78="N/A",0,(5*$F78))+IF(R79="N/A",0,(5*$F79))+IF(R80="N/A",0,(5*$F80)))) -> 0
A77: 7_2_46_161 | B77: GESTIÓN DEL TRABAJO NO ESTÁNDAR | C77: 15.1 | D77: Gestión de inducción de visitantes | E77: SÍ | F77: 1 | G77: El propósito de la incorporación de visitantes es garantizar que nadie pueda entrar en nuestras instalaciones sin un conocimiento básico de nuestras normas de seguridad, así como una comprensión de qué tipo de acciones requerirían que recibieran una formación más detallada antes de proceder. Diseñe el proceso de integración de visitantes para que tenga el mayor impacto. Considere una solución de software que permita a las personas revisar la formación antes de entrar en las instalaciones. Considere la posibilidad de crear un vídeo de integración en lugar de un powerpoint para que la gente se implique más. | H77: R15.1.1 - Proceso de integración de visitantes establecido para todos los visitantes y el personal. R15.1.2 - 100% de los visitantes/empleados formados en el proceso antes de la entrada. R15.1.3 - Registro/documentación de entrada de visitantes disponible. | I77: 5 - Todos los requisitos se cumplieron 3 - R15.1.1 y R15.1.2 pero R15.1.3 no se cumplió 1 - R15.1.1 se cumplió pero R15.1.2 no se cumplió 0 - R15.1.1 no se cumplió | J77: 1. Revisar el proceso de registro e incorporación de visitantes. Compruebe que existe un proceso de integración para todos los visitantes antes de su entrada. 2. Compruebe que todos los visitantes han completado la formación sobre el proceso de incorporación. 3. Verificar que se dispone de registro/documentación de entrada de visitantes. | L77: =IF(AND(M77="N/A",N77="N/A"),"N/A",IF(OR(M77="",N77=""),"",SMALL(M77:N77,1))) -> 0 | M77: 0 | N77: N/A | O77: =IF(AND(P77="N/A",Q77="N/A"),"N/A",IF(OR(P77="",Q77=""),"",SMALL(P77:Q77,1))) -> 0 | P77: 0 | Q77: N/A | R77: =IF(OR(L77="",O77=""),"",IF(AND(L77="N/A",O77="N/A"),"N/A",AVERAGE(L77,O77))) -> 0
A78: 7_2_46_162 | B78: GESTIÓN DEL TRABAJO NO ESTÁNDAR | C78: 15.2 | D78: Gestión de inducción de contratistas | E78: No | F78: 1 | G78: El propósito del proceso de incorporación de contratistas es garantizar que los contratistas que vayan a realizar trabajos para nosotros comprendan nuestro programa de seguridad más a fondo que nuestros visitantes. La incorporación del contratista debe preparar a las personas que van a realizar el trabajo, qué programas cubren ese trabajo y cuáles lo permiten. | H78: R15.2.1 - Proceso de integración de contratistas establecido para todos y que cubra todos los riesgos del área. R15.2.2 - El 100% de los contratistas reciben formación antes de entrar en la empresa. R15.2.3 - Documento de presentación del contratista disponible. | I78: 5 - Todos los requisitos se cumplieron 3 - R15.2.1 y R15.2.2 pero R15.2.3 no se cumplió 1 - R15.2.1 se cumplió pero R15.2.2 no se cumplió 0 - R15.2.1 no se cumplió | J78: 1. Revisar la documentación de incorporación de contratistas y compararla con los proyectos de la unidad. Comprobar que existe un proceso de incorporación de contratistas que cubre todos los riesgos del área. 2. Compruebe que todos los contratistas han completado la formación inicial. 3. Comprobar que se dispone de la documentación de incorporación de cada contratista identificado en la declaración de método. 4. Comprueba que la formación es lo suficientemente detallada como para abarcar todos los riesgos de la zona y los controles de seguridad. | L78: =IF(AND(M78="N/A",N78="N/A"),"N/A",IF(OR(M78="",N78=""),"",SMALL(M78:N78,1))) -> 0 | M78: 0 | N78: N/A | O78: =IF(AND(P78="N/A",Q78="N/A"),"N/A",IF(OR(P78="",Q78=""),"",SMALL(P78:Q78,1))) -> 0 | P78: 0 | Q78: N/A | R78: =IF(OR(L78="",O78=""),"",IF(AND(L78="N/A",O78="N/A"),"N/A",AVERAGE(L78,O78))) -> 0
A79: 7_2_46_163 | B79: GESTIÓN DEL TRABAJO NO ESTÁNDAR | C79: 15.3 | D79: Gestión de grandes obras | E79: No | F79: 1 | G79: Propósito: Los programas de seguridad y las declaraciones de método son necesarios para las obras importantes. Se considerarán obras importantes las que se realicen en más de 2 días o las que requieran más de 2 tipos de permisos. Se utiliza un plan de seguridad para abordar obras complejas, normalmente para ampliar el almacén o poner un tejado nuevo. Los planes de seguridad deben ser revisados. | H79: R15.3.1 - Programa de seguridad disponible para todos los grandes proyectos. R15.3.2 - programas de seguridad revisadas y aprobadas por la persona competente en la unidad. R15.3.3 - Las declaraciones de métodos de seguridad son un documento escrito. (programas de seguridad) | I79: 5 - Se cumplen todos los requisitos 0 - No se cumple ningún requisito | J79: 1. Revisar los proyectos recientes y la documentación relacionada: comprobar que se dispone de una declaración de método de seguridad para todos los proyectos importantes que defina las formas de seguridad laboral específicamente relacionadas con el tipo de trabajo que se está realizando. 2. Compruebe que ha sido revisado y aprobado por la persona competente de la unidad. 3. Comprueba que es un documento escrito. | L79: =IF(AND(M79="N/A",N79="N/A"),"N/A",IF(OR(M79="",N79=""),"",SMALL(M79:N79,1))) -> 0 | M79: 0 | N79: N/A | O79: =IF(AND(P79="N/A",Q79="N/A"),"N/A",IF(OR(P79="",Q79=""),"",SMALL(P79:Q79,1))) -> 0 | P79: 0 | Q79: N/A | R79: =IF(OR(L79="",O79=""),"",IF(AND(L79="N/A",O79="N/A"),"N/A",AVERAGE(L79,O79))) -> 0
A80: 7_2_46_164 | B80: GESTIÓN DEL TRABAJO NO ESTÁNDAR | C80: 15.4 | D80: Gestión de permisos de trabajo | E80: SÍ | F80: 1 | G80: Propósito: Los permisos de trabajo son nuestro método de control de los trabajos atípicos en nuestras obras. Todo el trabajo estándar se rige por Procedimientos Operativos Estándar, y el cumplimiento de estos procedimientos se valida a través de nuestros OWD y rutinas de formación. El trabajo no estándar no tiene un SOP que guíe a la persona que lo realiza, por lo que el permiso de trabajo es la herramienta que utilizamos para garantizar que se comprenden y tienen en cuenta los riesgos y que el trabajo se realiza como esperamos. | H80: R15.4.1 - La unidad ha implementado todos los permisos requeridos por los protocolos. R15.4.2 - Permisos de trabajo disponibles y completados 100% para todas las obras requeridas. R15.4.3 - Permisos de trabajo firmados por persona autorizada para garantizar la exactitud de los controles definidos. R15.4.4 - La lista de personas autorizadas está disponible. R15.4.5 - Existe formación para empleados, contratistas y lideres sobre el proceso de permisos de trabajo. R15.4.6 - Los directivos reciben formación sobre cómo expedir un permiso de trabajo. | I80: 5 - Se cumplen todos los requisitos. 3 - Se cumplen todos los requisitos pero 1 permiso seleccionado tiene campos incompletos. 1 - Se cumplen todos los requisitos pero 2-3 permisos seleccionados tienen campos incompletos. 0 - No se cumple ningún requisito o >3 permisos seleccionados con campos incompletos. | J80: 1. Revise los permisos de trabajo relacionados con todos los trabajos que requieren una autorización (consulte los protocolos) y compruebe que la unidad la ha implementado._x000D_ 2. Compruebe que se dispone de los permisos de trabajo necesarios para todas las obras._x000D_ 3. Comprobar que los permisos de trabajo están firmados por la persona autorizada, con una verificación final antes del trabajo para garantizar la exactitud de los controles definidos._x000D_ 4. Compruebe que dispone de una lista de personas autorizadas._x000D_ 5. Compruebe que existe formación para empleados, contratistas y lideres sobre el proceso de obtención de permisos de trabajo._x000D_ 6. Comprueba que los autorizados están formados para expedir un permiso de trabajo. | L80: =IF(AND(M80="N/A",N80="N/A"),"N/A",IF(OR(M80="",N80=""),"",SMALL(M80:N80,1))) -> 0 | M80: 0 | N80: N/A | O80: =IF(AND(P80="N/A",Q80="N/A"),"N/A",IF(OR(P80="",Q80=""),"",SMALL(P80:Q80,1))) -> 0 | P80: 0 | Q80: N/A | R80: =IF(OR(L80="",O80=""),"",IF(AND(L80="N/A",O80="N/A"),"N/A",AVERAGE(L80,O80))) -> 0
B81: GESTIÓN PARA MEJORAR | L81: =IF(COUNTBLANK(L82:L87)>0,"-", IF(L82="N/A","N/A", (N(L83)*$F83+ N(L84)*$F84+ N(L85)*$F85+ N(L86)*$F86+ N(L87)*$F87) / (IF(L83="N/A",0,$F83*5)+ IF(L84="N/A",0,$F84*5)+ IF(L85="N/A",0,$F85*5)+ IF(L86="N/A",0,$F86*5)+ IF(L87="N/A",0,$F87*5)))) -> 0 | M81: =IF(COUNTBLANK(M82:M87)>0,"-", IF(M82="N/A","N/A", (N(M83)*$F83+ N(M84)*$F84+ N(M85)*$F85+ N(M86)*$F86+ N(M87)*$F87) / (IF(M83="N/A",0,$F83*5)+ IF(M84="N/A",0,$F84*5)+ IF(M85="N/A",0,$F85*5)+ IF(M86="N/A",0,$F86*5)+ IF(M87="N/A",0,$F87*5)))) -> 0 | N81: =IF(COUNTBLANK(N82:N87)>0,"-", IF(N82="N/A","N/A", (N(N83)*$F83+ N(N84)*$F84+ N(N85)*$F85+ N(N86)*$F86+ N(N87)*$F87) / (IF(N83="N/A",0,$F83*5)+ IF(N84="N/A",0,$F84*5)+ IF(N85="N/A",0,$F85*5)+ IF(N86="N/A",0,$F86*5)+ IF(N87="N/A",0,$F87*5)))) -> N/A | O81: =IF(COUNTBLANK(O82:O87)>0,"-", IF(O82="N/A","N/A", (N(O83)*$F83+ N(O84)*$F84+ N(O85)*$F85+ N(O86)*$F86+ N(O87)*$F87) / (IF(O83="N/A",0,$F83*5)+ IF(O84="N/A",0,$F84*5)+ IF(O85="N/A",0,$F85*5)+ IF(O86="N/A",0,$F86*5)+ IF(O87="N/A",0,$F87*5)))) -> 0 | P81: =IF(COUNTBLANK(P82:P87)>0,"-", IF(P82="N/A","N/A", (N(P83)*$F83+ N(P84)*$F84+ N(P85)*$F85+ N(P86)*$F86+ N(P87)*$F87) / (IF(P83="N/A",0,$F83*5)+ IF(P84="N/A",0,$F84*5)+ IF(P85="N/A",0,$F85*5)+ IF(P86="N/A",0,$F86*5)+ IF(P87="N/A",0,$F87*5)))) -> 0 | Q81: =IF(COUNTBLANK(Q82:Q87)>0,"-", IF(Q82="N/A","N/A", (N(Q83)*$F83+ N(Q84)*$F84+ N(Q85)*$F85+ N(Q86)*$F86+ N(Q87)*$F87) / (IF(Q83="N/A",0,$F83*5)+ IF(Q84="N/A",0,$F84*5)+ IF(Q85="N/A",0,$F85*5)+ IF(Q86="N/A",0,$F86*5)+ IF(Q87="N/A",0,$F87*5)))) -> N/A | R81: =IF(COUNTBLANK(R82:R87)>0,"-", IF(R82="N/A","N/A", (N(R83)*$F83+ N(R84)*$F84+ N(R85)*$F85+ N(R86)*$F86+ N(R87)*$F87) / (IF(R83="N/A",0,$F83*5)+ IF(R84="N/A",0,$F84*5)+ IF(R85="N/A",0,$F85*5)+ IF(R86="N/A",0,$F86*5)+ IF(R87="N/A",0,$F87*5)))) -> 0
B82: GESTIÓN DEL COMPORTAMIENTO | L82: =IF(COUNTIF(L83:L87,"=N/A")=5,"N/A", ((N(L83)*$F83)+(N(L84)*$F84)+(N(L85)*$F85)+(N(L86)*$F86)+(N(L87)*$F87))/(IF(L83="N/A",0,(5*$F83))+IF(L84="N/A",0,(5*$F84))+IF(L85="N/A",0,(5*$F85))+IF(L86="N/A",0,(5*$F86))+IF(L87="N/A",0,(5*$F87)))) -> 0 | M82: =IF(COUNTIF(M83:M87,"=N/A")=5,"N/A", ((N(M83)*$F83)+(N(M84)*$F84)+(N(M85)*$F85)+(N(M86)*$F86)+(N(M87)*$F87))/(IF(M83="N/A",0,(5*$F83))+IF(M84="N/A",0,(5*$F84))+IF(M85="N/A",0,(5*$F85))+IF(M86="N/A",0,(5*$F86))+IF(M87="N/A",0,(5*$F87)))) -> 0 | N82: =IF(COUNTIF(N83:N87,"=N/A")=5,"N/A", ((N(N83)*$F83)+(N(N84)*$F84)+(N(N85)*$F85)+(N(N86)*$F86)+(N(N87)*$F87))/(IF(N83="N/A",0,(5*$F83))+IF(N84="N/A",0,(5*$F84))+IF(N85="N/A",0,(5*$F85))+IF(N86="N/A",0,(5*$F86))+IF(N87="N/A",0,(5*$F87)))) -> N/A | O82: =IF(COUNTIF(O83:O87,"=N/A")=5,"N/A", ((N(O83)*$F83)+(N(O84)*$F84)+(N(O85)*$F85)+(N(O86)*$F86)+(N(O87)*$F87))/(IF(O83="N/A",0,(5*$F83))+IF(O84="N/A",0,(5*$F84))+IF(O85="N/A",0,(5*$F85))+IF(O86="N/A",0,(5*$F86))+IF(O87="N/A",0,(5*$F87)))) -> 0 | P82: =IF(COUNTIF(P83:P87,"=N/A")=5,"N/A", ((N(P83)*$F83)+(N(P84)*$F84)+(N(P85)*$F85)+(N(P86)*$F86)+(N(P87)*$F87))/(IF(P83="N/A",0,(5*$F83))+IF(P84="N/A",0,(5*$F84))+IF(P85="N/A",0,(5*$F85))+IF(P86="N/A",0,(5*$F86))+IF(P87="N/A",0,(5*$F87)))) -> 0 | Q82: =IF(COUNTIF(Q83:Q87,"=N/A")=5,"N/A", ((N(Q83)*$F83)+(N(Q84)*$F84)+(N(Q85)*$F85)+(N(Q86)*$F86)+(N(Q87)*$F87))/(IF(Q83="N/A",0,(5*$F83))+IF(Q84="N/A",0,(5*$F84))+IF(Q85="N/A",0,(5*$F85))+IF(Q86="N/A",0,(5*$F86))+IF(Q87="N/A",0,(5*$F87)))) -> N/A | R82: =IF(COUNTIF(R83:R87,"=N/A")=5,"N/A", ((N(R83)*$F83)+(N(R84)*$F84)+(N(R85)*$F85)+(N(R86)*$F86)+(N(R87)*$F87))/(IF(R83="N/A",0,(5*$F83))+IF(R84="N/A",0,(5*$F84))+IF(R85="N/A",0,(5*$F85))+IF(R86="N/A",0,(5*$F86))+IF(R87="N/A",0,(5*$F87)))) -> 0
A83: 7_3_47_165 | B83: GESTIÓN DEL COMPORTAMIENTO | C83: 16.1 | D83: Preguntas de seguridad en la encuesta de engagement | E83: No | F83: 1 | G83: Propósito: utilizar las preguntas de la encuesta anual de compromiso para obtener información sobre la cultura de seguridad del centro. El centro debe identificar las acciones relacionadas con las lagunas y hacer un seguimiento de su realización, evaluando su progreso mediante encuestas de pulso. | H83: R16.1.1 H1 Y H2 Según corresponda: - Pregunta de SERVICIOS GENERALES: entorno laboral y seguridad. R16.1.2 - Se mejoran las puntuaciones. R16.1.3 - Plan de acción en marcha seguido hasta su finalización. R16.1.4 - Evaluación/análisis de seguimiento completo, se desarrollan estrategias para abordar problemas de compromiso de mayor envergadura. | I83: 5 - Se cumplen todos los requisitos 3 - R16.1.1 Y R16.1.3 cumplidas PERO R16.1.4 no cumplida 1 - Se cumple R16.1.1 PERO no se cumple R16.1.3 0 - No se cumple R16.1.1 | J83: 1. Compruebe si se analizan las preguntas de encuesta de engagement. 2. Comprobar si mejoran las puntuaciones. 3. Comprobar si existe un plan de acción para mejorar las puntuaciones seguido hasta su finalización. 4. 4. El plan de acción debe incluir una evaluación/análisis de seguimiento completado para abordar problemas de compromiso mayores. | L83: =IF(AND(M83="N/A",N83="N/A"),"N/A",IF(OR(M83="",N83=""),"",SMALL(M83:N83,1))) -> 0 | M83: 0 | N83: N/A | O83: =IF(AND(P83="N/A",Q83="N/A"),"N/A",IF(OR(P83="",Q83=""),"",SMALL(P83:Q83,1))) -> 0 | P83: 0 | Q83: N/A | R83: =IF(OR(L83="",O83=""),"",IF(AND(L83="N/A",O83="N/A"),"N/A",AVERAGE(L83,O83))) -> 0
A84: 7_3_47_166 | B84: GESTIÓN DEL COMPORTAMIENTO | C84: 16.2 | D84: Liderazgo en seguridad conductual | E84: No | F84: 1 | G84: Propósito: garantizar que los líderes de todos los niveles de la organización dispongan de la formación, las competencias y los objetivos necesarios para influir en la seguridad de sus instalaciones. A la hora de seleccionar los objetivos en los que debe centrarse el equipo de gestión, el centro debe evaluar su rendimiento en materia de seguridad y seleccionar las acciones que repercutan en esas deficiencias de rendimiento. Por ejemplo, si el centro observa que ha notificado más incidentes de SIF Potencial que de SIF Precursor, podría asignar un objetivo de formación centrado en los comportamientos de SIF Precursor. | H84: R16.2.1 - Objetivos de desempeño de cultura de seguridad definidos y seguidos por el equipo liderazgo. R16.2.2 - Formación OLT/ completada al 100%. R16.2.3 - Plan de acción para completar la formación OLT/ con los nuevos directivos. R16.2.4 - Disponer de al menos un empleado formado como formador de OLT | I84: 5 - Se cumplen todos los requisitos 3 - Se cumplen R16.2.1 Y R16.2.2 PERO NO SE CUMPLE R16.2.3 1 - Se cumple R16.2.2 PERO no se cumple R16.2.1 0 - No se cumple R16.2.1 | J84: 1. Revise los objetivos de gestión: Compruebe si el equipo directivo tiene establecidos objetivos de rendimiento en materia de seguridad. 2. Comprobar si han completado la formación OLT. 3. Comprobar si existe un plan de acción para completar la formación OLT con los nuevos directivos. 4. El punto 16.2.4 debe evaluarse a partir de julio de 2024. | L84: =IF(AND(M84="N/A",N84="N/A"),"N/A",IF(OR(M84="",N84=""),"",SMALL(M84:N84,1))) -> 0 | M84: 0 | N84: N/A | O84: =IF(AND(P84="N/A",Q84="N/A"),"N/A",IF(OR(P84="",Q84=""),"",SMALL(P84:Q84,1))) -> 0 | P84: 0 | Q84: N/A | R84: =IF(OR(L84="",O84=""),"",IF(AND(L84="N/A",O84="N/A"),"N/A",AVERAGE(L84,O84))) -> 0
